Workbook

Sheet WBS Tracker
A1: Project | B1: Module | C1: Sub-Module | D1: Page / Functionality Check | E1: Scope of Check | F1: Estimation Rationale | G1: Estimated Hours | H1: Actual Hours | I1: Date Worked | J1: Status | K1: Variance (h) | L1: Remarks
A2: Progbiz ERP | B2: HRMS | C2: Core HR | D2: Employee listing (/employees) | E2: List load, Filter panel, incl-archived toggle, columns (Code/Name/Dept/Designation/Status), row actions, drill-down | F2: List + filter matrix; grid starts empty until filtered | G2: 3 | J2: Pending | K2: =G2-H2 -> 3
A3: Progbiz ERP | B3: HRMS | C3: Core HR | D3: Employee create / edit form | E3: New Employee form: personal, branch/department/designation, contact, joining, mandatory-field negatives, save/cancel | F3: Largest master form in the module; full field matrix + negative paths | G3: 4 | J3: Pending | K3: =G3-H3 -> 4
A4: Progbiz ERP | B4: HRMS | C4: Core HR | D4: Sections (/sections) | E4: Department-linked section create, inline form + grid, edit, delete, duplicate rejection | F4: Simple inline-form CRUD master | G4: 1.5 | J4: Pending | K4: =G4-H4 -> 1.5
A5: Progbiz ERP | B5: HRMS | C5: Core HR | D5: Worker Directory (/worker-directory) | E5: Cards view, Org Chart view, department filter, name/designation search | F5: Two non-grid visualisations; org chart needs hierarchy data | G5: 2.5 | J5: Pending | K5: =G5-H5 -> 2.5
A6: Progbiz ERP | B6: HRMS | C6: Core HR | D6: Salary Revisions (/salary-revisions) | E6: Raise Revision form (employee, effective date, new salary, reason), revision history grid, %-change, approval status | F6: Form + history + routes into the approval chain | G6: 3 | J6: Pending | K6: =G6-H6 -> 3
A7: Progbiz ERP | B7: HRMS | C7: Core HR | D7: Employee Salary Process (/employee-salary-process) | E7: Branch selection, staff list, Basic/leave/payable computation, narration fields, save | F7: Arithmetic verification per employee; consumes attendance + deductions | G7: 3.5 | J7: Pending | K7: =G7-H7 -> 3.5
A8: Progbiz ERP | B8: HRMS | C8: Core HR | D8: Employee Deductions (/employee-deduction) | E8: Branch/staff/date/deduction-type typeahead/amount/details, save, Cancel discards | F8: Duplicate element ids (#employee x2) + swal2 validation dialog | G8: 2.5 | J8: Pending | K8: =G8-H8 -> 2.5
A9: Progbiz ERP | B9: HRMS | C9: Core HR | D9: Employee Remarks (/employee-remark) | E9: Reduced form (branch/employee/date/details), save, cancel | F9: Small form; header falsely reads 'Employee Deduction' (build bug to log) | G9: 1.5 | J9: Pending | K9: =G9-H9 -> 1.5
A10: Progbiz ERP | B10: HRMS | C10: Core HR | D10: Probation Dashboard (/hrms/probation) | E10: Employees-on-probation grid, Start Probation, review checkpoints, days-left, decision actions | F10: State-dependent; needs employees seeded on probation | G10: 3 | J10: Pending | K10: =G10-H10 -> 3
A11: Progbiz ERP | B11: HRMS | C11: Core HR | D11: Probation Templates (/hrms/probation-templates) | E11: New Template (duration, checkpoint days, criteria), default/active flags, edit, delete | F11: CRUD master feeding the probation flow | G11: 2 | J11: Pending | K11: =G11-H11 -> 2
A12: Progbiz ERP | B12: HRMS | C12: Core HR | D12: Probation Report (/hrms/probation-report) | E12: Date-range + outcome filter, Run Report, Export Excel, overdue/decision columns | F12: Filter-first report; export not downloaded, only triggered | G12: 2 | J12: Pending | K12: =G12-H12 -> 2
A13: Progbiz ERP | B13: HRMS | C13: Core HR | D13: Resigned Employees (/resigned-employees) | E13: List, name filter, columns (date/name/phone/designation/nationality) | F13: Read-only list | G13: 1 | J13: Pending | K13: =G13-H13 -> 1
... A84: Progbiz ERP | B84: HRMS | C84: Cross-Cutting | D84: Defect logging & retest | E84: Log build bugs found (remark header, 'Add Vist Report' typo, upload-employee stray card title), retest after fixes | F84: Known issues already observed during the study | G84: 2.5 | J84: Pending | K84: =G84-H84 -> 2.5
F85: TOTAL | G85: =SUM(G2:G84) -> 217 | H85: =SUM(H2:H84) -> 0

Sheet Daily Hours Log
A1: Date | B1: Module | C1: Sub-Module | D1: Hours Spent | E1: What was done | F1: Status Update

Sheet Dashboard
A1: WBS DASHBOARD — HRMS (Core HR · Recruitment · Attendance · Leave · ESS)
A3: By Sub-Module
A4: Sub-Module | B4: Checks | C4: Completed | D4: Pending/In-Prog | E4: Est Hours | F4: Actual Hours | G4: Variance (h) | H4: % Complete
A5: Core HR | B5: =COUNTIF('WBS Tracker'!C:C,A5) -> 18 | C5: =COUNTIFS('WBS Tracker'!C:C,A5,'WBS Tracker'!J:J,"Completed") -> 0 | D5: =B5-C5 -> 18 | E5: =SUMIF('WBS Tracker'!C:C,A5,'WBS Tracker'!G:G) -> 46.5 | F5: =SUMIF('WBS Tracker'!C:C,A5,'WBS Tracker'!H:H) -> 0 | G5: =E5-F5 -> 46.5 | H5: =IF(B5=0,0,C5/B5) -> 0
A6: Recruitment & Onboarding | B6: =COUNTIF('WBS Tracker'!C:C,A6) -> 15 | C6: =COUNTIFS('WBS Tracker'!C:C,A6,'WBS Tracker'!J:J,"Completed") -> 0 | D6: =B6-C6 -> 15 | E6: =SUMIF('WBS Tracker'!C:C,A6,'WBS Tracker'!G:G) -> 38.5 | F6: =SUMIF('WBS Tracker'!C:C,A6,'WBS Tracker'!H:H) -> 0 | G6: =E6-F6 -> 38.5 | H6: =IF(B6=0,0,C6/B6) -> 0
A7: Attendance & Time | B7: =COUNTIF('WBS Tracker'!C:C,A7) -> 13 | C7: =COUNTIFS('WBS Tracker'!C:C,A7,'WBS Tracker'!J:J,"Completed") -> 0 | D7: =B7-C7 -> 13 | E7: =SUMIF('WBS Tracker'!C:C,A7,'WBS Tracker'!G:G) -> 39.5 | F7: =SUMIF('WBS Tracker'!C:C,A7,'WBS Tracker'!H:H) -> 0 | G7: =E7-F7 -> 39.5 | H7: =IF(B7=0,0,C7/B7) -> 0
A8: Leave Management | B8: =COUNTIF('WBS Tracker'!C:C,A8) -> 21 | C8: =COUNTIFS('WBS Tracker'!C:C,A8,'WBS Tracker'!J:J,"Completed") -> 0 | D8: =B8-C8 -> 21 | E8: =SUMIF('WBS Tracker'!C:C,A8,'WBS Tracker'!G:G) -> 52 | F8: =SUMIF('WBS Tracker'!C:C,A8,'WBS Tracker'!H:H) -> 0 | G8: =E8-F8 -> 52 | H8: =IF(B8=0,0,C8/B8) -> 0
A9: My Workspace (ESS) | B9: =COUNTIF('WBS Tracker'!C:C,A9) -> 11 | C9: =COUNTIFS('WBS Tracker'!C:C,A9,'WBS Tracker'!J:J,"Completed") -> 0 | D9: =B9-C9 -> 11 | E9: =SUMIF('WBS Tracker'!C:C,A9,'WBS Tracker'!G:G) -> 26.5 | F9: =SUMIF('WBS Tracker'!C:C,A9,'WBS Tracker'!H:H) -> 0 | G9: =E9-F9 -> 26.5 | H9: =IF(B9=0,0,C9/B9) -> 0
A10: Cross-Cutting | B10: =COUNTIF('WBS Tracker'!C:C,A10) -> 5 | C10: =COUNTIFS('WBS Tracker'!C:C,A10,'WBS Tracker'!J:J,"Completed") -> 0 | D10: =B10-C10 -> 5 | E10: =SUMIF('WBS Tracker'!C:C,A10,'WBS Tracker'!G:G) -> 14 | F10: =SUMIF('WBS Tracker'!C:C,A10,'WBS Tracker'!H:H) -> 0 | G10: =E10-F10 -> 14 | H10: =IF(B10=0,0,C10/B10) -> 0
A11: TOTAL | B11: =SUM(B5:B10) -> 83 | C11: =SUM(C5:C10) -> 0 | D11: =SUM(D5:D10) -> 83 | E11: =SUM(E5:E10) -> 217 | F11: =SUM(F5:F10) -> 0 | G11: =SUM(G5:G10) -> 217 | H11: =IF(B11=0,0,C11/B11) -> 0
A13: Daily hours (from Daily Hours Log)
A14: Today's logged hours: | B14: =SUMIF(DailyLogHRMS[Date],TODAY(),DailyLogHRMS[Hours Spent]) -> 0
A15: Total logged hours: | B15: =SUM(DailyLogHRMS[Hours Spent]) -> 0
A18: HOW TO USE (daily routine)
A19: 1. Each day, add a row in 'Daily Hours Log' per sub-module you worked on (Date, Module, Sub-Module, Hours).
A20: 2. Update 'Actual Hours' + 'Date Worked' + 'Status' on the matching WBS Tracker row (add hours cumulatively).
A21: 3. Variance auto-calculates (Estimated - Actual); negative = over-estimate risk, raise early.
A22: 4. Filter the WBS Tracker Status column for Completed vs Pending (it is an Excel Table - use the header filters).
A23: 5. Pivot: Insert > PivotTable > table 'WBS_HRMS' > Rows: Sub-Module, Page; Values: Sum of Estimated/Actual Hours.
A24: 6. Burndown by day: Insert > PivotTable on table 'DailyLogHRMS' > Rows: Date; Values: Sum of Hours Spent.
A25: 7. Estimates assume the config chain is seeded first (shifts+roster, leave types->pattern->policy->assignment,
A26: holidays, requisition->opening->candidate) - see the 'Test data seeding' row under Cross-Cutting.
