Workbook

Sheet Summary
A1: HRMS — Test Case Report
A3: Application | B3: Progbiz HRMS — https://hrms-test.progbiz.in (company pbhrms)
A4: Scope | B4: All HRMS modules (sidebar), public career page, cross-module journeys, non-functional
A5: Automation suite | B5: Playwright linear run — hrms/tests/00_linear/hrms_linear_run.spec.js (128 pages, one tab)
A6: Last automated run | B6: 19 Oct 2026 — full headed run, 128/128 page checks passed; all actions green after fixes
A7: Report generated | B7: 20 Oct 2026
A10: Module (sheet) | B10: Total | C10: High | D10: Positive | E10: Negative | F10: Automated (Linear Run) | G10: Automated (Page Check) | H10: Not Automated | I10: Blocked | J10: Out of Scope | K10: Passed | L10: % Automated | M10: % Executed
A11: Login & Navigation | B11: =COUNTA('Login & Navigation'!$A$2:$A$92) -> 91 | C11: =COUNTIF('Login & Navigation'!$L$2:$L$92,"High") -> 44 | D11: =COUNTIF('Login & Navigation'!$J$2:$J$92,"Positive") -> 27 | E11: =COUNTIF('Login & Navigation'!$J$2:$J$92,"Negative") -> 11 | F11: =COUNTIF('Login & Navigation'!$M$2:$M$92,"Automated (Linear Run)") -> 4 | G11: =COUNTIF('Login & Navigation'!$M$2:$M$92,"Automated (Page Check)") -> 1 | H11: =COUNTIF('Login & Navigation'!$M$2:$M$92,"Not Automated") -> 84 | I11: =COUNTIF('Login & Navigation'!$M$2:$M$92,"Blocked") -> 2 | J11: =COUNTIF('Login & Navigation'!$M$2:$M$92,"Out of Scope") -> 0 | K11: =COUNTIF('Login & Navigation'!$O$2:$O$92,"Passed*") -> 5 | L11: =IF(B11=0,0,(F11+G11)/B11) -> 0.054945055 | M11: =IF(B11=0,0,K11/B11) -> 0.054945055
A12: Core HR | B12: =COUNTA('Core HR'!$A$2:$A$295) -> 294 | C12: =COUNTIF('Core HR'!$L$2:$L$295,"High") -> 98 | D12: =COUNTIF('Core HR'!$J$2:$J$295,"Positive") -> 105 | E12: =COUNTIF('Core HR'!$J$2:$J$295,"Negative") -> 46 | F12: =COUNTIF('Core HR'!$M$2:$M$295,"Automated (Linear Run)") -> 31 | G12: =COUNTIF('Core HR'!$M$2:$M$295,"Automated (Page Check)") -> 11 | H12: =COUNTIF('Core HR'!$M$2:$M$295,"Not Automated") -> 252 | I12: =COUNTIF('Core HR'!$M$2:$M$295,"Blocked") -> 0 | J12: =COUNTIF('Core HR'!$M$2:$M$295,"Out of Scope") -> 0 | K12: =COUNTIF('Core HR'!$O$2:$O$295,"Passed*") -> 42 | L12: =IF(B12=0,0,(F12+G12)/B12) -> 0.14285714 | M12: =IF(B12=0,0,K12/B12) -> 0.14285714
A13: Recruitment | B13: =COUNTA('Recruitment'!$A$2:$A$341) -> 340 | C13: =COUNTIF('Recruitment'!$L$2:$L$341,"High") -> 101 | D13: =COUNTIF('Recruitment'!$J$2:$J$341,"Positive") -> 120 | E13: =COUNTIF('Recruitment'!$J$2:$J$341,"Negative") -> 38 | F13: =COUNTIF('Recruitment'!$M$2:$M$341,"Automated (Linear Run)") -> 39 | G13: =COUNTIF('Recruitment'!$M$2:$M$341,"Automated (Page Check)") -> 12 | H13: =COUNTIF('Recruitment'!$M$2:$M$341,"Not Automated") -> 283 | I13: =COUNTIF('Recruitment'!$M$2:$M$341,"Blocked") -> 6 | J13: =COUNTIF('Recruitment'!$M$2:$M$341,"Out of Scope") -> 0 | K13: =COUNTIF('Recruitment'!$O$2:$O$341,"Passed*") -> 51 | L13: =IF(B13=0,0,(F13+G13)/B13) -> 0.15 | M13: =IF(B13=0,0,K13/B13) -> 0.15
A14: Referral | B14: =COUNTA('Referral'!$A$2:$A$84) -> 83 | C14: =COUNTIF('Referral'!$L$2:$L$84,"High") -> 25 | D14: =COUNTIF('Referral'!$J$2:$J$84,"Positive") -> 24 | E14: =COUNTIF('Referral'!$J$2:$J$84,"Negative") -> 13 | F14: =COUNTIF('Referral'!$M$2:$M$84,"Automated (Linear Run)") -> 13 | G14: =COUNTIF('Referral'!$M$2:$M$84,"Automated (Page Check)") -> 3 | H14: =COUNTIF('Referral'!$M$2:$M$84,"Not Automated") -> 55 | I14: =COUNTIF('Referral'!$M$2:$M$84,"Blocked") -> 0 | J14: =COUNTIF('Referral'!$M$2:$M$84,"Out of Scope") -> 12 | K14: =COUNTIF('Referral'!$O$2:$O$84,"Passed*") -> 16 | L14: =IF(B14=0,0,(F14+G14)/B14) -> 0.19277108 | M14: =IF(B14=0,0,K14/B14) -> 0.19277108
A15: Onboarding & Probation | B15: =COUNTA('Onboarding & Probation'!$A$2:$A$239) -> 238 | C15: =COUNTIF('Onboarding & Probation'!$L$2:$L$239,"High") -> 84 | D15: =COUNTIF('Onboarding & Probation'!$J$2:$J$239,"Positive") -> 79 | E15: =COUNTIF('Onboarding & Probation'!$J$2:$J$239,"Negative") -> 37 | F15: =COUNTIF('Onboarding & Probation'!$M$2:$M$239,"Automated (Linear Run)") -> 3 | G15: =COUNTIF('Onboarding & Probation'!$M$2:$M$239,"Automated (Page Check)") -> 15 | H15: =COUNTIF('Onboarding & Probation'!$M$2:$M$239,"Not Automated") -> 202 | I15: =COUNTIF('Onboarding & Probation'!$M$2:$M$239,"Blocked") -> 18 | J15: =COUNTIF('Onboarding & Probation'!$M$2:$M$239,"Out of Scope") -> 0 | K15: =COUNTIF('Onboarding & Probation'!$O$2:$O$239,"Passed*") -> 18 | L15: =IF(B15=0,0,(F15+G15)/B15) -> 0.075630252 | M15: =IF(B15=0,0,K15/B15) -> 0.075630252
A16: Attendance | B16: =COUNTA('Attendance'!$A$2:$A$170) -> 169 | C16: =COUNTIF('Attendance'!$L$2:$L$170,"High") -> 51 | D16: =COUNTIF('Attendance'!$J$2:$J$170,"Positive") -> 55 | E16: =COUNTIF('Attendance'!$J$2:$J$170,"Negative") -> 26 | F16: =COUNTIF('Attendance'!$M$2:$M$170,"Automated (Linear Run)") -> 0 | G16: =COUNTIF('Attendance'!$M$2:$M$170,"Automated (Page Check)") -> 8 | H16: =COUNTIF('Attendance'!$M$2:$M$170,"Not Automated") -> 138 | I16: =COUNTIF('Attendance'!$M$2:$M$170,"Blocked") -> 23 | J16: =COUNTIF('Attendance'!$M$2:$M$170,"Out of Scope") -> 0 | K16: =COUNTIF('Attendance'!$O$2:$O$170,"Passed*") -> 8 | L16: =IF(B16=0,0,(F16+G16)/B16) -> 0.047337278 | M16: =IF(B16=0,0,K16/B16) -> 0.047337278
A17: Leave | B17: =COUNTA('Leave'!$A$2:$A$296) -> 295 | C17: =COUNTIF('Leave'!$L$2:$L$296,"High") -> 84 | D17: =COUNTIF('Leave'!$J$2:$J$296,"Positive") -> 86 | E17: =COUNTIF('Leave'!$J$2:$J$296,"Negative") -> 55 | F17: =COUNTIF('Leave'!$M$2:$M$296,"Automated (Linear Run)") -> 11 | G17: =COUNTIF('Leave'!$M$2:$M$296,"Automated (Page Check)") -> 13 | H17: =COUNTIF('Leave'!$M$2:$M$296,"Not Automated") -> 269 | I17: =COUNTIF('Leave'!$M$2:$M$296,"Blocked") -> 0 | J17: =COUNTIF('Leave'!$M$2:$M$296,"Out of Scope") -> 2 | K17: =COUNTIF('Leave'!$O$2:$O$296,"Passed*") -> 24 | L17: =IF(B17=0,0,(F17+G17)/B17) -> 0.081355932 | M17: =IF(B17=0,0,K17/B17) -> 0.081355932
A18: Payroll | B18: =COUNTA('Payroll'!$A$2:$A$286) -> 285 | C18: =COUNTIF('Payroll'!$L$2:$L$286,"High") -> 120 | D18: =COUNTIF('Payroll'!$J$2:$J$286,"Positive") -> 88 | E18: =COUNTIF('Payroll'!$J$2:$J$286,"Negative") -> 41 | F18: =COUNTIF('Payroll'!$M$2:$M$286,"Automated (Linear Run)") -> 0 | G18: =COUNTIF('Payroll'!$M$2:$M$286,"Automated (Page Check)") -> 30 | H18: =COUNTIF('Payroll'!$M$2:$M$286,"Not Automated") -> 236 | I18: =COUNTIF('Payroll'!$M$2:$M$286,"Blocked") -> 0 | J18: =COUNTIF('Payroll'!$M$2:$M$286,"Out of Scope") -> 19 | K18: =COUNTIF('Payroll'!$O$2:$O$286,"Passed*") -> 30 | L18: =IF(B18=0,0,(F18+G18)/B18) -> 0.10526316 | M18: =IF(B18=0,0,K18/B18) -> 0.10526316
A19: Resignation & Exit | B19: =COUNTA('Resignation & Exit'!$A$2:$A$182) -> 181 | C19: =COUNTIF('Resignation & Exit'!$L$2:$L$182,"High") -> 67 | D19: =COUNTIF('Resignation & Exit'!$J$2:$J$182,"Positive") -> 51 | E19: =COUNTIF('Resignation & Exit'!$J$2:$J$182,"Negative") -> 28 | F19: =COUNTIF('Resignation & Exit'!$M$2:$M$182,"Automated (Linear Run)") -> 0 | G19: =COUNTIF('Resignation & Exit'!$M$2:$M$182,"Automated (Page Check)") -> 15 | H19: =COUNTIF('Resignation & Exit'!$M$2:$M$182,"Not Automated") -> 146 | I19: =COUNTIF('Resignation & Exit'!$M$2:$M$182,"Blocked") -> 1 | J19: =COUNTIF('Resignation & Exit'!$M$2:$M$182,"Out of Scope") -> 19 | K19: =COUNTIF('Resignation & Exit'!$O$2:$O$182,"Passed*") -> 15 | L19: =IF(B19=0,0,(F19+G19)/B19) -> 0.082872928 | M19: =IF(B19=0,0,K19/B19) -> 0.082872928
A20: My Workspace (ESS) | B20: =COUNTA('My Workspace (ESS)'!$A$2:$A$210) -> 209 | C20: =COUNTIF('My Workspace (ESS)'!$L$2:$L$210,"High") -> 96 | D20: =COUNTIF('My Workspace (ESS)'!$J$2:$J$210,"Positive") -> 67 | E20: =COUNTIF('My Workspace (ESS)'!$J$2:$J$210,"Negative") -> 27 | F20: =COUNTIF('My Workspace (ESS)'!$M$2:$M$210,"Automated (Linear Run)") -> 6 | G20: =COUNTIF('My Workspace (ESS)'!$M$2:$M$210,"Automated (Page Check)") -> 22 | H20: =COUNTIF('My Workspace (ESS)'!$M$2:$M$210,"Not Automated") -> 179 | I20: =COUNTIF('My Workspace (ESS)'!$M$2:$M$210,"Blocked") -> 2 | J20: =COUNTIF('My Workspace (ESS)'!$M$2:$M$210,"Out of Scope") -> 0 | K20: =COUNTIF('My Workspace (ESS)'!$O$2:$O$210,"Passed*") -> 28 | L20: =IF(B20=0,0,(F20+G20)/B20) -> 0.13397129 | M20: =IF(B20=0,0,K20/B20) -> 0.13397129
A21: Helpdesk | B21: =COUNTA('Helpdesk'!$A$2:$A$89) -> 88 | C21: =COUNTIF('Helpdesk'!$L$2:$L$89,"High") -> 28 | D21: =COUNTIF('Helpdesk'!$J$2:$J$89,"Positive") -> 40 | E21: =COUNTIF('Helpdesk'!$J$2:$J$89,"Negative") -> 3 | F21: =COUNTIF('Helpdesk'!$M$2:$M$89,"Automated (Linear Run)") -> 6 | G21: =COUNTIF('Helpdesk'!$M$2:$M$89,"Automated (Page Check)") -> 2 | H21: =COUNTIF('Helpdesk'!$M$2:$M$89,"Not Automated") -> 80 | I21: =COUNTIF('Helpdesk'!$M$2:$M$89,"Blocked") -> 0 | J21: =COUNTIF('Helpdesk'!$M$2:$M$89,"Out of Scope") -> 0 | K21: =COUNTIF('Helpdesk'!$O$2:$O$89,"Passed*") -> 8 | L21: =IF(B21=0,0,(F21+G21)/B21) -> 0.090909091 | M21: =IF(B21=0,0,K21/B21) -> 0.090909091
A22: Cross-Module E2E | B22: =COUNTA('Cross-Module E2E'!$A$2:$A$69) -> 68 | C22: =COUNTIF('Cross-Module E2E'!$L$2:$L$69,"High") -> 38 | D22: =COUNTIF('Cross-Module E2E'!$J$2:$J$69,"Positive") -> 0 | E22: =COUNTIF('Cross-Module E2E'!$J$2:$J$69,"Negative") -> 0 | F22: =COUNTIF('Cross-Module E2E'!$M$2:$M$69,"Automated (Linear Run)") -> 22 | G22: =COUNTIF('Cross-Module E2E'!$M$2:$M$69,"Automated (Page Check)") -> 0 | H22: =COUNTIF('Cross-Module E2E'!$M$2:$M$69,"Not Automated") -> 38 | I22: =COUNTIF('Cross-Module E2E'!$M$2:$M$69,"Blocked") -> 3 | J22: =COUNTIF('Cross-Module E2E'!$M$2:$M$69,"Out of Scope") -> 5 | K22: =COUNTIF('Cross-Module E2E'!$O$2:$O$69,"Passed*") -> 22 | L22: =IF(B22=0,0,(F22+G22)/B22) -> 0.32352941 | M22: =IF(B22=0,0,K22/B22) -> 0.32352941
A23: Non-Functional | B23: =COUNTA('Non-Functional'!$A$2:$A$104) -> 103 | C23: =COUNTIF('Non-Functional'!$L$2:$L$104,"High") -> 42 | D23: =COUNTIF('Non-Functional'!$J$2:$J$104,"Positive") -> 0 | E23: =COUNTIF('Non-Functional'!$J$2:$J$104,"Negative") -> 0 | F23: =COUNTIF('Non-Functional'!$M$2:$M$104,"Automated (Linear Run)") -> 3 | G23: =COUNTIF('Non-Functional'!$M$2:$M$104,"Automated (Page Check)") -> 1 | H23: =COUNTIF('Non-Functional'!$M$2:$M$104,"Not Automated") -> 96 | I23: =COUNTIF('Non-Functional'!$M$2:$M$104,"Blocked") -> 2 | J23: =COUNTIF('Non-Functional'!$M$2:$M$104,"Out of Scope") -> 1 | K23: =COUNTIF('Non-Functional'!$O$2:$O$104,"Passed*") -> 4 | L23: =IF(B23=0,0,(F23+G23)/B23) -> 0.038834951 | M23: =IF(B23=0,0,K23/B23) -> 0.038834951
A24: TOTAL | B24: =SUM(B11:B23) -> 2444 | C24: =SUM(C11:C23) -> 878 | D24: =SUM(D11:D23) -> 742 | E24: =SUM(E11:E23) -> 325 | F24: =SUM(F11:F23) -> 138 | G24: =SUM(G11:G23) -> 133 | H24: =SUM(H11:H23) -> 2058 | I24: =SUM(I11:I23) -> 57 | ... K24: =SUM(K11:K23) -> 271 | L24: =IF(B24=0,0,(F24+G24)/B24) -> 0.1108838 | M24: =IF(B24=0,0,K24/B24) -> 0.1108838
A26: Counts are live formulas over each module sheet — they update when you edit Automation / Execution Status. % Automated = (Linear Run + Page Check) ÷ Total.

Sheet Legend & How To Use
A1: COLUMNS
A2: Test ID | B2: TC-<MODULE>-<NNN>. Prefixes: LOG Login & Navigation · CHR Core HR · REC Recruitment · REF Referral · ONB Onboarding & Probation · ATT Attendance · LV Leave · PAY Payroll · EXT Resignation & Exit · ESS My Workspace · HD Helpdesk · E2E Cross-Module · NFR Non-Functional
A3: Page / Sub-module, Route | B3: Sidebar page the case belongs to and its URL path on hrms-test.progbiz.in
A4: Scenario / Description | B4: Feature under test and what this specific test case checks
A5: Test Steps | B5: Numbered actions to execute the test
A6: Steps to Reproduce | B6: The same path on one line — precondition → each step — ready to paste into a defect report if the case fails
A7: Severity | B7: Impact if the case fails. Critical = High priority core flow (Positive / E2E / Integration / Security) · Major = other High, or Medium core flow / Permission · Minor = other Medium, Low functional · Trivial = Low UI / Usability
A8: Type | B8: Positive · Negative · Boundary · Validation · UI · Permission · Integration · E2E · Security · Performance · Usability
A9: Priority | B9: High = core business flow / data integrity · Medium = important function · Low = cosmetic / rare
A10: Test Steps / Expected Result | B10: Numbered actions and the observable result that decides Pass/Fail
A11: Execution Status / Actual Result / Tested By | B11: For manual execution: set Execution Status (dropdown), note the Actual Result, and who/when
A13: AUTOMATION STATUS
A14: Automated (Linear Run) | B14: Exercised end-to-end by the Playwright linear run ("add data once" action on that page). Reference names the step, e.g. "Linear 013 Job Board — openingAndCandidate".
A15: Automated (Page Check) | B15: The linear run opens the page and checks it: not bounced to login, route exists, no application error, loading clears, heading shown, every list renders.
A16: Not Automated | B16: Valid case, not yet automated (manual execution). Payroll / Attendance / Resignation & Exit deep cases are owned by teammates.
A17: Blocked | B17: Cannot be automated now — needs an e-mailed link (candidate pre-boarding form), a device (attendance check-in), attendance records, or an unavailable role.
A18: Out of Scope | B18: Deliberately never automated (irreversible / financial / shared config): exit approval-clearance-F&F, payroll run finalisation & payments, statutory submissions, reward approval/payment, editing shared Payroll/Reward policy. Valid manual cases.
A20: RUNNING THE AUTOMATION
A21: Full run (headed) | B21: HEADED=1 npx playwright test -c hrms/playwright.config.js hrms/tests/00_linear --workers=1 --retries=0
A22: Read-only walk | B22: HRMS_LINEAR_READONLY=1 … (checks every page, adds nothing)
A23: One page / resume | B23: HRMS_PAGES="leave-approval,offer-list" · HRMS_FROM=52
A24: Evidence | B24: On any failure: reports/hrms-evidence/<run>/index.html — screenshots, recordings (incl. second user / candidate windows), whole-run video, trace.

Sheet Page Coverage
A1: # | B1: Section | C1: Page | D1: Route | E1: Linear-run check | F1: "Add data once" action | G1: Last run
A2: 1 | B2: Core HR | C2: Employee | D2: /employees | E2: Page check | F2: createRunEmployee | G2: Passed (19 Oct 2026)
A3: 2 | B3: Core HR | C3: Worker Directory | D3: /worker-directory | E3: Page check | F3: findRunEmployeeAndCompleteProfile | G3: Passed (19 Oct 2026)
A4: 3 | B4: Core HR | C4: Document Compliance | D4: /document-compliance | E4: Page check | F4: — | G4: Passed (19 Oct 2026)
A5: 4 | B5: Core HR | C5: HR Reminders | D5: /hrms/reminder-rules | E5: Page check | F5: — | G5: Passed (19 Oct 2026)
A6: 5 | B6: Core HR | C6: Employee Excel Import | D6: /upload-employee | E6: Page check | F6: — | G6: Passed (19 Oct 2026)
A7: 6 | B7: Core HR | C7: Letter Templates | D7: /letters/templates | E7: Page check | F7: createLetterTemplate | G7: Passed (19 Oct 2026)
A8: 7 | B8: Core HR | C8: Generate Letter | D8: /letters/generate | E8: Page check | F8: generateLetter | G8: Passed (19 Oct 2026)
A9: 8 | B9: Core HR | C9: Letterheads | D9: /letters/letterheads | E9: Page check | F9: — | G9: Passed (19 Oct 2026)
A10: 9 | B10: Core HR | C10: Merge Fields | D10: /letters/fields | E10: Page check | F10: — | G10: Passed (19 Oct 2026)
A11: 10 | B11: Core HR | C11: Approval Config | D11: /approval/config | E11: Page check | F11: — | G11: Passed (19 Oct 2026)
A12: 11 | B12: Core HR | C12: Duty Handover | D12: /employee-handover | E12: Page check | F12: createDutyHandover | G12: Passed (19 Oct 2026)
A13: 12 | B13: Recruitment | C13: Job Requisitions | D13: /requisition-list | E13: Page check | F13: raiseAndApproveRequisition | G13: Passed (19 Oct 2026)
... A129: 128 | B129: Helpdesk | C129: Helpdesk Dashboard | D129: /ess/helpdesk/admin | E129: Page check | F129: ticketLifecycle | G129: Passed (19 Oct 2026)

Sheet Login & Navigation
A1: Test ID | B1: Page / Sub-module | C1: Scenario | D1: Description | E1: Preconditions | F1: Test Data | G1: Test Steps | H1: Steps to Reproduce | I1: Expected Result | J1: Type | K1: Severity | L1: Priority | M1: Automation Status | N1: Automation Reference | O1: Execution Status | P1: Actual Result | Q1: Tested By / Date | R1: Route | S1: Remarks | T1: SRS Ref
A2: TC-LOG-001 | B2: Login | C2: Login page UI | D2: Login page renders all controls | E2: Logged out (fresh browser profile, no session) | G2: 1. Open https://hrms-test.progbiz.in/login 2. Observe the form | H2: Logged out (fresh browser profile, no session) → Open https://hrms-test.progbiz.in/login → Observe the form | I2: Company Code, User Name and Password inputs, a Sign In button, a Forgot password link and a Sign Up link are shown; no console/app error; password input is masked | J2: UI | K2: Major | L2: High | M2: Not Automated | O2: Not Executed | R2: /login
A3: TC-LOG-002 | B3: Login | C3: Login page UI | D3: Password characters are masked | E3: Logged out (fresh browser profile, no session) | F3: Password: Abc@1234 | G3: 1. Open /login 2. Type any text in Password | H3: Logged out (fresh browser profile, no session) → Open /login → Type any text in Password | I3: Password field is of type password and shows masked characters; value is never echoed in plain text | J3: Security | K3: Critical | L3: High | M3: Not Automated | O3: Not Executed | R3: /login
A4: TC-LOG-003 | B4: Login | C4: Login page UI | D4: Enter key submits the login form | E4: Logged out (fresh browser profile, no session) | F4: pbhrms / amit / <admin password> | G4: 1. Open /login 2. Fill Company Code, User Name, Password 3. Press Enter in the Password field | H4: Logged out (fresh browser profile, no session) → Open /login → Fill Company Code, User Name, Password → Press Enter in the Password field | I4: Form is submitted exactly as with the Sign In button and the user lands on Home | J4: Usability | K4: Minor | L4: Medium | M4: Not Automated | O4: Not Executed | R4: /login
A5: TC-LOG-004 | B5: Login | C5: Valid login | D5: Admin signs in with valid company code, user name and password | E5: Logged out (fresh browser profile, no session); admin account amit is active | F5: Company Code: pbhrms; User Name: amit | G5: 1. Open /login 2. Enter Company Code 3. Enter User Name 4. Enter Password 5. Click Sign In | H5: Logged out (fresh browser profile, no session); admin account amit is active → Open /login → Enter Company Code → Enter User Name → Enter Password → Click Sign In | I5: User leaves /login and lands on Home (/home); sidebar shows the HRMS menu; header shows Amit Kumar Shaji | J5: Positive | K5: Critical | L5: High | M5: Automated (Linear Run) | N5: Linear run global-setup — HrmsLoginPage.login (admin session reused by all 128 steps) | O5: Passed (19 Oct 2026) | R5: /login
A6: TC-LOG-005 | B6: Login | C6: Valid login | D6: Employee signs in with the initial password = employee code | E6: Logged out (fresh browser profile, no session); an employee was created in Core HR with Login Username set and Can Login ticked | F6: Username: as set on create; Password: employee code (e.g. pbhrms0305) | G6: 1. Open /login 2. Enter Company Code pbhrms 3. Enter the employee's Login Username 4. Enter the employee code as Password 5. Click Sign In | H6: Logged out (fresh browser profile, no session); an employee was created in Core HR with Login Username set and Can Login ticked → Open /login → Enter Company Code pbhrms → Enter the employee's Login Username → Enter the employee code as Password → Click Sign In | I6: Login succeeds; employee lands on Home / My Workspace with only the menus their role allows | J6: Positive | K6: Critical | L6: High | M6: Automated (Linear Run) | N6: Linear 056 Leave Approval — employeeAppliesManagerApproves (withUser signs in as the run employee) | O6: Passed (19 Oct 2026) | R6: /login
A7: TC-LOG-006 | B7: Login | C7: Valid login | D7: Team Lead user signs in | E7: Logged out (fresh browser profile, no session); a user with access role Team Lead exists | G7: 1. Open /login 2. Enter pbhrms, the Team Lead user name and password 3. Click Sign In | H7: Logged out (fresh browser profile, no session); a user with access role Team Lead exists → Open /login → Enter pbhrms, the Team Lead user name and password → Click Sign In | I7: Login succeeds; Team Lead sees My Workspace plus the team/approval menus their role grants | J7: Positive | K7: Major | L7: Medium | M7: Not Automated | O7: Not Executed | R7: /login
A8: TC-LOG-007 | B8: Login | C8: Valid login | D8: Login completes within acceptable time | E8: Logged out (fresh browser profile, no session) | G8: 1. Open /login 2. Sign in with valid admin credentials 3. Measure time until Home is fully rendered | H8: Logged out (fresh browser profile, no session) → Open /login → Sign in with valid admin credentials → Measure time until Home is fully rendered | I8: Home page is interactive within 5 seconds on a normal connection | J8: Performance | K8: Minor | L8: Medium | M8: Not Automated | O8: Not Executed | R8: /login
A9: TC-LOG-008 | B9: Login | C9: Invalid login | D9: Wrong password is rejected | E9: Logged out (fresh browser profile, no session) | F9: Password: WrongPass@1 | G9: 1. Open /login 2. Enter pbhrms / amit 3. Enter an incorrect password 4. Click Sign In | H9: Logged out (fresh browser profile, no session) → Open /login → Enter pbhrms / amit → Enter an incorrect password → Click Sign In | I9: Login refused with an error message (e.g. invalid credentials); user stays on /login; password field cleared or kept masked | J9: Negative | K9: Major | L9: High | M9: Not Automated | O9: Not Executed | R9: /login
A10: TC-LOG-009 | B10: Login | C10: Invalid login | D10: Unknown user name is rejected | E10: Logged out (fresh browser profile, no session) | F10: User Name: no.such.user | G10: 1. Open /login 2. Enter pbhrms 3. Enter user name that does not exist 4. Enter any password 5. Click Sign In | H10: Logged out (fresh browser profile, no session) → Open /login → Enter pbhrms → Enter user name that does not exist → Enter any password → Click Sign In | I10: Login refused; error message does not reveal whether the user name exists | J10: Negative | K10: Major | L10: High | M10: Not Automated | O10: Not Executed | R10: /login
A11: TC-LOG-010 | B11: Login | C11: Invalid login | D11: Wrong company code is rejected | E11: Logged out (fresh browser profile, no session) | F11: Company Code: pbhrmsX | G11: 1. Open /login 2. Enter an invalid company code 3. Enter valid user name and password 4. Click Sign In | H11: Logged out (fresh browser profile, no session) → Open /login → Enter an invalid company code → Enter valid user name and password → Click Sign In | I11: Login refused with an invalid company / credentials message; no session created | J11: Negative | K11: Major | L11: High | M11: Not Automated | O11: Not Executed | R11: /login
A12: TC-LOG-011 | B12: Login | C12: Invalid login | D12: Valid user name with another tenant's company code is rejected | E12: Logged out (fresh browser profile, no session); a second tenant code exists (e.g. progbiz) | G12: 1. Open /login 2. Enter the other tenant's company code 3. Enter amit and the pbhrms password 4. Click Sign In | H12: Logged out (fresh browser profile, no session); a second tenant code exists (e.g. progbiz) → Open /login → Enter the other tenant's company code → Enter amit and the pbhrms password → Click Sign In | I12: Login refused; user cannot reach pbhrms data through another tenant code (tenant isolation) | J12: Security | K12: Critical | L12: High | M12: Not Automated | O12: Not Executed | R12: /login
A13: TC-LOG-012 | B13: Login | C13: Mandatory fields | D13: Company Code blank shows validation | E13: Logged out (fresh browser profile, no session) | G13: 1. Open /login 2. Leave Company Code empty 3. Fill User Name and Password 4. Click Sign In | H13: Logged out (fresh browser profile, no session) → Open /login → Leave Company Code empty → Fill User Name and Password → Click Sign In | I13: Inline/required validation on Company Code; no login request is sent | J13: Validation | K13: Major | L13: High | M13: Not Automated | O13: Not Executed | R13: /login
A14: TC-LOG-013 | B14: Login | C14: Mandatory fields | D14: User Name blank shows validation | E14: Logged out (fresh browser profile, no session) | G14: 1. Open /login 2. Fill Company Code 3. Leave User Name empty 4. Fill Password 5. Click Sign In | H14: Logged out (fresh browser profile, no session) → Open /login → Fill Company Code → Leave User Name empty → Fill Password → Click Sign In | I14: Required validation on User Name; user stays on /login | J14: Validation | K14: Major | L14: High | M14: Not Automated | O14: Not Executed | R14: /login
A15: TC-LOG-014 | B15: Login | C15: Mandatory fields | D15: Password blank shows validation | E15: Logged out (fresh browser profile, no session) | G15: 1. Open /login 2. Fill Company Code and User Name 3. Leave Password empty 4. Click Sign In | H15: Logged out (fresh browser profile, no session) → Open /login → Fill Company Code and User Name → Leave Password empty → Click Sign In | I15: Required validation on Password; user stays on /login | J15: Validation | K15: Major | L15: High | M15: Not Automated | O15: Not Executed | R15: /login
A16: TC-LOG-015 | B16: Login | C16: Mandatory fields | D16: All fields blank shows validation for each | E16: Logged out (fresh browser profile, no session) | G16: 1. Open /login 2. Click Sign In without filling anything | H16: Logged out (fresh browser profile, no session) → Open /login → Click Sign In without filling anything | I16: All three fields flagged as required; no request sent; no server error | J16: Validation | K16: Minor | L16: Medium | M16: Not Automated | O16: Not Executed | R16: /login
A17: TC-LOG-016 | B17: Login | C17: Input handling | D17: Company code is case-insensitive | E17: Logged out (fresh browser profile, no session) | F17: Company Code: PBHRMS | G17: 1. Open /login 2. Enter PBHRMS (upper case) with valid user name and password 3. Click Sign In | H17: Logged out (fresh browser profile, no session) → Open /login → Enter PBHRMS (upper case) with valid user name and password → Click Sign In | I17: Login behaves consistently — accepted as the same tenant (case-insensitive) or refused with a clear message; never an application error | J17: Boundary | K17: Minor | L17: Low | M17: Not Automated | O17: Not Executed | R17: /login
A18: TC-LOG-017 | B18: Login | C18: Input handling | D18: Password is case-sensitive | E18: Logged out (fresh browser profile, no session) | G18: 1. Open /login 2. Enter valid company code and user name 3. Enter the correct password with letter case inverted 4. Click Sign In | H18: Logged out (fresh browser profile, no session) → Open /login → Enter valid company code and user name → Enter the correct password with letter case inverted → Click Sign In | I18: Login refused — password comparison is case-sensitive | J18: Security | K18: Critical | L18: High | M18: Not Automated | O18: Not Executed | R18: /login
A19: TC-LOG-018 | B19: Login | C19: Input handling | D19: Leading/trailing spaces in user name and company code | E19: Logged out (fresh browser profile, no session) | G19: 1. Open /login 2. Enter " pbhrms " and " amit " with surrounding spaces 3. Enter correct password 4. Click Sign In | H19: Logged out (fresh browser profile, no session) → Open /login → Enter " pbhrms " and " amit " with surrounding spaces → Enter correct password → Click Sign In | I19: Spaces are trimmed and login succeeds, or a clear invalid-credentials message is shown; no application error | J19: Boundary | K19: Minor | L19: Medium | M19: Not Automated | O19: Not Executed | R19: /login
A20: TC-LOG-019 | B20: Login | C20: Security | D20: SQL injection in User Name is not executed | E20: Logged out (fresh browser profile, no session) | F20: User Name: ' OR 1=1 -- | G20: 1. Open /login 2. Enter pbhrms 3. Enter ' OR 1=1 -- as User Name 4. Enter any password 5. Click Sign In | H20: Logged out (fresh browser profile, no session) → Open /login → Enter pbhrms → Enter ' OR 1=1 -- as User Name → Enter any password → Click Sign In | I20: Login refused as invalid credentials; no database error or internal detail is shown | J20: Security | K20: Critical | L20: High | M20: Not Automated | O20: Not Executed | R20: /login
A21: TC-LOG-020 | B21: Login | C21: Security | D21: Repeated failed logins are throttled or locked | E21: Logged out (fresh browser profile, no session) | G21: 1. Open /login 2. Attempt 10 consecutive logins for amit with a wrong password 3. Then try the correct password | H21: Logged out (fresh browser profile, no session) → Open /login → Attempt 10 consecutive logins for amit with a wrong password → Then try the correct password | I21: After repeated failures the account/IP is throttled or temporarily locked (or a delay is enforced); behaviour is documented and no unlimited brute force is possible | J21: Security | K21: Major | L21: Medium | M21: Not Automated | O21: Not Executed | R21: /login | S21: Lockout threshold is not defined in the SRS — record actual behaviour; run only against a disposable test user
A22: TC-LOG-021 | B22: Login | C22: Security | D22: Credentials are never sent in the URL | E22: Logged out (fresh browser profile, no session) | G22: 1. Open /login with browser DevTools Network tab 2. Sign in 3. Inspect the login request and resulting URL | H22: Logged out (fresh browser profile, no session) → Open /login with browser DevTools Network tab → Sign in → Inspect the login request and resulting URL | I22: Login is a POST over HTTPS; company code, user name and password never appear in the URL or query string | J22: Security | K22: Critical | L22: High | M22: Not Automated | O22: Not Executed | R22: /login
A23: TC-LOG-022 | B23: Login | C23: Account state | D23: Employee with Can Login unticked cannot sign in | E23: An employee exists whose Can Login checkbox is unticked on the employee form | G23: 1. Open /login 2. Enter pbhrms, that employee's user name and employee-code password 3. Click Sign In | H23: An employee exists whose Can Login checkbox is unticked on the employee form → Open /login → Enter pbhrms, that employee's user name and employee-code password → Click Sign In | I23: Login refused (login disabled / invalid credentials); no session created | J23: Permission | K23: Major | L23: High | M23: Not Automated | O23: Not Executed | R23: /login
A24: TC-LOG-023 | B24: Login | C24: Account state | D24: Exited / archived employee cannot sign in | E24: An employee whose exit is completed (status Archived/Resigned) exists with a login | G24: 1. Open /login 2. Enter that employee's credentials 3. Click Sign In | H24: An employee whose exit is completed (status Archived/Resigned) exists with a login → Open /login → Enter that employee's credentials → Click Sign In | I24: Login refused; former employee cannot access the app | J24: Permission | K24: Major | L24: High | M24: Not Automated | O24: Not Executed | R24: /login
A25: TC-LOG-024 | B25: Forgot Password | C25: Forgot password | D25: Forgot password link opens the reset form | E25: Logged out (fresh browser profile, no session) | G25: 1. Open /login 2. Click Forgot password | H25: Logged out (fresh browser profile, no session) → Open /login → Click Forgot password | I25: Password reset form opens with the identifying fields (company code / user name or e-mail) and a submit button, plus a way back to Sign In | J25: UI | K25: Major | L25: High | M25: Not Automated | O25: Not Executed | R25: /login
A26: TC-LOG-025 | B26: Forgot Password | C26: Forgot password | D26: Reset request for a registered user | E26: Logged out (fresh browser profile, no session); a test employee with a valid @example.com e-mail exists | F26: User: run employee (e.g. rohan.varghese@example.com) | G26: 1. Open Forgot password 2. Enter the company code and the test user's user name / e-mail 3. Submit | H26: Logged out (fresh browser profile, no session); a test employee with a valid @example.com e-mail exists → Open Forgot password → Enter the company code and the test user's user name / e-mail → Submit | I26: Confirmation message that reset instructions were sent; reset e-mail queued to the user's registered address | J26: Positive | K26: Critical | L26: High | M26: Not Automated | O26: Not Executed | R26: /login
A27: TC-LOG-026 | B27: Forgot Password | C27: Forgot password | D27: Reset request for an unknown user does not reveal existence | E27: Logged out (fresh browser profile, no session) | F27: nobody@example.com | G27: 1. Open Forgot password 2. Enter a user name / e-mail that does not exist 3. Submit | H27: Logged out (fresh browser profile, no session) → Open Forgot password → Enter a user name / e-mail that does not exist → Submit | I27: Generic message (same as for a valid user) or a neutral error; the response does not confirm whether the account exists | J27: Security | K27: Major | L27: Medium | M27: Not Automated | O27: Not Executed | R27: /login
A28: TC-LOG-027 | B28: Forgot Password | C28: Forgot password | D28: Reset form mandatory validation | E28: Logged out (fresh browser profile, no session) | G28: 1. Open Forgot password 2. Submit with all fields empty | H28: Logged out (fresh browser profile, no session) → Open Forgot password → Submit with all fields empty | I28: Required-field validation shown; no request sent | J28: Validation | K28: Minor | L28: Medium | M28: Not Automated | O28: Not Executed | R28: /login
A29: TC-LOG-028 | B29: Forgot Password | C29: Forgot password | D29: Reset link sets a new password and old one stops working | E29: A reset e-mail has been received for a test user | G29: 1. Open the reset link from the e-mail 2. Enter and confirm a new password 3. Submit 4. Sign in with the new password 5. Try the old password | H29: A reset e-mail has been received for a test user → Open the reset link from the e-mail → Enter and confirm a new password → Submit → Sign in with the new password → Try the old password | I29: New password works; old password is rejected; reset link cannot be reused | J29: E2E | K29: Critical | L29: High | M29: Blocked | O29: Not Executed | R29: /login | S29: Needs the e-mailed reset link, which automation cannot receive
A30: TC-LOG-029 | B30: Forgot Password | C30: Forgot password | D30: Expired or reused reset link is refused | E30: A reset link has already been used or has expired | G30: 1. Open the used/expired reset link | H30: A reset link has already been used or has expired → Open the used/expired reset link | I30: Page states the link is invalid or expired and offers to request a new one | J30: Negative | K30: Minor | L30: Medium | M30: Blocked | O30: Not Executed | R30: /login | S30: Needs the e-mailed reset link
A31: TC-LOG-030 | B31: Sign Up | C31: Sign up | D31: Sign Up link opens the registration form | E31: Logged out (fresh browser profile, no session) | G31: 1. Open /login 2. Click Sign Up | H31: Logged out (fresh browser profile, no session) → Open /login → Click Sign Up | I31: Registration form opens with its fields and a submit button; nothing is created until submitted | J31: UI | K31: Minor | L31: Medium | M31: Not Automated | O31: Not Executed | R31: /login | S31: Do not submit on the shared test tenant — creates a new organisation/account
A32: TC-LOG-031 | B32: Sign Up | C32: Sign up | D32: Sign Up mandatory-field validation | E32: Logged out (fresh browser profile, no session) | G32: 1. Open Sign Up 2. Click submit with all fields empty | H32: Logged out (fresh browser profile, no session) → Open Sign Up → Click submit with all fields empty | I32: Each required field is flagged; no account is created | J32: Validation | K32: Minor | L32: Low | M32: Not Automated | O32: Not Executed | R32: /login
A33: TC-LOG-032 | B33: Session & Logout | C33: Logout | D33: Logout from the profile menu ends the session | E33: Logged in as HRMS admin amit (Amit Kumar Shaji, role HRMS / Administrator) | G33: 1. Click the profile avatar in the header 2. Click Logout | H33: Logged in as HRMS admin amit (Amit Kumar Shaji, role HRMS / Administrator) → Click the profile avatar in the header → Click Logout | I33: User is returned to /login; session cookie/token is cleared | J33: Positive | K33: Critical | L33: High | M33: Not Automated | O33: Not Executed
A34: TC-LOG-033 | B34: Session & Logout | C34: Logout | D34: Browser Back after logout does not show protected data | E34: Logged in as HRMS admin amit (Amit Kumar Shaji, role HRMS / Administrator) | G34: 1. Open /employees 2. Logout 3. Press browser Back | H34: Logged in as HRMS admin amit (Amit Kumar Shaji, role HRMS / Administrator) → Open /employees → Logout → Press browser Back | I34: User stays on / is redirected to /login; the employee list is not displayed from cache with live data | J34: Security | K34: Critical | L34: High | M34: Not Automated | O34: Not Executed
A35: TC-LOG-034 | B35: Session & Logout | C35: Logout | D35: Protected URL after logout redirects to login | E35: Logged in as HRMS admin amit (Amit Kumar Shaji, role HRMS / Administrator) | G35: 1. Logout 2. Type /employees in the address bar | H35: Logged in as HRMS admin amit (Amit Kumar Shaji, role HRMS / Administrator) → Logout → Type /employees in the address bar | I35: Redirected to /login; no data shown | J35: Security | K35: Critical | L35: High | M35: Not Automated | O35: Not Executed
A36: TC-LOG-035 | B36: Session & Logout | C36: Logout | D36: Logout in one tab invalidates the other tab | E36: Logged in as HRMS admin amit (Amit Kumar Shaji, role HRMS / Administrator) in two tabs | G36: 1. Open /employees in tab A and /leave-approval in tab B 2. Logout in tab A 3. Click any menu link in tab B | H36: Logged in as HRMS admin amit (Amit Kumar Shaji, role HRMS / Administrator) in two tabs → Open /employees in tab A and /leave-approval in tab B → Logout in tab A → Click any menu link in tab B | I36: Tab B is redirected to /login on its next request | J36: Security | K36: Major | L36: Medium | M36: Not Automated | O36: Not Executed
A37: TC-LOG-036 | B37: Session & Logout | C37: Session | D37: Session survives a page refresh | E37: Logged in as HRMS admin amit (Amit Kumar Shaji, role HRMS / Administrator) | G37: 1. Open /letters/templates 2. Press F5 | H37: Logged in as HRMS admin amit (Amit Kumar Shaji, role HRMS / Administrator) → Open /letters/templates → Press F5 | I37: User stays signed in on the same page; data reloads; no login prompt | J37: Positive | K37: Critical | L37: High | M37: Not Automated | O37: Not Executed
A38: TC-LOG-037 | B38: Session & Logout | C38: Session | D38: Two different users in separate browser contexts | E38: Logged in as HRMS admin amit (Amit Kumar Shaji, role HRMS / Administrator); a test employee login exists | G38: 1. Keep admin signed in in the main window 2. Open an incognito/second context 3. Sign in as the test employee 4. Act in both | H38: Logged in as HRMS admin amit (Amit Kumar Shaji, role HRMS / Administrator); a test employee login exists → Keep admin signed in in the main window → Open an incognito/second context → Sign in as the test employee → Act in both | I38: Each window keeps its own user; actions are attributed to the correct user; no session bleed | J38: Positive | K38: Critical | L38: High | M38: Automated (Linear Run) | N38: Linear 056 Leave Approval — employeeAppliesManagerApproves (withUser signs in as the run employee) | O38: Passed (19 Oct 2026)
A39: TC-LOG-038 | B39: Session & Logout | C39: Session expiry | D39: Idle session expires and next action goes to login | E39: Logged in as HRMS admin amit (Amit Kumar Shaji, role HRMS / Administrator) | G39: 1. Sign in 2. Leave the browser idle beyond the token lifetime 3. Click a menu item | H39: Logged in as HRMS admin amit (Amit Kumar Shaji, role HRMS / Administrator) → Sign in → Leave the browser idle beyond the token lifetime → Click a menu item | I39: If the token refresh fails the user is redirected to /login; no partial page or false success | J39: Security | K39: Critical | L39: High | M39: Not Automated | O39: Not Executed | T39: Core HR SRS §10.4
A40: TC-LOG-039 | B40: Session & Logout | C40: Session expiry | D40: Active user is not logged out mid-work | E40: Logged in as HRMS admin amit (Amit Kumar Shaji, role HRMS / Administrator) | G40: 1. Keep using the app (navigate every few minutes) past the access-token lifetime | H40: Logged in as HRMS admin amit (Amit Kumar Shaji, role HRMS / Administrator) → Keep using the app (navigate every few minutes) past the access-token lifetime | I40: Expired access token is refreshed transparently; the user is not interrupted | J40: Positive | K40: Major | L40: Medium | M40: Not Automated | O40: Not Executed | T40: Core HR SRS §10.4
A41: TC-LOG-040 | B41: Session & Logout | C41: Session expiry | D41: Unsaved form when the session expires | E41: Logged in as HRMS admin amit (Amit Kumar Shaji, role HRMS / Administrator) | G41: 1. Open New Employee 2. Fill some fields 3. Wait until the session expires 4. Click Save | H41: Logged in as HRMS admin amit (Amit Kumar Shaji, role HRMS / Administrator) → Open New Employee → Fill some fields → Wait until the session expires → Click Save | I41: Save is not silently lost as success: user is told the session expired / redirected to login; no partial employee is created | J41: Negative | K41: Minor | L41: Medium | M41: Not Automated | O41: Not Executed
A42: TC-LOG-041 | B42: Session & Logout | C42: Session | D42: Tampered auth token is rejected | E42: Logged in as HRMS admin amit (Amit Kumar Shaji, role HRMS / Administrator) | G42: 1. Open DevTools 2. Alter the stored auth token/cookie value 3. Reload /employees | H42: Logged in as HRMS admin amit (Amit Kumar Shaji, role HRMS / Administrator) → Open DevTools → Alter the stored auth token/cookie value → Reload /employees | I42: User is redirected to /login; no data is returned for an invalid token | J42: Security | K42: Critical | L42: High | M42: Not Automated | O42: Not Executed
A43: TC-LOG-042 | B43: Change Password | C43: Change password | D43: Change own password with the correct current password | E43: Logged in as an employee with access role Staff (User Level Team Member), login created via Core HR (initial password = employee code) | F43: New password: Test@2026x | G43: 1. Open profile menu > Change Password 2. Enter current password (employee code) 3. Enter and confirm a new password 4. Save 5. Logout and sign in with the new password | H43: Logged in as an employee with access role Staff (User Level Team Member), login created via Core HR (initial password = employee code) → Open profile menu > Change Password → Enter current password (employee code) → Enter and confirm a new password → Save → Logout and sign in with the new password | I43: Success message; new password works; old password (employee code) is rejected | J43: Positive | K43: Critical | L43: High | M43: Not Automated | O43: Not Executed | R43: /change-password
A44: TC-LOG-043 | B44: Change Password | C44: Change password | D44: Wrong current password is rejected | E44: Logged in as an employee with access role Staff (User Level Team Member), login created via Core HR (initial password = employee code) | G44: 1. Open Change Password 2. Enter a wrong current password 3. Enter matching new passwords 4. Save | H44: Logged in as an employee with access role Staff (User Level Team Member), login created via Core HR (initial password = employee code) → Open Change Password → Enter a wrong current password → Enter matching new passwords → Save | I44: Error that the current password is incorrect; password unchanged | J44: Negative | K44: Major | L44: High | M44: Not Automated | O44: Not Executed | R44: /change-password
A45: TC-LOG-044 | B45: Change Password | C45: Change password | D45: New and confirm password mismatch | E45: Logged in as an employee with access role Staff (User Level Team Member), login created via Core HR (initial password = employee code) | G45: 1. Open Change Password 2. Enter current password 3. Enter different New and Confirm values 4. Save | H45: Logged in as an employee with access role Staff (User Level Team Member), login created via Core HR (initial password = employee code) → Open Change Password → Enter current password → Enter different New and Confirm values → Save | I45: Validation message that passwords do not match; nothing saved | J45: Validation | K45: Minor | L45: Medium | M45: Not Automated | O45: Not Executed | R45: /change-password
A46: TC-LOG-045 | B46: Change Password | C46: Admin reset | D46: Admin resets an employee password from Master > Reset Password | E46: Logged in as HRMS admin amit (Amit Kumar Shaji, role HRMS / Administrator); a test employee login exists | G46: 1. Open Master > Reset Password (/change-user-password) 2. Pick the test employee 3. Enter a new password 4. Save 5. Sign in as the employee with it | H46: Logged in as HRMS admin amit (Amit Kumar Shaji, role HRMS / Administrator); a test employee login exists → Open Master > Reset Password (/change-user-password) → Pick the test employee → Enter a new password → Save → Sign in as the employee with it | I46: Reset succeeds; employee can sign in with the new password | J46: Positive | K46: Major | L46: Medium | M46: Not Automated | O46: Not Executed | R46: /change-password
A47: TC-LOG-046 | B47: Sidebar Navigation | C47: Sidebar structure | D47: Admin sidebar shows every HRMS module group | E47: Logged in as HRMS admin amit (Amit Kumar Shaji, role HRMS / Administrator) | G47: 1. Sign in 2. Expand HRMS in the left sidebar | H47: Logged in as HRMS admin amit (Amit Kumar Shaji, role HRMS / Administrator) → Sign in → Expand HRMS in the left sidebar | I47: Groups Core HR, Recruitment, Onboarding, Attendance, Leave Management, Payroll, Resignation & Exit, My Workspace, Employee Referrals/Referral, Helpdesk and Master are listed in that order | J47: UI | K47: Major | L47: High | M47: Not Automated | O47: Not Executed
A48: TC-LOG-047 | B48: Sidebar Navigation | C48: Sidebar structure | D48: Every HRMS sidebar page opens without error for admin | E48: Logged in as HRMS admin amit (Amit Kumar Shaji, role HRMS / Administrator) | G48: 1. Open each of the 128 HRMS sidebar routes in sidebar order 2. Wait for loading to clear | H48: Logged in as HRMS admin amit (Amit Kumar Shaji, role HRMS / Administrator) → Open each of the 128 HRMS sidebar routes in sidebar order → Wait for loading to clear | I48: Every page stays on its route (no /login bounce, no "Sorry, there's nothing at this address"), shows a heading, no app error bar, lists render | J48: Positive | K48: Critical | L48: High | M48: Automated (Page Check) | N48: Linear 001–128 — page check (all HRMS pages) | O48: Passed (19 Oct 2026)
A49: TC-LOG-048 | B49: Sidebar Navigation | C49: Core HR menu | D49: Core HR menu items open their pages | E49: Logged in as HRMS admin amit (Amit Kumar Shaji, role HRMS / Administrator) | G49: 1. Expand HRMS > Core HR 2. Click Employee, Worker Directory, Document Compliance, HR Reminders, Employee Excel Import in turn 3. Expand Letters and click Letter Templates, Generate Letter, Letterheads, Merge Fields 4. Expand Approvals and click Approval Config, Duty Handover | H49: Logged in as HRMS admin amit (Amit Kumar Shaji, role HRMS / Administrator) → Expand HRMS > Core HR → Click Employee, Worker Directory, Document Compliance, HR Reminders, Employee Excel Import in turn → Expand Letters and click Letter Templates, Generate Letter, Letterheads, Merge Fields → Expand Approvals and click Approval Config, Duty Handover | I49: Each click opens /employees, /worker-directory, /document-compliance, /hrms/reminder-rules, /upload-employee, /letters/templates, /letters/generate, /letters/letterheads, /letters/fields, /approval/config, /employee-handover respectively | J49: Positive | K49: Critical | L49: High | M49: Not Automated | O49: Not Executed
A50: TC-LOG-049 | B50: Sidebar Navigation | C50: Recruitment menu | D50: Recruitment menu items open their pages | E50: Logged in as HRMS admin amit (Amit Kumar Shaji, role HRMS / Administrator) | G50: 1. Expand HRMS > Recruitment 2. Click each item including Pipeline > Pipeline Board/Talent Pool, Settings > Interview Rounds, Employee Referrals > Referral Dashboard/Reward Policy | H50: Logged in as HRMS admin amit (Amit Kumar Shaji, role HRMS / Administrator) → Expand HRMS > Recruitment → Click each item including Pipeline > Pipeline Board/Talent Pool, Settings > Interview Rounds, Employee Referrals > Referral Dashboard/Reward Policy | I50: Each item opens its route (/requisition-list, /vacancy-list, /job-applications-list, /assessment-list, /interview-schedules, /offer-list, /offer-acceptance, /recruitment/approvals, /recruitment-dashboard, /recruitment-pipeline, /talent-pool, /interview-rounds, /ess/referral/admin, /ess/referral/admin/policy) | J50: Positive | K50: Major | L50: Medium | M50: Not Automated | O50: Not Executed
A51: TC-LOG-050 | B51: Sidebar Navigation | C51: Onboarding menu | D51: Onboarding menu items open their pages | E51: Logged in as HRMS admin amit (Amit Kumar Shaji, role HRMS / Administrator) | G51: 1. Expand HRMS > Onboarding 2. Click each item including the Probation and Reports sub-groups | H51: Logged in as HRMS admin amit (Amit Kumar Shaji, role HRMS / Administrator) → Expand HRMS > Onboarding → Click each item including the Probation and Reports sub-groups | I51: All 15 items open their routes (/onboarding-templates … /hrms/probation-report) with no error | J51: Positive | K51: Major | L51: Medium | M51: Not Automated | O51: Not Executed
A52: TC-LOG-051 | B52: Sidebar Navigation | C52: Attendance menu | D52: Attendance menu items open their pages | E52: Logged in as HRMS admin amit (Amit Kumar Shaji, role HRMS / Administrator) | G52: 1. Expand HRMS > Attendance 2. Click each of the 8 items | H52: Logged in as HRMS admin amit (Amit Kumar Shaji, role HRMS / Administrator) → Expand HRMS > Attendance → Click each of the 8 items | I52: Shifts & Rules, Shift Roster, Regularization, Late In / Early Out Requests, Overtime Approval, Attendance Finalization, Geofences, Test Data Generator open their routes | J52: Positive | K52: Major | L52: Medium | M52: Not Automated | O52: Not Executed
A53: TC-LOG-052 | B53: Sidebar Navigation | C53: Leave menu | D53: Leave Management menu items open their pages | E53: Logged in as HRMS admin amit (Amit Kumar Shaji, role HRMS / Administrator) | G53: 1. Expand HRMS > Leave Management 2. Click each item under Setup, Records & Oversight and Analytics | H53: Logged in as HRMS admin amit (Amit Kumar Shaji, role HRMS / Administrator) → Expand HRMS > Leave Management → Click each item under Setup, Records & Oversight and Analytics | I53: All items open (/leave-types … /leave-calendar); sub-group headings Setup / Records & Oversight / Analytics are shown | J53: Positive | K53: Major | L53: Medium | M53: Not Automated | O53: Not Executed
A54: TC-LOG-053 | B54: Sidebar Navigation | C54: Payroll menu | D54: Payroll menu items open their pages | E54: Logged in as HRMS admin amit (Amit Kumar Shaji, role HRMS / Administrator) | G54: 1. Expand HRMS > Payroll 2. Click each item under Pay Design, Consultant Payouts, Processing, Tax & Compliance and reports | H54: Logged in as HRMS admin amit (Amit Kumar Shaji, role HRMS / Administrator) → Expand HRMS > Payroll → Click each item under Pay Design, Consultant Payouts, Processing, Tax & Compliance and reports | I54: All Payroll items open their /payroll/* routes with no error | J54: Positive | K54: Major | L54: Medium | M54: Not Automated | O54: Not Executed
A55: TC-LOG-054 | B55: Sidebar Navigation | C55: Exit menu | D55: Resignation & Exit menu items open their pages | E55: Logged in as HRMS admin amit (Amit Kumar Shaji, role HRMS / Administrator) | G55: 1. Expand HRMS > Resignation & Exit 2. Click each of the 12 items | H55: Logged in as HRMS admin amit (Amit Kumar Shaji, role HRMS / Administrator) → Expand HRMS > Resignation & Exit → Click each of the 12 items | I55: Exit Dashboard, Exit Reports, Resignations & Exits, F&F Settlements, Exit Watch, Exit Approvals, Exit Clearance and the 5 configuration pages open their routes | J55: Positive | K55: Major | L55: Medium | M55: Not Automated | O55: Not Executed
A56: TC-LOG-055 | B56: Sidebar Navigation | C56: My Workspace menu | D56: My Workspace menu items open their pages | E56: Logged in as HRMS admin amit (Amit Kumar Shaji, role HRMS / Administrator) | G56: 1. Expand HRMS > My Workspace 2. Click each item | H56: Logged in as HRMS admin amit (Amit Kumar Shaji, role HRMS / Administrator) → Expand HRMS > My Workspace → Click each item | I56: Workspace, Profile, Digital ID, Directory, Requests, Approvals, Leave, Handover, Onboarding Tasks, Trainings, Resignation, Exit Tasks, Exit Interview, Attendance, Shift, Locations, Documents, Letters, Pay, Tax, Previous Employer (12B), Probation open their /ess/* or /my-* routes | J56: Positive | K56: Major | L56: Medium | M56: Not Automated | O56: Not Executed
A57: TC-LOG-056 | B57: Sidebar Navigation | C57: Master menu | D57: Master menu items open their pages | E57: Logged in as HRMS admin amit (Amit Kumar Shaji, role HRMS / Administrator) | G57: 1. Expand Master 2. Click Customers, Users, User Levels, User Hierarchy, Access Roles, Teams, Departments, Designations, Reset Password, Branches, Tenant Settings | H57: Logged in as HRMS admin amit (Amit Kumar Shaji, role HRMS / Administrator) → Expand Master → Click Customers, Users, User Levels, User Hierarchy, Access Roles, Teams, Departments, Designations, Reset Password, Branches, Tenant Settings | I57: Each opens its route (/customers, /users, /user-levels, /users?view=hierarchy, /access-roles, /teams, /department, /designations, /change-user-password, /branches, /client-setting) | J57: Positive | K57: Major | L57: Medium | M57: Not Automated | O57: Not Executed
A58: TC-LOG-057 | B58: Sidebar Navigation | C58: Sidebar behaviour | D58: Active page is highlighted and its group expanded | E58: Logged in as HRMS admin amit (Amit Kumar Shaji, role HRMS / Administrator) | G58: 1. Open /leave-approval directly via the address bar | H58: Logged in as HRMS admin amit (Amit Kumar Shaji, role HRMS / Administrator) → Open /leave-approval directly via the address bar | I58: Leave Management group is expanded and Leave Approval is highlighted as the active item | J58: UI | K58: Minor | L58: Medium | M58: Not Automated | O58: Not Executed
A59: TC-LOG-058 | B59: Sidebar Navigation | C59: Sidebar behaviour | D59: Sidebar collapse / expand toggle | E59: Logged in as HRMS admin amit (Amit Kumar Shaji, role HRMS / Administrator) | G59: 1. Click the sidebar collapse (hamburger) icon 2. Click it again | H59: Logged in as HRMS admin amit (Amit Kumar Shaji, role HRMS / Administrator) → Click the sidebar collapse (hamburger) icon → Click it again | I59: Sidebar collapses to icons (or hides) and the content area widens; expanding restores labels | J59: UI | K59: Trivial | L59: Low | M59: Not Automated | O59: Not Executed
A60: TC-LOG-059 | B60: Sidebar Navigation | C60: Sidebar behaviour | D60: Menu navigation updates page heading and breadcrumb | E60: Logged in as HRMS admin amit (Amit Kumar Shaji, role HRMS / Administrator) | G60: 1. Click Letter Templates then Approval Config | H60: Logged in as HRMS admin amit (Amit Kumar Shaji, role HRMS / Administrator) → Click Letter Templates then Approval Config | I60: Content heading/breadcrumb and browser tab title change to the selected page without a full reload (SPA navigation) | J60: Usability | K60: Trivial | L60: Low | M60: Not Automated | O60: Not Executed
A61: TC-LOG-060 | B61: Search Menu | C61: Search menu | D61: Search menu filters sidebar items | E61: Logged in as HRMS admin amit (Amit Kumar Shaji, role HRMS / Administrator) | F61: Leave | G61: 1. Click the Search menu box at the top of the sidebar 2. Type "Leave" | H61: Logged in as HRMS admin amit (Amit Kumar Shaji, role HRMS / Administrator) → Click the Search menu box at the top of the sidebar → Type "Leave" | I61: Only matching items are listed (Leave Types, Leave Patterns, Leave Policy, Leave Assignment, Leave Approval, Leave Ledger, Leave Reports, Leave Calendar, Apply Leave for Employee, My Workspace > Leave) | J61: Positive | K61: Critical | L61: High | M61: Not Automated | O61: Not Executed
A62: TC-LOG-061 | B62: Search Menu | C62: Search menu | D62: Search menu is case-insensitive | E62: Logged in as HRMS admin amit (Amit Kumar Shaji, role HRMS / Administrator) | G62: 1. Type "employee" in Search menu 2. Clear 3. Type "EMPLOYEE" | H62: Logged in as HRMS admin amit (Amit Kumar Shaji, role HRMS / Administrator) → Type "employee" in Search menu → Clear → Type "EMPLOYEE" | I62: Both return the same items (Employee, Employee Excel Import, Onboarding Employees, Employee Salary, …) | J62: Positive | K62: Major | L62: Medium | M62: Not Automated | O62: Not Executed
A63: TC-LOG-062 | B63: Search Menu | C63: Search menu | D63: No matching item | E63: Logged in as HRMS admin amit (Amit Kumar Shaji, role HRMS / Administrator) | F63: zzqq | G63: 1. Type "zzqq" in Search menu | H63: Logged in as HRMS admin amit (Amit Kumar Shaji, role HRMS / Administrator) → Type "zzqq" in Search menu | I63: No items are listed (or a no-results note); no error | J63: Negative | K63: Minor | L63: Low | M63: Not Automated | O63: Not Executed
A64: TC-LOG-063 | B64: Search Menu | C64: Search menu | D64: Selecting a search result navigates | E64: Logged in as HRMS admin amit (Amit Kumar Shaji, role HRMS / Administrator) | G64: 1. Type "Merge" 2. Click Merge Fields in the results | H64: Logged in as HRMS admin amit (Amit Kumar Shaji, role HRMS / Administrator) → Type "Merge" → Click Merge Fields in the results | I64: Navigates to /letters/fields | J64: Positive | K64: Major | L64: Medium | M64: Not Automated | O64: Not Executed
A65: TC-LOG-064 | B65: Search Menu | C65: Search menu | D65: Search respects role visibility | E65: Logged in as an employee with access role Staff (User Level Team Member), login created via Core HR (initial password = employee code) | G65: 1. Type "Payroll" in Search menu | H65: Logged in as an employee with access role Staff (User Level Team Member), login created via Core HR (initial password = employee code) → Type "Payroll" in Search menu | I65: Only items the Staff user is permitted to see are returned (e.g. My Workspace > Pay); admin-only payroll pages are not offered | J65: Permission | K65: Major | L65: Medium | M65: Not Automated | O65: Not Executed
A66: TC-LOG-065 | B66: Header | C66: Notifications | D66: Notification bell shows unread count and list | E66: Logged in as HRMS admin amit (Amit Kumar Shaji, role HRMS / Administrator); at least one unread notification | G66: 1. Look at the bell icon in the header 2. Click it | H66: Logged in as HRMS admin amit (Amit Kumar Shaji, role HRMS / Administrator); at least one unread notification → Look at the bell icon in the header → Click it | I66: Badge shows the unread count; dropdown lists recent notifications with text and time | J66: UI | K66: Minor | L66: Medium | M66: Not Automated | O66: Not Executed
A67: TC-LOG-066 | B67: Header | C67: Notifications | D67: Opening a notification navigates and marks it read | E67: Logged in as HRMS admin amit (Amit Kumar Shaji, role HRMS / Administrator); an unread notification exists (e.g. a leave request awaiting approval) | G67: 1. Open the bell 2. Click the notification | H67: Logged in as HRMS admin amit (Amit Kumar Shaji, role HRMS / Administrator); an unread notification exists (e.g. a leave request awaiting approval) → Open the bell → Click the notification | I67: User is taken to the related page; notification shows as read and the unread count drops by one | J67: Positive | K67: Major | L67: Medium | M67: Not Automated | O67: Not Executed
A68: TC-LOG-067 | B68: Header | C68: Notifications | D68: Real-time notification arrives without refresh | E68: Logged in as HRMS admin amit (Amit Kumar Shaji, role HRMS / Administrator) in one window; test employee signed in another | G68: 1. As the employee apply for a leave 2. Watch admin's header without refreshing | H68: Logged in as HRMS admin amit (Amit Kumar Shaji, role HRMS / Administrator) in one window; test employee signed in another → As the employee apply for a leave → Watch admin's header without refreshing | I68: Admin bell count increases and the new approval notification appears in real time | J68: Integration | K68: Major | L68: Medium | M68: Not Automated | O68: Not Executed
A69: TC-LOG-068 | B69: Header | C69: Profile menu | D69: Profile menu shows user identity and actions | E69: Logged in as HRMS admin amit (Amit Kumar Shaji, role HRMS / Administrator) | G69: 1. Click the user avatar/name in the header | H69: Logged in as HRMS admin amit (Amit Kumar Shaji, role HRMS / Administrator) → Click the user avatar/name in the header | I69: Menu shows the signed-in name (Amit Kumar Shaji) and links Profile, Change Password and Logout | J69: UI | K69: Minor | L69: Medium | M69: Not Automated | O69: Not Executed
A70: TC-LOG-069 | B70: Header | C70: Theme | D70: Dark mode toggle switches the theme | E70: Logged in as HRMS admin amit (Amit Kumar Shaji, role HRMS / Administrator) | G70: 1. Click the dark mode toggle in the header 2. Click it again | H70: Logged in as HRMS admin amit (Amit Kumar Shaji, role HRMS / Administrator) → Click the dark mode toggle in the header → Click it again | I70: Theme switches to dark and back to light; text, tables and forms stay readable | J70: UI | K70: Trivial | L70: Low | M70: Not Automated | O70: Not Executed
A71: TC-LOG-070 | B71: Header | C71: Full screen | D71: Full screen toggle enters and exits full screen | E71: Logged in as HRMS admin amit (Amit Kumar Shaji, role HRMS / Administrator) | G71: 1. Click the full screen icon in the header 2. Press Esc or click the icon again | H71: Logged in as HRMS admin amit (Amit Kumar Shaji, role HRMS / Administrator) → Click the full screen icon in the header → Press Esc or click the icon again | I71: Browser enters full screen mode and exits on the second click/Esc; layout re-flows correctly | J71: UI | K71: Trivial | L71: Low | M71: Not Automated | O71: Not Executed
A72: TC-LOG-071 | B72: Role-based Access | C72: Menu visibility | D72: HRMS (Administrator) role sees all HRMS modules and Master | E72: Logged in as HRMS admin amit (Amit Kumar Shaji, role HRMS / Administrator) | G72: 1. Sign in 2. Expand the HRMS and Master groups | H72: Logged in as HRMS admin amit (Amit Kumar Shaji, role HRMS / Administrator) → Sign in → Expand the HRMS and Master groups | I72: All modules (Core HR … Helpdesk) and Master items are visible | J72: Permission | K72: Major | L72: High | M72: Not Automated | O72: Not Executed
A73: TC-LOG-072 | B73: Role-based Access | C73: Menu visibility | D73: Staff role sees only self-service menus | E73: Logged in as an employee with access role Staff (User Level Team Member), login created via Core HR (initial password = employee code) | G73: 1. Sign in as the Staff employee 2. Inspect the sidebar | H73: Logged in as an employee with access role Staff (User Level Team Member), login created via Core HR (initial password = employee code) → Sign in as the Staff employee → Inspect the sidebar | I73: My Workspace (ESS) items, Support Tickets and Refer & Earn are visible; Core HR, Payroll, Recruitment admin, Master and approval configuration are hidden | J73: Permission | K73: Major | L73: High | M73: Not Automated | O73: Not Executed | S73: Known (access-roles review 2026-09-25): Staff access role has Employee Add/Edit/Delete ticked — confirm whether Employee menu appears for Staff and whether that is intended
A74: TC-LOG-073 | B74: Role-based Access | C74: Menu visibility | D74: Team Lead role sees self-service plus team approval menus | E74: Logged in as a Team Lead (access role Team Lead) with at least one direct report (Reports To = this Team Lead) | G74: 1. Sign in as the Team Lead 2. Inspect the sidebar | H74: Logged in as a Team Lead (access role Team Lead) with at least one direct report (Reports To = this Team Lead) → Sign in as the Team Lead → Inspect the sidebar | I74: My Workspace plus the approval pages granted to Team Lead (e.g. Leave Approval) are visible; tenant administration is hidden per policy | J74: Permission | K74: Major | L74: High | M74: Not Automated | O74: Not Executed | S74: Known (access-roles review): Team Lead role holds Access Role/Users Add/Edit/Delete and full payroll incl. Payroll Approval Confirm — verify against intended policy
A75: TC-LOG-074 | B75: Role-based Access | C75: Menu visibility | D75: Access-role change takes effect on next sign-in | E75: Logged in as HRMS admin amit (Amit Kumar Shaji, role HRMS / Administrator); a test user with Staff role | G75: 1. Change the test user's role group from Staff to Team Lead 2. Sign in as that user | H75: Logged in as HRMS admin amit (Amit Kumar Shaji, role HRMS / Administrator); a test user with Staff role → Change the test user's role group from Staff to Team Lead → Sign in as that user | I75: Sidebar now reflects Team Lead permissions; previous Staff-only view no longer applies | J75: Permission | K75: Major | L75: Medium | M75: Not Automated | O75: Not Executed
A76: TC-LOG-075 | B76: Role-based Access | C76: Direct URL without permission | D76: Staff opening /employees directly is denied | E76: Logged in as an employee with access role Staff (User Level Team Member), login created via Core HR (initial password = employee code) | G76: 1. Type https://hrms-test.progbiz.in/employees in the address bar | H76: Logged in as an employee with access role Staff (User Level Team Member), login created via Core HR (initial password = employee code) → Type https://hrms-test.progbiz.in/employees in the address bar | I76: Access denied / redirected (no employee list, no data); hiding the menu is not the only control | J76: Security | K76: Critical | L76: High | M76: Not Automated | O76: Not Executed | T76: Core HR SRS §10.4
A77: TC-LOG-076 | B77: Role-based Access | C77: Direct URL without permission | D77: Staff opening /payroll/runs directly is denied | E77: Logged in as an employee with access role Staff (User Level Team Member), login created via Core HR (initial password = employee code) | G77: 1. Open /payroll/runs by URL | H77: Logged in as an employee with access role Staff (User Level Team Member), login created via Core HR (initial password = employee code) → Open /payroll/runs by URL | I77: Access denied; no payroll data shown | J77: Security | K77: Critical | L77: High | M77: Not Automated | O77: Not Executed
A78: TC-LOG-077 | B78: Role-based Access | C78: Direct URL without permission | D78: Staff opening /access-roles directly is denied | E78: Logged in as an employee with access role Staff (User Level Team Member), login created via Core HR (initial password = employee code) | G78: 1. Open /access-roles by URL | H78: Logged in as an employee with access role Staff (User Level Team Member), login created via Core HR (initial password = employee code) → Open /access-roles by URL | I78: Access denied; role definitions cannot be viewed or edited | J78: Security | K78: Critical | L78: High | M78: Not Automated | O78: Not Executed
A79: TC-LOG-078 | B79: Role-based Access | C79: Direct URL without permission | D79: Staff opening /approval/config directly is denied | E79: Logged in as an employee with access role Staff (User Level Team Member), login created via Core HR (initial password = employee code) | G79: 1. Open /approval/config by URL | H79: Logged in as an employee with access role Staff (User Level Team Member), login created via Core HR (initial password = employee code) → Open /approval/config by URL | I79: Access denied; workflows cannot be edited | J79: Security | K79: Major | L79: Medium | M79: Not Automated | O79: Not Executed
A80: TC-LOG-079 | B80: Role-based Access | C80: Direct URL without permission | D80: Staff opening another employee's profile by GUID is denied | E80: Logged in as an employee with access role Staff (User Level Team Member), login created via Core HR (initial password = employee code); the GUID of another employee is known | G80: 1. Open /employee-view/<other employee GUID> | H80: Logged in as an employee with access role Staff (User Level Team Member), login created via Core HR (initial password = employee code); the GUID of another employee is known → Open /employee-view/<other employee GUID> | I80: Access denied; no personal data of the other employee is shown | J80: Security | K80: Critical | L80: High | M80: Not Automated | O80: Not Executed
A81: TC-LOG-080 | B81: Role-based Access | C81: Direct URL without permission | D81: Forbidden API response leaves the screen unchanged | E81: Logged in as an employee with access role Staff (User Level Team Member), login created via Core HR (initial password = employee code) | G81: 1. Trigger a call to an endpoint the role lacks (e.g. via a stale admin link) 2. Observe the UI | H81: Logged in as an employee with access role Staff (User Level Team Member), login created via Core HR (initial password = employee code) → Trigger a call to an endpoint the role lacks (e.g. via a stale admin link) → Observe the UI | I81: Endpoint returns 403; the screen shows an error/no data and never a false success message | J81: Security | K81: Major | L81: Medium | M81: Not Automated | O81: Not Executed | T81: Core HR SRS §10.4
A82: TC-LOG-081 | B82: Role-based Access | C82: Data scope | D82: Team Lead sees only own team in approvals | E82: Logged in as a Team Lead (access role Team Lead) with at least one direct report (Reports To = this Team Lead); another team has a pending leave request | G82: 1. Open Leave Approval | H82: Logged in as a Team Lead (access role Team Lead) with at least one direct report (Reports To = this Team Lead); another team has a pending leave request → Open Leave Approval | I82: Only requests of the Team Lead's reportees are listed; other teams' requests are not visible | J82: Permission | K82: Major | L82: High | M82: Not Automated | O82: Not Executed
A83: TC-LOG-082 | B83: Direct URL Access | C83: Logged-out access | D83: Logged-out visit to /employees redirects to login | E83: Logged out (fresh browser profile, no session) | G83: 1. Open https://hrms-test.progbiz.in/employees | H83: Logged out (fresh browser profile, no session) → Open https://hrms-test.progbiz.in/employees | I83: Redirected to /login; no employee data rendered (not even briefly) | J83: Security | K83: Critical | L83: High | M83: Not Automated | O83: Not Executed
A84: TC-LOG-083 | B84: Direct URL Access | C84: Logged-out access | D84: Logged-out visit to an employee profile redirects to login | E84: Logged out (fresh browser profile, no session) | G84: 1. Open /employee-view/<valid GUID> | H84: Logged out (fresh browser profile, no session) → Open /employee-view/<valid GUID> | I84: Redirected to /login; no personal data flashes before the redirect | J84: Security | K84: Critical | L84: High | M84: Not Automated | O84: Not Executed
A85: TC-LOG-084 | B85: Direct URL Access | C85: Logged-out access | D85: Logged-out visit to ESS payslips redirects to login | E85: Logged out (fresh browser profile, no session) | G85: 1. Open /ess/payslips | H85: Logged out (fresh browser profile, no session) → Open /ess/payslips | I85: Redirected to /login | J85: Security | K85: Critical | L85: High | M85: Not Automated | O85: Not Executed
A86: TC-LOG-085 | B86: Direct URL Access | C86: Logged-out access | D86: Public career page is reachable without login | E86: Logged out (fresh browser profile, no session); a Published job opening exists | G86: 1. Open /careers/<tenant-guid> | H86: Logged out (fresh browser profile, no session); a Published job opening exists → Open /careers/<tenant-guid> | I86: Career page shows published openings with Apply Now; no internal menus or data | J86: Positive | K86: Major | L86: Medium | M86: Automated (Linear Run) | N86: Linear 014 Job Applications — candidateSelfApplies (withVisitor) | O86: Passed (19 Oct 2026)
A87: TC-LOG-086 | B87: Direct URL Access | C87: Invalid route | D87: Unknown route shows the not-found page | E87: Logged in as HRMS admin amit (Amit Kumar Shaji, role HRMS / Administrator) | G87: 1. Open /does-not-exist | H87: Logged in as HRMS admin amit (Amit Kumar Shaji, role HRMS / Administrator) → Open /does-not-exist | I87: "Sorry, there's nothing at this address" is shown; sidebar still usable; no app error bar | J87: Negative | K87: Minor | L87: Low | M87: Not Automated | O87: Not Executed
A88: TC-LOG-087 | B88: Direct URL Access | C88: Invalid route | D88: Malformed GUID in employee route | E88: Logged in as HRMS admin amit (Amit Kumar Shaji, role HRMS / Administrator) | G88: 1. Open /employee-view/not-a-guid | H88: Logged in as HRMS admin amit (Amit Kumar Shaji, role HRMS / Administrator) → Open /employee-view/not-a-guid | I88: Friendly not-found / invalid record message; no unhandled error or stack trace | J88: Negative | K88: Minor | L88: Medium | M88: Not Automated | O88: Not Executed
A89: TC-LOG-088 | B89: Browser Navigation | C89: Back / forward | D89: Back and Forward move between visited pages | E89: Logged in as HRMS admin amit (Amit Kumar Shaji, role HRMS / Administrator) | G89: 1. Open Employee 2. Open Worker Directory 3. Press Back 4. Press Forward | H89: Logged in as HRMS admin amit (Amit Kumar Shaji, role HRMS / Administrator) → Open Employee → Open Worker Directory → Press Back → Press Forward | I89: Back shows the Employee list, Forward returns to Worker Directory; content and sidebar highlight match each page | J89: Positive | K89: Major | L89: Medium | M89: Not Automated | O89: Not Executed
A90: TC-LOG-089 | B90: Browser Navigation | C90: Back / forward | D90: Back after saving a form does not resubmit | E90: Logged in as HRMS admin amit (Amit Kumar Shaji, role HRMS / Administrator) | G90: 1. Create a duty handover and Save 2. Press browser Back | H90: Logged in as HRMS admin amit (Amit Kumar Shaji, role HRMS / Administrator) → Create a duty handover and Save → Press browser Back | I90: No second record is created; the form is shown empty or the list is shown | J90: Negative | K90: Major | L90: High | M90: Not Automated | O90: Not Executed
A91: TC-LOG-090 | B91: Browser Navigation | C91: Refresh | D91: Refresh on a deep page keeps the page and filters | E91: Logged in as HRMS admin amit (Amit Kumar Shaji, role HRMS / Administrator) | G91: 1. Open Duty Handover 2. Set Status filter to Pending 3. Press F5 | H91: Logged in as HRMS admin amit (Amit Kumar Shaji, role HRMS / Administrator) → Open Duty Handover → Set Status filter to Pending → Press F5 | I91: Page reloads on /employee-handover signed in; data loads (filters may reset to defaults) with no error | J91: Positive | K91: Major | L91: Medium | M91: Not Automated | O91: Not Executed
A92: TC-LOG-091 | B92: Browser Navigation | C92: Refresh | D92: Refresh on a half-filled form does not save | E92: Logged in as HRMS admin amit (Amit Kumar Shaji, role HRMS / Administrator) | G92: 1. Open New Employee 2. Fill First Name only 3. Press F5 | H92: Logged in as HRMS admin amit (Amit Kumar Shaji, role HRMS / Administrator) → Open New Employee → Fill First Name only → Press F5 | I92: Form reloads empty (or a leave-page warning is shown); no partial employee is created | J92: Negative | K92: Minor | L92: Medium | M92: Not Automated | O92: Not Executed

Sheet Core HR
A1: Test ID | B1: Page / Sub-module | C1: Scenario | D1: Description | E1: Preconditions | F1: Test Data | G1: Test Steps | H1: Steps to Reproduce | I1: Expected Result | J1: Type | K1: Severity | L1: Priority | M1: Automation Status | N1: Automation Reference | O1: Execution Status | P1: Actual Result | Q1: Tested By / Date | R1: Route | S1: Remarks | T1: SRS Ref
A2: TC-CHR-001 | B2: Employee | C2: Page load | D2: Employee list page opens and renders | E2: Logged in as HRMS admin amit (Amit Kumar Shaji, role HRMS / Administrator) | G2: 1. Open HRMS > Core HR > Employee | H2: Logged in as HRMS admin amit (Amit Kumar Shaji, role HRMS / Administrator) → Open HRMS > Core HR > Employee | I2: Heading shown; grid with columns Sl.No, Employee Code, Employee Name, Department Name, Designation, Status, Actions; New Employee button; loading clears; no app error | J2: UI | K2: Major | L2: High | M2: Automated (Page Check) | N2: Linear 001 Employee — page check | O2: Passed (19 Oct 2026) | R2: /employees
A3: TC-CHR-002 | B3: Employee | C3: List | D3: Default sort is Employee Code ascending | E3: Logged in as HRMS admin amit (Amit Kumar Shaji, role HRMS / Administrator) | G3: 1. Open Employee list 2. Observe the order of the Employee Code column | H3: Logged in as HRMS admin amit (Amit Kumar Shaji, role HRMS / Administrator) → Open Employee list → Observe the order of the Employee Code column | I3: Rows are sorted by Employee Code ascending with a sort indicator on that column | J3: Positive | K3: Minor | L3: Low | M3: Not Automated | O3: Not Executed | R3: /employees | T3: §4.2
A4: TC-CHR-003 | B4: Employee | C4: List | D4: Sort by each sortable column | E4: Logged in as HRMS admin amit (Amit Kumar Shaji, role HRMS / Administrator) | G4: 1. Click Employee Code header 2. Click again 3. Repeat for Employee Name, Department Name, Designation | H4: Logged in as HRMS admin amit (Amit Kumar Shaji, role HRMS / Administrator) → Click Employee Code header → Click again → Repeat for Employee Name, Department Name, Designation | I4: Each click toggles ascending/descending; sort indicator updates; data re-ordered server-side | J4: Positive | K4: Major | L4: Medium | M4: Not Automated | O4: Not Executed | R4: /employees | T4: §4.2
A5: TC-CHR-004 | B5: Employee | C5: Search | D5: Quick search by employee name | E5: Logged in as HRMS admin amit (Amit Kumar Shaji, role HRMS / Administrator); run employee exists | F5: e.g. "Varghese" | G5: 1. Type part of the run employee's name in the quick-search box | H5: Logged in as HRMS admin amit (Amit Kumar Shaji, role HRMS / Administrator); run employee exists → Type part of the run employee's name in the quick-search box | I5: Grid shows only matching employees; count updates | J5: Positive | K5: Critical | L5: High | M5: Not Automated | O5: Not Executed | R5: /employees | T5: FR-CH-023
A6: TC-CHR-005 | B6: Employee | C6: Search | D6: Quick search by employee code | E6: Logged in as HRMS admin amit (Amit Kumar Shaji, role HRMS / Administrator) | F6: e.g. pbhrms0305 | G6: 1. Type a full employee code in quick search | H6: Logged in as HRMS admin amit (Amit Kumar Shaji, role HRMS / Administrator) → Type a full employee code in quick search | I6: Exactly the employee with that code is listed | J6: Positive | K6: Critical | L6: High | M6: Automated (Linear Run) | N6: Linear 001 Employee — createRunEmployee | O6: Passed (19 Oct 2026) | R6: /employees | T6: FR-CH-023
A7: TC-CHR-006 | B7: Employee | C7: Search | D7: Quick search by phone and by e-mail | E7: Logged in as HRMS admin amit (Amit Kumar Shaji, role HRMS / Administrator) | G7: 1. Search the run employee's phone 2. Clear 3. Search their e-mail | H7: Logged in as HRMS admin amit (Amit Kumar Shaji, role HRMS / Administrator) → Search the run employee's phone → Clear → Search their e-mail | I7: Both searches return the run employee | J7: Positive | K7: Major | L7: Medium | M7: Not Automated | O7: Not Executed | R7: /employees | T7: FR-CH-023
A8: TC-CHR-007 | B8: Employee | C8: Search | D8: Quick search with no match | E8: Logged in as HRMS admin amit (Amit Kumar Shaji, role HRMS / Administrator) | G8: 1. Type "zzqqxx" in quick search | H8: Logged in as HRMS admin amit (Amit Kumar Shaji, role HRMS / Administrator) → Type "zzqqxx" in quick search | I8: Empty-state row / "no records" message; no error | J8: Negative | K8: Minor | L8: Low | M8: Not Automated | O8: Not Executed | R8: /employees
A9: TC-CHR-008 | B9: Employee | C9: Filter | D9: Advanced filter drawer narrows the list | E9: Logged in as HRMS admin amit (Amit Kumar Shaji, role HRMS / Administrator) | G9: 1. Open the filter drawer 2. Choose Branch Main Branch and Designation SOFTWARE TESTER 3. Click Apply Filters | H9: Logged in as HRMS admin amit (Amit Kumar Shaji, role HRMS / Administrator) → Open the filter drawer → Choose Branch Main Branch and Designation SOFTWARE TESTER → Click Apply Filters | I9: Only matching employees listed; badge shows 2 active filters | J9: Positive | K9: Major | L9: Medium | M9: Not Automated | O9: Not Executed | R9: /employees | T9: FR-CH-024
A10: TC-CHR-009 | B10: Employee | C10: Filter | D10: Closing the drawer without Apply changes nothing | E10: Logged in as HRMS admin amit (Amit Kumar Shaji, role HRMS / Administrator) | G10: 1. Open the filter drawer 2. Change Department 3. Close the drawer without Apply | H10: Logged in as HRMS admin amit (Amit Kumar Shaji, role HRMS / Administrator) → Open the filter drawer → Change Department → Close the drawer without Apply | I10: Grid and active-filter badge unchanged | J10: Positive | K10: Minor | L10: Low | M10: Not Automated | O10: Not Executed | R10: /employees | T10: FR-CH-024
A11: TC-CHR-010 | B11: Employee | C11: Filter | D11: Reset clears all drawer filters | E11: Logged in as HRMS admin amit (Amit Kumar Shaji, role HRMS / Administrator); filters applied | G11: 1. Open the filter drawer 2. Click Reset | H11: Logged in as HRMS admin amit (Amit Kumar Shaji, role HRMS / Administrator); filters applied → Open the filter drawer → Click Reset | I11: All narrowing filters cleared; badge disappears; full list shown | J11: Positive | K11: Minor | L11: Low | M11: Not Automated | O11: Not Executed | R11: /employees
A12: TC-CHR-011 | B12: Employee | C12: Filter | D12: Joined-from after joined-to | E12: Logged in as HRMS admin amit (Amit Kumar Shaji, role HRMS / Administrator) | G12: 1. Open filter drawer 2. Set Joined From 2026-10-01 and Joined To 2026-09-01 3. Apply | H12: Logged in as HRMS admin amit (Amit Kumar Shaji, role HRMS / Administrator) → Open filter drawer → Set Joined From 2026-10-01 and Joined To 2026-09-01 → Apply | I12: Validation message or empty result; no server error | J12: Negative | K12: Minor | L12: Low | M12: Not Automated | O12: Not Executed | R12: /employees
A13: TC-CHR-012 | B13: Employee | C13: Archived | D13: Archived employees hidden by default and shown with Include archived | E13: Logged in as HRMS admin amit (Amit Kumar Shaji, role HRMS / Administrator); an archived (exited) employee exists | G13: 1. Open Employee list 2. Search the archived employee 3. Switch on Include archived | H13: Logged in as HRMS admin amit (Amit Kumar Shaji, role HRMS / Administrator); an archived (exited) employee exists → Open Employee list → Search the archived employee → Switch on Include archived | I13: Not found by default; listed once Include archived is on; the toggle is not counted in the filter badge | J13: Positive | K13: Major | L13: Medium | M13: Not Automated | O13: Not Executed | R13: /employees | T13: FR-CH-025
A14: TC-CHR-013 | B14: Employee | C14: Paging | D14: Pagination and page size | E14: Logged in as HRMS admin amit (Amit Kumar Shaji, role HRMS / Administrator); more than 10 employees | G14: 1. Change page size to 25 2. Go to page 2 3. Run a search | H14: Logged in as HRMS admin amit (Amit Kumar Shaji, role HRMS / Administrator); more than 10 employees → Change page size to 25 → Go to page 2 → Run a search | I14: Page size applies and is preserved across the search; pager shows total count and page index | J14: Positive | K14: Major | L14: Medium | M14: Not Automated | O14: Not Executed | R14: /employees | T14: FR-CH-021
A15: TC-CHR-014 | B15: Employee | C15: Row actions | D15: Edit icon opens the employee Edit form | E15: Logged in as HRMS admin amit (Amit Kumar Shaji, role HRMS / Administrator) | G15: 1. Click the pencil icon on the run employee row | H15: Logged in as HRMS admin amit (Amit Kumar Shaji, role HRMS / Administrator) → Click the pencil icon on the run employee row | I15: Navigates to /employee/<guid> with the form pre-filled | J15: Positive | K15: Critical | L15: High | M15: Not Automated | O15: Not Executed | R15: /employees
A16: TC-CHR-015 | B16: Employee | C16: Row actions | D16: Clicking the employee name opens the read-only profile | E16: Logged in as HRMS admin amit (Amit Kumar Shaji, role HRMS / Administrator) | G16: 1. Click the run employee's name/view action | H16: Logged in as HRMS admin amit (Amit Kumar Shaji, role HRMS / Administrator) → Click the run employee's name/view action | I16: Navigates to /employee-view/<guid> | J16: Positive | K16: Major | L16: Medium | M16: Not Automated | O16: Not Executed | R16: /employees
A17: TC-CHR-016 | B17: Employee | C17: Row actions | D17: Delete asks for confirmation; Cancel keeps the employee | E17: Logged in as HRMS admin amit (Amit Kumar Shaji, role HRMS / Administrator); a disposable test employee exists | G17: 1. Click the delete icon on the test employee row 2. Click No/Cancel in the confirmation | H17: Logged in as HRMS admin amit (Amit Kumar Shaji, role HRMS / Administrator); a disposable test employee exists → Click the delete icon on the test employee row → Click No/Cancel in the confirmation | I17: Confirmation names the employee; on Cancel nothing is deleted and the row remains | J17: Negative | K17: Major | L17: High | M17: Not Automated | O17: Not Executed | R17: /employees
A18: TC-CHR-017 | B18: Employee | C18: Row actions | D18: Delete a disposable employee after confirmation | E18: Logged in as HRMS admin amit (Amit Kumar Shaji, role HRMS / Administrator); a disposable test employee with no transactions | G18: 1. Click delete on the test employee 2. Confirm Yes | H18: Logged in as HRMS admin amit (Amit Kumar Shaji, role HRMS / Administrator); a disposable test employee with no transactions → Click delete on the test employee → Confirm Yes | I18: Success message; employee no longer listed; their login no longer works | J18: Positive | K18: Major | L18: Medium | M18: Not Automated | O18: Not Executed | R18: /employees | S18: Use only a throwaway employee created for this test
A19: TC-CHR-018 | B19: Employee | C19: Row actions | D19: Delete of an employee with transactions is refused or soft | E19: Logged in as HRMS admin amit (Amit Kumar Shaji, role HRMS / Administrator); employee with leave/payroll history | G19: 1. Click delete on that employee 2. Confirm | H19: Logged in as HRMS admin amit (Amit Kumar Shaji, role HRMS / Administrator); employee with leave/payroll history → Click delete on that employee → Confirm | I19: Delete is refused with a clear message, or the employee is soft-deleted so history in Leave/Payroll stays intact | J19: Negative | K19: Minor | L19: Medium | M19: Not Automated | O19: Not Executed | R19: /employees
A20: TC-CHR-019 | B20: Employee | C20: Status badge | D20: Status column reflects lifecycle status | E20: Logged in as HRMS admin amit (Amit Kumar Shaji, role HRMS / Administrator); employees in Active and Pre-Employee status | G20: 1. Open the list 2. Compare the Status badge with each employee's status | H20: Logged in as HRMS admin amit (Amit Kumar Shaji, role HRMS / Administrator); employees in Active and Pre-Employee status → Open the list → Compare the Status badge with each employee's status | I20: Active and Pre-Employee badges are shown correctly with distinct colours | J20: UI | K20: Trivial | L20: Low | M20: Not Automated | O20: Not Executed | R20: /employees
A21: TC-CHR-020 | B21: Employee | C21: Create employee | D21: Create an employee with all mandatory fields | E21: Logged in as HRMS admin amit (Amit Kumar Shaji, role HRMS / Administrator); on Core HR > Employee, New Employee form (/employee) open | F21: Role Group Staff, User Level Team Member, Reports To Amit Kumar Shaji, Designation SOFTWARE TESTER, Branch Main Branch, First Name, Last Name, Display Name, Date of Birth, Gender, Phone, Email, Employment Type Full Time Employee, Status Active, Joining Date; Name: realistic person e.g. Rohan Varghese; Email: rohan.varghese@example.com | G21: 1. Choose Role Group and User Level 2. Pick Reports To 3. Fill Designation, Branch, names, Date of Birth, Gender, Phone (Same as Phone ON), Email 4. Choose Work Location, Employment Type, Status, Joining Date 5. Fill present address, tick Same as Present 6. Set Login Username, keep Can Login ticked 7. Save | H21: Logged in as HRMS admin amit (Amit Kumar Shaji, role HRMS / Administrator); on Core HR > Employee, New Employee form (/employee) open → Choose Role Group and User Level → Pick Reports To → Fill Designation, Branch, names, Date of Birth, Gender, Phone (Same as Phone ON), Email → Choose Work Location, Employment Type, Status, Joining Date → Fill present address, tick Same as Present → Set Login Username, keep Can Login ticked → Save | I21: Success / redirect to /employees; employee listed with a new auto-generated code (e.g. pbhrms0xxx); "Login created for <name>" dialog shows username and password = code | J21: Positive | K21: Critical | L21: High | M21: Automated (Linear Run) | N21: Linear 001 Employee — createRunEmployee | O21: Passed (19 Oct 2026) | R21: /employee
A22: TC-CHR-021 | B22: Employee | C22: Create employee | D22: Employee Code is auto-generated and read-only | E22: Logged in as HRMS admin amit (Amit Kumar Shaji, role HRMS / Administrator); on Core HR > Employee, New Employee form (/employee) open | G22: 1. Observe the Employee Code field on the new form | H22: Logged in as HRMS admin amit (Amit Kumar Shaji, role HRMS / Administrator); on Core HR > Employee, New Employee form (/employee) open → Observe the Employee Code field on the new form | I22: Employee Code is pre-filled/assigned automatically and the input is disabled | J22: UI | K22: Major | L22: High | M22: Automated (Linear Run) | N22: Linear 001 Employee — createRunEmployee | O22: Passed (19 Oct 2026) | R22: /employee | S22: SRS FR-CH-002 says code is overridable; live build disables it — confirm intended behaviour
A23: TC-CHR-022 | B23: Employee | C23: Create employee | D23: Reports To and login fields appear after Role Group + User Level | E23: Logged in as HRMS admin amit (Amit Kumar Shaji, role HRMS / Administrator); on Core HR > Employee, New Employee form (/employee) open | G23: 1. Open the form 2. Observe Reports To / Login Username 3. Choose Role Group Staff and User Level Team Member | H23: Logged in as HRMS admin amit (Amit Kumar Shaji, role HRMS / Administrator); on Core HR > Employee, New Employee form (/employee) open → Open the form → Observe Reports To / Login Username → Choose Role Group Staff and User Level Team Member | I23: Reports To, Login Username, Can Login (ticked by default) and All Branches render only after both are chosen; Reports To options load | J23: UI | K23: Major | L23: High | M23: Automated (Linear Run) | N23: Linear 001 Employee — createRunEmployee | O23: Passed (19 Oct 2026) | R23: /employee
A24: TC-CHR-023 | B24: Employee | C24: Create employee | D24: Same as Phone copies phone to WhatsApp | E24: Logged in as HRMS admin amit (Amit Kumar Shaji, role HRMS / Administrator); on Core HR > Employee, New Employee form (/employee) open | F24: Phone: 9876543210 | G24: 1. Enter Phone 2. Tick Same as Phone | H24: Logged in as HRMS admin amit (Amit Kumar Shaji, role HRMS / Administrator); on Core HR > Employee, New Employee form (/employee) open → Enter Phone → Tick Same as Phone | I24: WhatsApp number equals the phone and is not separately editable while ticked | J24: Positive | K24: Major | L24: Medium | M24: Automated (Linear Run) | N24: Linear 001 Employee — createRunEmployee | O24: Passed (19 Oct 2026) | R24: /employee
A25: TC-CHR-024 | B25: Employee | C25: Create employee | D25: Same as Present copies the address | E25: Logged in as HRMS admin amit (Amit Kumar Shaji, role HRMS / Administrator); on Core HR > Employee, New Employee form (/employee) open | G25: 1. Fill present Country/State/City/Pincode/Address lines 2. Tick Same as Present 3. Save 4. Open the profile Address tab | H25: Logged in as HRMS admin amit (Amit Kumar Shaji, role HRMS / Administrator); on Core HR > Employee, New Employee form (/employee) open → Fill present Country/State/City/Pincode/Address lines → Tick Same as Present → Save → Open the profile Address tab | I25: Permanent address inputs hide; saved permanent address equals present address | J25: Positive | K25: Major | L25: Medium | M25: Automated (Linear Run) | N25: Linear 001 Employee — createRunEmployee | O25: Passed (19 Oct 2026) | R25: /employee | T25: FR-CH-014
A26: TC-CHR-025 | B26: Employee | C26: Create employee | D26: Address Country → State → City cascade | E26: Logged in as HRMS admin amit (Amit Kumar Shaji, role HRMS / Administrator); on Core HR > Employee, New Employee form (/employee) open | G26: 1. Choose Country India 2. Open State 3. Choose Kerala 4. Open City | H26: Logged in as HRMS admin amit (Amit Kumar Shaji, role HRMS / Administrator); on Core HR > Employee, New Employee form (/employee) open → Choose Country India → Open State → Choose Kerala → Open City | I26: State list loads only after country; City list only after state; changing Country clears State and City | J26: Positive | K26: Major | L26: Medium | M26: Not Automated | O26: Not Executed | R26: /employee
A27: TC-CHR-026 | B27: Employee | C27: Create employee | D27: Create with all optional fields filled | E27: Logged in as HRMS admin amit (Amit Kumar Shaji, role HRMS / Administrator); on Core HR > Employee, New Employee form (/employee) open | F27: Honorific Mr; Marital Single; Work Location Office | G27: 1. Fill all mandatory fields 2. Also fill Honorific, Marital Status, Work Location, both addresses, photo 3. Save | H27: Logged in as HRMS admin amit (Amit Kumar Shaji, role HRMS / Administrator); on Core HR > Employee, New Employee form (/employee) open → Fill all mandatory fields → Also fill Honorific, Marital Status, Work Location, both addresses, photo → Save | I27: Employee saved; all optional values visible on the profile view | J27: Positive | K27: Major | L27: Medium | M27: Not Automated | O27: Not Executed | R27: /employee
A28: TC-CHR-027 | B28: Employee | C28: Create employee | D28: Create employee with status Pre-Employee | E28: Logged in as HRMS admin amit (Amit Kumar Shaji, role HRMS / Administrator); on Core HR > Employee, New Employee form (/employee) open | G28: 1. Fill mandatory fields 2. Choose Status Pre-Employee 3. Save | H28: Logged in as HRMS admin amit (Amit Kumar Shaji, role HRMS / Administrator); on Core HR > Employee, New Employee form (/employee) open → Fill mandatory fields → Choose Status Pre-Employee → Save | I28: Employee saved with Pre-Employee badge in list and profile | J28: Positive | K28: Major | L28: Medium | M28: Not Automated | O28: Not Executed | R28: /employee | S28: Live Status options: Active / Pre-Employee (SRS also allows Probation on create)
A29: TC-CHR-028 | B29: Employee | C29: Create employee | D29: Joined history event written on create | E29: Logged in as HRMS admin amit (Amit Kumar Shaji, role HRMS / Administrator); employee just created | G29: 1. Open the new employee's profile 2. Open History / Lifecycle tab | H29: Logged in as HRMS admin amit (Amit Kumar Shaji, role HRMS / Administrator); employee just created → Open the new employee's profile → Open History / Lifecycle tab | I29: A single "Joined" event with the joining date is shown | J29: Integration | K29: Minor | L29: Low | M29: Not Automated | O29: Not Executed | R29: /employee | T29: §4.8
A30: TC-CHR-029 | B30: Employee | C30: Create employee | D30: Success redirects to the list | E30: Logged in as HRMS admin amit (Amit Kumar Shaji, role HRMS / Administrator); on Core HR > Employee, New Employee form (/employee) open | G30: 1. Create a valid employee 2. Close the login dialog | H30: Logged in as HRMS admin amit (Amit Kumar Shaji, role HRMS / Administrator); on Core HR > Employee, New Employee form (/employee) open → Create a valid employee → Close the login dialog | I30: User returns to /employees and the new employee is findable by code | J30: UI | K30: Trivial | L30: Low | M30: Automated (Linear Run) | N30: Linear 001 Employee — createRunEmployee | O30: Passed (19 Oct 2026) | R30: /employee
A31: TC-CHR-030 | B31: Employee | C31: Create employee | D31: Save is guarded against double click | E31: Logged in as HRMS admin amit (Amit Kumar Shaji, role HRMS / Administrator); on Core HR > Employee, New Employee form (/employee) open | G31: 1. Fill a valid employee 2. Double-click Save rapidly | H31: Logged in as HRMS admin amit (Amit Kumar Shaji, role HRMS / Administrator); on Core HR > Employee, New Employee form (/employee) open → Fill a valid employee → Double-click Save rapidly | I31: Only one employee is created (no duplicate code/phone error, no second row) | J31: Negative | K31: Minor | L31: Medium | M31: Not Automated | O31: Not Executed | R31: /employee | T31: FR-CH-013
A32: TC-CHR-031 | B32: Employee | C32: Create employee | D32: Cancel / navigate away does not save | E32: Logged in as HRMS admin amit (Amit Kumar Shaji, role HRMS / Administrator); on Core HR > Employee, New Employee form (/employee) open | G32: 1. Fill some fields 2. Click Back/Cancel or a sidebar link | H32: Logged in as HRMS admin amit (Amit Kumar Shaji, role HRMS / Administrator); on Core HR > Employee, New Employee form (/employee) open → Fill some fields → Click Back/Cancel or a sidebar link | I32: No employee is created | J32: Negative | K32: Minor | L32: Low | M32: Not Automated | O32: Not Executed | R32: /employee
A33: TC-CHR-032 | B33: Employee | C33: Mandatory fields | D33: First Name missing blocks save | E33: Logged in as HRMS admin amit (Amit Kumar Shaji, role HRMS / Administrator); on Core HR > Employee, New Employee form (/employee) open | F33: Role Group Staff, User Level Team Member, Reports To Amit Kumar Shaji, Designation SOFTWARE TESTER, Branch Main Branch, First Name, Last Name, Display Name, Date of Birth, Gender, Phone, Email, Employment Type Full Time Employee, Status Active, Joining Date minus First Name | G33: 1. Fill every mandatory field except First Name 2. Click Save | H33: Logged in as HRMS admin amit (Amit Kumar Shaji, role HRMS / Administrator); on Core HR > Employee, New Employee form (/employee) open → Fill every mandatory field except First Name → Click Save | I33: Save blocked; message "Please Enter First Name."; field highlighted and scrolled into view; no employee created | J33: Validation | K33: Major | L33: High | M33: Not Automated | O33: Not Executed | R33: /employee | T33: Core HR SRS §10.2
A34: TC-CHR-033 | B34: Employee | C34: Mandatory fields | D34: Display Name missing blocks save | E34: Logged in as HRMS admin amit (Amit Kumar Shaji, role HRMS / Administrator); on Core HR > Employee, New Employee form (/employee) open | F34: Role Group Staff, User Level Team Member, Reports To Amit Kumar Shaji, Designation SOFTWARE TESTER, Branch Main Branch, First Name, Last Name, Display Name, Date of Birth, Gender, Phone, Email, Employment Type Full Time Employee, Status Active, Joining Date minus Display Name | G34: 1. Fill every mandatory field except Display Name 2. Click Save | H34: Logged in as HRMS admin amit (Amit Kumar Shaji, role HRMS / Administrator); on Core HR > Employee, New Employee form (/employee) open → Fill every mandatory field except Display Name → Click Save | I34: Save blocked; message "Please enter a Display Name."; field highlighted and scrolled into view; no employee created | J34: Validation | K34: Major | L34: High | M34: Not Automated | O34: Not Executed | R34: /employee | T34: Core HR SRS §10.2
A35: TC-CHR-034 | B35: Employee | C35: Mandatory fields | D35: Date of Birth missing blocks save | E35: Logged in as HRMS admin amit (Amit Kumar Shaji, role HRMS / Administrator); on Core HR > Employee, New Employee form (/employee) open | F35: Role Group Staff, User Level Team Member, Reports To Amit Kumar Shaji, Designation SOFTWARE TESTER, Branch Main Branch, First Name, Last Name, Display Name, Date of Birth, Gender, Phone, Email, Employment Type Full Time Employee, Status Active, Joining Date minus Date of Birth | G35: 1. Fill every mandatory field except Date of Birth 2. Click Save | H35: Logged in as HRMS admin amit (Amit Kumar Shaji, role HRMS / Administrator); on Core HR > Employee, New Employee form (/employee) open → Fill every mandatory field except Date of Birth → Click Save | I35: Save blocked; message "Please enter the Date of Birth."; field highlighted and scrolled into view; no employee created | J35: Validation | K35: Major | L35: High | M35: Not Automated | O35: Not Executed | R35: /employee | T35: Core HR SRS §10.2
A36: TC-CHR-035 | B36: Employee | C36: Mandatory fields | D36: Phone missing blocks save | E36: Logged in as HRMS admin amit (Amit Kumar Shaji, role HRMS / Administrator); on Core HR > Employee, New Employee form (/employee) open | F36: Role Group Staff, User Level Team Member, Reports To Amit Kumar Shaji, Designation SOFTWARE TESTER, Branch Main Branch, First Name, Last Name, Display Name, Date of Birth, Gender, Phone, Email, Employment Type Full Time Employee, Status Active, Joining Date minus Phone | G36: 1. Fill every mandatory field except Phone 2. Click Save | H36: Logged in as HRMS admin amit (Amit Kumar Shaji, role HRMS / Administrator); on Core HR > Employee, New Employee form (/employee) open → Fill every mandatory field except Phone → Click Save | I36: Save blocked; message "phone required / The phone number is not valid."; field highlighted and scrolled into view; no employee created | J36: Validation | K36: Major | L36: High | M36: Not Automated | O36: Not Executed | R36: /employee | T36: Core HR SRS §10.2
A37: TC-CHR-036 | B37: Employee | C37: Mandatory fields | D37: Email missing blocks save | E37: Logged in as HRMS admin amit (Amit Kumar Shaji, role HRMS / Administrator); on Core HR > Employee, New Employee form (/employee) open | F37: Role Group Staff, User Level Team Member, Reports To Amit Kumar Shaji, Designation SOFTWARE TESTER, Branch Main Branch, First Name, Last Name, Display Name, Date of Birth, Gender, Phone, Email, Employment Type Full Time Employee, Status Active, Joining Date minus Email | G37: 1. Fill every mandatory field except Email 2. Click Save | H37: Logged in as HRMS admin amit (Amit Kumar Shaji, role HRMS / Administrator); on Core HR > Employee, New Employee form (/employee) open → Fill every mandatory field except Email → Click Save | I37: Save blocked; message "Please provide a valid email address."; field highlighted and scrolled into view; no employee created | J37: Validation | K37: Major | L37: High | M37: Not Automated | O37: Not Executed | R37: /employee | T37: Core HR SRS §10.2
A38: TC-CHR-037 | B38: Employee | C38: Mandatory fields | D38: Role Group missing blocks save | E38: Logged in as HRMS admin amit (Amit Kumar Shaji, role HRMS / Administrator); on Core HR > Employee, New Employee form (/employee) open | F38: Role Group Staff, User Level Team Member, Reports To Amit Kumar Shaji, Designation SOFTWARE TESTER, Branch Main Branch, First Name, Last Name, Display Name, Date of Birth, Gender, Phone, Email, Employment Type Full Time Employee, Status Active, Joining Date minus Role Group | G38: 1. Fill every mandatory field except Role Group 2. Click Save | H38: Logged in as HRMS admin amit (Amit Kumar Shaji, role HRMS / Administrator); on Core HR > Employee, New Employee form (/employee) open → Fill every mandatory field except Role Group → Click Save | I38: Save blocked; message "Please choose Role Group."; field highlighted and scrolled into view; no employee created | J38: Validation | K38: Major | L38: High | M38: Not Automated | O38: Not Executed | R38: /employee | T38: Core HR SRS §10.2
A39: TC-CHR-038 | B39: Employee | C39: Mandatory fields | D39: User Level missing blocks save | E39: Logged in as HRMS admin amit (Amit Kumar Shaji, role HRMS / Administrator); on Core HR > Employee, New Employee form (/employee) open | F39: Role Group Staff, User Level Team Member, Reports To Amit Kumar Shaji, Designation SOFTWARE TESTER, Branch Main Branch, First Name, Last Name, Display Name, Date of Birth, Gender, Phone, Email, Employment Type Full Time Employee, Status Active, Joining Date minus User Level | G39: 1. Fill every mandatory field except User Level 2. Click Save | H39: Logged in as HRMS admin amit (Amit Kumar Shaji, role HRMS / Administrator); on Core HR > Employee, New Employee form (/employee) open → Fill every mandatory field except User Level → Click Save | I39: Save blocked; message "Please choose user level"; field highlighted and scrolled into view; no employee created | J39: Validation | K39: Major | L39: High | M39: Not Automated | O39: Not Executed | R39: /employee | T39: Core HR SRS §10.2
A40: TC-CHR-039 | B40: Employee | C40: Mandatory fields | D40: Reports To missing blocks save | E40: Logged in as HRMS admin amit (Amit Kumar Shaji, role HRMS / Administrator); on Core HR > Employee, New Employee form (/employee) open | F40: Role Group Staff, User Level Team Member, Reports To Amit Kumar Shaji, Designation SOFTWARE TESTER, Branch Main Branch, First Name, Last Name, Display Name, Date of Birth, Gender, Phone, Email, Employment Type Full Time Employee, Status Active, Joining Date minus Reports To | G40: 1. Fill every mandatory field except Reports To 2. Click Save | H40: Logged in as HRMS admin amit (Amit Kumar Shaji, role HRMS / Administrator); on Core HR > Employee, New Employee form (/employee) open → Fill every mandatory field except Reports To → Click Save | I40: Save blocked; message "Please choose a report person from a higher level"; field highlighted and scrolled into view; no employee created | J40: Validation | K40: Major | L40: High | M40: Not Automated | O40: Not Executed | R40: /employee | T40: Core HR SRS §10.2
A41: TC-CHR-040 | B41: Employee | C41: Mandatory fields | D41: Designation missing blocks save | E41: Logged in as HRMS admin amit (Amit Kumar Shaji, role HRMS / Administrator); on Core HR > Employee, New Employee form (/employee) open | F41: Role Group Staff, User Level Team Member, Reports To Amit Kumar Shaji, Designation SOFTWARE TESTER, Branch Main Branch, First Name, Last Name, Display Name, Date of Birth, Gender, Phone, Email, Employment Type Full Time Employee, Status Active, Joining Date minus Designation | G41: 1. Fill every mandatory field except Designation 2. Click Save | H41: Logged in as HRMS admin amit (Amit Kumar Shaji, role HRMS / Administrator); on Core HR > Employee, New Employee form (/employee) open → Fill every mandatory field except Designation → Click Save | I41: Save blocked; message "designation required"; field highlighted and scrolled into view; no employee created | J41: Validation | K41: Major | L41: High | M41: Not Automated | O41: Not Executed | R41: /employee | T41: Core HR SRS §10.2
A42: TC-CHR-041 | B42: Employee | C42: Mandatory fields | D42: Branch missing blocks save | E42: Logged in as HRMS admin amit (Amit Kumar Shaji, role HRMS / Administrator); on Core HR > Employee, New Employee form (/employee) open | F42: Role Group Staff, User Level Team Member, Reports To Amit Kumar Shaji, Designation SOFTWARE TESTER, Branch Main Branch, First Name, Last Name, Display Name, Date of Birth, Gender, Phone, Email, Employment Type Full Time Employee, Status Active, Joining Date minus Branch | G42: 1. Fill every mandatory field except Branch 2. Click Save | H42: Logged in as HRMS admin amit (Amit Kumar Shaji, role HRMS / Administrator); on Core HR > Employee, New Employee form (/employee) open → Fill every mandatory field except Branch → Click Save | I42: Save blocked; message "branch required"; field highlighted and scrolled into view; no employee created | J42: Validation | K42: Major | L42: High | M42: Not Automated | O42: Not Executed | R42: /employee | T42: Core HR SRS §10.2
A43: TC-CHR-042 | B43: Employee | C43: Mandatory fields | D43: Employment Type missing blocks save | E43: Logged in as HRMS admin amit (Amit Kumar Shaji, role HRMS / Administrator); on Core HR > Employee, New Employee form (/employee) open | F43: Role Group Staff, User Level Team Member, Reports To Amit Kumar Shaji, Designation SOFTWARE TESTER, Branch Main Branch, First Name, Last Name, Display Name, Date of Birth, Gender, Phone, Email, Employment Type Full Time Employee, Status Active, Joining Date minus Employment Type | G43: 1. Fill every mandatory field except Employment Type 2. Click Save | H43: Logged in as HRMS admin amit (Amit Kumar Shaji, role HRMS / Administrator); on Core HR > Employee, New Employee form (/employee) open → Fill every mandatory field except Employment Type → Click Save | I43: Save blocked; message "Please choose Employee Type."; field highlighted and scrolled into view; no employee created | J43: Validation | K43: Major | L43: High | M43: Not Automated | O43: Not Executed | R43: /employee | T43: Core HR SRS §10.2
A44: TC-CHR-043 | B44: Employee | C44: Mandatory fields | D44: Joining Date missing blocks save | E44: Logged in as HRMS admin amit (Amit Kumar Shaji, role HRMS / Administrator); on Core HR > Employee, New Employee form (/employee) open | F44: Role Group Staff, User Level Team Member, Reports To Amit Kumar Shaji, Designation SOFTWARE TESTER, Branch Main Branch, First Name, Last Name, Display Name, Date of Birth, Gender, Phone, Email, Employment Type Full Time Employee, Status Active, Joining Date minus Joining Date | G44: 1. Fill every mandatory field except Joining Date 2. Click Save | H44: Logged in as HRMS admin amit (Amit Kumar Shaji, role HRMS / Administrator); on Core HR > Employee, New Employee form (/employee) open → Fill every mandatory field except Joining Date → Click Save | I44: Save blocked; message "Please choose joining date"; field highlighted and scrolled into view; no employee created | J44: Validation | K44: Major | L44: High | M44: Not Automated | O44: Not Executed | R44: /employee | T44: Core HR SRS §10.2
A45: TC-CHR-044 | B45: Employee | C45: Mandatory fields | D45: Gender missing blocks save | E45: Logged in as HRMS admin amit (Amit Kumar Shaji, role HRMS / Administrator); on Core HR > Employee, New Employee form (/employee) open | F45: Role Group Staff, User Level Team Member, Reports To Amit Kumar Shaji, Designation SOFTWARE TESTER, Branch Main Branch, First Name, Last Name, Display Name, Date of Birth, Gender, Phone, Email, Employment Type Full Time Employee, Status Active, Joining Date minus Gender | G45: 1. Fill every mandatory field except Gender 2. Click Save | H45: Logged in as HRMS admin amit (Amit Kumar Shaji, role HRMS / Administrator); on Core HR > Employee, New Employee form (/employee) open → Fill every mandatory field except Gender → Click Save | I45: Save blocked; message "gender required"; field highlighted and scrolled into view; no employee created | J45: Validation | K45: Minor | L45: Medium | M45: Not Automated | O45: Not Executed | R45: /employee | S45: SRS lists Gender optional; live create form marks it — confirm | T45: Core HR SRS §10.2
A46: TC-CHR-045 | B46: Employee | C46: Mandatory fields | D46: Save with an empty form lists all outstanding fields | E46: Logged in as HRMS admin amit (Amit Kumar Shaji, role HRMS / Administrator); on Core HR > Employee, New Employee form (/employee) open | G46: 1. Click Save without filling anything | H46: Logged in as HRMS admin amit (Amit Kumar Shaji, role HRMS / Administrator); on Core HR > Employee, New Employee form (/employee) open → Click Save without filling anything | I46: One consolidated message lists the outstanding items; after dismissing, the page scrolls to the first missing field; required fields carry a red asterisk | J46: Validation | K46: Major | L46: High | M46: Not Automated | O46: Not Executed | R46: /employee | T46: §10.1
A47: TC-CHR-046 | B47: Employee | C47: Mandatory fields | D47: Required fields are marked with an asterisk | E47: Logged in as HRMS admin amit (Amit Kumar Shaji, role HRMS / Administrator); on Core HR > Employee, New Employee form (/employee) open | G47: 1. Inspect field labels | H47: Logged in as HRMS admin amit (Amit Kumar Shaji, role HRMS / Administrator); on Core HR > Employee, New Employee form (/employee) open → Inspect field labels | I47: Every mandatory field label shows a red * | J47: UI | K47: Trivial | L47: Low | M47: Not Automated | O47: Not Executed | R47: /employee | T47: §11.6
A48: TC-CHR-047 | B48: Employee | C48: Field validation | D48: Digits in First Name rejected | E48: Logged in as HRMS admin amit (Amit Kumar Shaji, role HRMS / Administrator); on Core HR > Employee, New Employee form (/employee) open | F48: Rohan2 | G48: 1. Enter "Rohan2" in First Name 2. Tab out 3. Save | H48: Logged in as HRMS admin amit (Amit Kumar Shaji, role HRMS / Administrator); on Core HR > Employee, New Employee form (/employee) open → Enter "Rohan2" in First Name → Tab out → Save | I48: Inline and on-save message "First Name may contain only letters." | J48: Validation | K48: Major | L48: High | M48: Not Automated | O48: Not Executed | R48: /employee | T48: §7.2
A49: TC-CHR-048 | B49: Employee | C49: Field validation | D49: Special characters in First Name rejected | E49: Logged in as HRMS admin amit (Amit Kumar Shaji, role HRMS / Administrator); on Core HR > Employee, New Employee form (/employee) open | F49: Ro@han# | G49: 1. Enter "Ro@han#" in First Name 2. Save | H49: Logged in as HRMS admin amit (Amit Kumar Shaji, role HRMS / Administrator); on Core HR > Employee, New Employee form (/employee) open → Enter "Ro@han#" in First Name → Save | I49: Save blocked with the letters-only message | J49: Validation | K49: Minor | L49: Medium | M49: Not Automated | O49: Not Executed | R49: /employee
A50: TC-CHR-049 | B50: Employee | C50: Field validation | D50: Allowed punctuation in names accepted | E50: Logged in as HRMS admin amit (Amit Kumar Shaji, role HRMS / Administrator); on Core HR > Employee, New Employee form (/employee) open | F50: Mary-Ann / D'Souza | G50: 1. Enter First Name "Mary-Ann" and Last Name "D'Souza" 2. Fill the rest 3. Save | H50: Logged in as HRMS admin amit (Amit Kumar Shaji, role HRMS / Administrator); on Core HR > Employee, New Employee form (/employee) open → Enter First Name "Mary-Ann" and Last Name "D'Souza" → Fill the rest → Save | I50: Accepted — space, dot, apostrophe and hyphen are allowed | J50: Positive | K50: Minor | L50: Low | M50: Not Automated | O50: Not Executed | R50: /employee | T50: §7.2
A51: TC-CHR-050 | B51: Employee | C51: Field validation | D51: Name must start with a letter | E51: Logged in as HRMS admin amit (Amit Kumar Shaji, role HRMS / Administrator); on Core HR > Employee, New Employee form (/employee) open | F51: .Rohan | G51: 1. Enter First Name ".Rohan" 2. Save | H51: Logged in as HRMS admin amit (Amit Kumar Shaji, role HRMS / Administrator); on Core HR > Employee, New Employee form (/employee) open → Enter First Name ".Rohan" → Save | I51: Rejected — name must start with a letter | J51: Validation | K51: Minor | L51: Low | M51: Not Automated | O51: Not Executed | R51: /employee
A52: TC-CHR-051 | B52: Employee | C52: Field validation | D52: Digits in Last Name rejected | E52: Logged in as HRMS admin amit (Amit Kumar Shaji, role HRMS / Administrator); on Core HR > Employee, New Employee form (/employee) open | F52: Nair3 | G52: 1. Enter Last Name "Nair3" 2. Save | H52: Logged in as HRMS admin amit (Amit Kumar Shaji, role HRMS / Administrator); on Core HR > Employee, New Employee form (/employee) open → Enter Last Name "Nair3" → Save | I52: Save blocked with a letters-only message for Last Name | J52: Validation | K52: Minor | L52: Medium | M52: Not Automated | O52: Not Executed | R52: /employee
A53: TC-CHR-052 | B53: Employee | C53: Field validation | D53: Digits in Display Name rejected | E53: Logged in as HRMS admin amit (Amit Kumar Shaji, role HRMS / Administrator); on Core HR > Employee, New Employee form (/employee) open | F53: Rohan V 2 | G53: 1. Enter Display Name "Rohan V 2" 2. Save | H53: Logged in as HRMS admin amit (Amit Kumar Shaji, role HRMS / Administrator); on Core HR > Employee, New Employee form (/employee) open → Enter Display Name "Rohan V 2" → Save | I53: Save blocked; Display Name follows the First Name character rule | J53: Validation | K53: Minor | L53: Medium | M53: Automated (Linear Run) | N53: Linear 001 Employee — createRunEmployee | O53: Passed (19 Oct 2026) | R53: /employee
A54: TC-CHR-053 | B54: Employee | C54: Field validation | D54: First Name max length 30 | E54: Logged in as HRMS admin amit (Amit Kumar Shaji, role HRMS / Administrator); on Core HR > Employee, New Employee form (/employee) open | F54: 30 / 31 × "a" | G54: 1. Enter 30 letters in First Name 2. Then 31 letters 3. Save each time | H54: Logged in as HRMS admin amit (Amit Kumar Shaji, role HRMS / Administrator); on Core HR > Employee, New Employee form (/employee) open → Enter 30 letters in First Name → Then 31 letters → Save each time | I54: 30 accepted; 31 blocked or truncated with a message | J54: Boundary | K54: Minor | L54: Medium | M54: Not Automated | O54: Not Executed | R54: /employee | T54: §7.2
A55: TC-CHR-054 | B55: Employee | C55: Field validation | D55: Leading/trailing spaces in names trimmed and capitalised | E55: Logged in as HRMS admin amit (Amit Kumar Shaji, role HRMS / Administrator); on Core HR > Employee, New Employee form (/employee) open | G55: 1. Enter First Name " rohan " 2. Fill rest 3. Save 4. Open profile | H55: Logged in as HRMS admin amit (Amit Kumar Shaji, role HRMS / Administrator); on Core HR > Employee, New Employee form (/employee) open → Enter First Name " rohan " → Fill rest → Save → Open profile | I55: Saved as "Rohan" — trimmed and capitalised; no error for surrounding blanks | J55: Positive | K55: Minor | L55: Low | M55: Not Automated | O55: Not Executed | R55: /employee | T55: §10.1
A56: TC-CHR-055 | B56: Employee | C56: Field validation | D56: Future Date of Birth rejected | E56: Logged in as HRMS admin amit (Amit Kumar Shaji, role HRMS / Administrator); on Core HR > Employee, New Employee form (/employee) open | F56: DOB: tomorrow | G56: 1. Enter Date of Birth tomorrow 2. Save | H56: Logged in as HRMS admin amit (Amit Kumar Shaji, role HRMS / Administrator); on Core HR > Employee, New Employee form (/employee) open → Enter Date of Birth tomorrow → Save | I56: "Date of Birth cannot be a future date." Save blocked | J56: Validation | K56: Major | L56: High | M56: Not Automated | O56: Not Executed | R56: /employee | T56: FR-CH-008
A57: TC-CHR-056 | B57: Employee | C57: Field validation | D57: Date of Birth today accepted / age 0 | E57: Logged in as HRMS admin amit (Amit Kumar Shaji, role HRMS / Administrator); on Core HR > Employee, New Employee form (/employee) open | G57: 1. Enter today as Date of Birth 2. Save | H57: Logged in as HRMS admin amit (Amit Kumar Shaji, role HRMS / Administrator); on Core HR > Employee, New Employee form (/employee) open → Enter today as Date of Birth → Save | I57: Accepted (no minimum age enforced) or blocked consistently; Age shows 0 | J57: Boundary | K57: Minor | L57: Low | M57: Not Automated | O57: Not Executed | R57: /employee | T57: §7.2
A58: TC-CHR-057 | B58: Employee | C58: Field validation | D58: Age is computed from Date of Birth | E58: Logged in as HRMS admin amit (Amit Kumar Shaji, role HRMS / Administrator); on Core HR > Employee, New Employee form (/employee) open | G58: 1. Enter Date of Birth 1995-06-15 | H58: Logged in as HRMS admin amit (Amit Kumar Shaji, role HRMS / Administrator); on Core HR > Employee, New Employee form (/employee) open → Enter Date of Birth 1995-06-15 | I58: Read-only Age shows completed years (31 on 2026-10-20) | J58: UI | K58: Trivial | L58: Low | M58: Not Automated | O58: Not Executed | R58: /employee | T58: §12.1
A59: TC-CHR-058 | B59: Employee | C59: Field validation | D59: Invalid phone format rejected | E59: Logged in as HRMS admin amit (Amit Kumar Shaji, role HRMS / Administrator); on Core HR > Employee, New Employee form (/employee) open | F59: 98abc43210 | G59: 1. Enter Phone "98abc43210" 2. Save | H59: Logged in as HRMS admin amit (Amit Kumar Shaji, role HRMS / Administrator); on Core HR > Employee, New Employee form (/employee) open → Enter Phone "98abc43210" → Save | I59: "The phone number is not valid." Save blocked | J59: Validation | K59: Major | L59: High | M59: Not Automated | O59: Not Executed | R59: /employee | T59: §10.2
A60: TC-CHR-059 | B60: Employee | C60: Field validation | D60: Phone length boundaries | E60: Logged in as HRMS admin amit (Amit Kumar Shaji, role HRMS / Administrator); on Core HR > Employee, New Employee form (/employee) open | F60: 1 / 16 / 10 digits | G60: 1. Enter a 1-digit phone 2. Save 3. Enter a 16-digit phone 4. Save 5. Enter a valid 10-digit phone | H60: Logged in as HRMS admin amit (Amit Kumar Shaji, role HRMS / Administrator); on Core HR > Employee, New Employee form (/employee) open → Enter a 1-digit phone → Save → Enter a 16-digit phone → Save → Enter a valid 10-digit phone | I60: Too short/too long rejected; 10 digits accepted (E.164 shape, max 15 digits) | J60: Boundary | K60: Minor | L60: Medium | M60: Not Automated | O60: Not Executed | R60: /employee | T60: §7.3
A61: TC-CHR-060 | B61: Employee | C61: Field validation | D61: Phone starting with 0 rejected | E61: Logged in as HRMS admin amit (Amit Kumar Shaji, role HRMS / Administrator); on Core HR > Employee, New Employee form (/employee) open | F61: 0987654321 | G61: 1. Enter Phone 0987654321 2. Save | H61: Logged in as HRMS admin amit (Amit Kumar Shaji, role HRMS / Administrator); on Core HR > Employee, New Employee form (/employee) open → Enter Phone 0987654321 → Save | I61: Rejected — first digit must be 1–9 | J61: Validation | K61: Minor | L61: Low | M61: Not Automated | O61: Not Executed | R61: /employee | T61: §7.3
A62: TC-CHR-061 | B62: Employee | C62: Field validation | D62: Invalid WhatsApp number when Same as Phone is off | E62: Logged in as HRMS admin amit (Amit Kumar Shaji, role HRMS / Administrator); on Core HR > Employee, New Employee form (/employee) open | F62: 12ab | G62: 1. Untick Same as Phone 2. Enter WhatsApp "12ab" 3. Save | H62: Logged in as HRMS admin amit (Amit Kumar Shaji, role HRMS / Administrator); on Core HR > Employee, New Employee form (/employee) open → Untick Same as Phone → Enter WhatsApp "12ab" → Save | I62: "The WhatsApp number is not valid." Save blocked | J62: Validation | K62: Minor | L62: Medium | M62: Not Automated | O62: Not Executed | R62: /employee
A63: TC-CHR-062 | B63: Employee | C63: Field validation | D63: Invalid e-mail formats rejected | E63: Logged in as HRMS admin amit (Amit Kumar Shaji, role HRMS / Administrator); on Core HR > Employee, New Employee form (/employee) open | F63: rohan@ ; rohan.example.com | G63: 1. Enter Email "rohan@" 2. Save 3. Try "rohan.example.com" 4. Save | H63: Logged in as HRMS admin amit (Amit Kumar Shaji, role HRMS / Administrator); on Core HR > Employee, New Employee form (/employee) open → Enter Email "rohan@" → Save → Try "rohan.example.com" → Save | I63: "Please provide a valid email address." Save blocked | J63: Validation | K63: Major | L63: High | M63: Not Automated | O63: Not Executed | R63: /employee
A64: TC-CHR-063 | B64: Employee | C64: Field validation | D64: Non-numeric pincode rejected | E64: Logged in as HRMS admin amit (Amit Kumar Shaji, role HRMS / Administrator); on Core HR > Employee, New Employee form (/employee) open | F64: 68A016 | G64: 1. Enter Present Pincode "68A016" 2. Save | H64: Logged in as HRMS admin amit (Amit Kumar Shaji, role HRMS / Administrator); on Core HR > Employee, New Employee form (/employee) open → Enter Present Pincode "68A016" → Save | I64: "Present address: Pincode may contain only digits." Save blocked | J64: Validation | K64: Minor | L64: Medium | M64: Not Automated | O64: Not Executed | R64: /employee | T64: §10.2
A65: TC-CHR-064 | B65: Employee | C65: Field validation | D65: Pincode longer than 10 digits | E65: Logged in as HRMS admin amit (Amit Kumar Shaji, role HRMS / Administrator); on Core HR > Employee, New Employee form (/employee) open | F65: 68201612345 | G65: 1. Enter Pincode with 11 digits 2. Save | H65: Logged in as HRMS admin amit (Amit Kumar Shaji, role HRMS / Administrator); on Core HR > Employee, New Employee form (/employee) open → Enter Pincode with 11 digits → Save | I65: Rejected or input capped at 10 characters | J65: Boundary | K65: Minor | L65: Low | M65: Not Automated | O65: Not Executed | R65: /employee
A66: TC-CHR-065 | B66: Employee | C66: Field validation | D66: Script text in address is stored as plain text | E66: Logged in as HRMS admin amit (Amit Kumar Shaji, role HRMS / Administrator); on Core HR > Employee, New Employee form (/employee) open | G66: 1. Enter Address Line 1 "<script>alert(1)</script>" 2. Save 3. Open profile | H66: Logged in as HRMS admin amit (Amit Kumar Shaji, role HRMS / Administrator); on Core HR > Employee, New Employee form (/employee) open → Enter Address Line 1 "<script>alert(1)</script>" → Save → Open profile | I66: No script executes on save or on the profile; text shown escaped | J66: Security | K66: Major | L66: Medium | M66: Not Automated | O66: Not Executed | R66: /employee
A67: TC-CHR-066 | B67: Employee | C67: Duplicates | D67: Duplicate phone rejected | E67: Logged in as HRMS admin amit (Amit Kumar Shaji, role HRMS / Administrator); on Core HR > Employee, New Employee form (/employee) open; an employee with phone 9555232501 exists | G67: 1. Fill a new employee with phone 9555232501 2. Save | H67: Logged in as HRMS admin amit (Amit Kumar Shaji, role HRMS / Administrator); on Core HR > Employee, New Employee form (/employee) open; an employee with phone 9555232501 exists → Fill a new employee with phone 9555232501 → Save | I67: "<owner> Already Exist" — nothing created | J67: Negative | K67: Major | L67: High | M67: Not Automated | O67: Not Executed | R67: /employee | T67: FR-CH-004
A68: TC-CHR-067 | B68: Employee | C68: Duplicates | D68: Duplicate phone with country code prefix rejected | E68: Logged in as HRMS admin amit (Amit Kumar Shaji, role HRMS / Administrator); on Core HR > Employee, New Employee form (/employee) open; an employee with phone 9555232501 exists | G68: 1. Enter phone 919555232501 2. Save | H68: Logged in as HRMS admin amit (Amit Kumar Shaji, role HRMS / Administrator); on Core HR > Employee, New Employee form (/employee) open; an employee with phone 9555232501 exists → Enter phone 919555232501 → Save | I68: Rejected as duplicate — comparison ignores the country code | J68: Negative | K68: Minor | L68: Medium | M68: Not Automated | O68: Not Executed | R68: /employee | T68: FR-CH-004
A69: TC-CHR-068 | B69: Employee | C69: Duplicates | D69: Duplicate e-mail rejected case-insensitively | E69: Logged in as HRMS admin amit (Amit Kumar Shaji, role HRMS / Administrator); on Core HR > Employee, New Employee form (/employee) open; employee with rohan.varghese@example.com exists | G69: 1. Enter ROHAN.VARGHESE@EXAMPLE.COM 2. Save | H69: Logged in as HRMS admin amit (Amit Kumar Shaji, role HRMS / Administrator); on Core HR > Employee, New Employee form (/employee) open; employee with rohan.varghese@example.com exists → Enter ROHAN.VARGHESE@EXAMPLE.COM → Save | I69: Rejected as duplicate e-mail | J69: Negative | K69: Major | L69: High | M69: Not Automated | O69: Not Executed | R69: /employee | T69: FR-CH-005
A70: TC-CHR-069 | B70: Employee | C70: Duplicates | D70: Duplicate login username rejected | E70: Logged in as HRMS admin amit (Amit Kumar Shaji, role HRMS / Administrator); on Core HR > Employee, New Employee form (/employee) open; username rohan.varghese already exists | G70: 1. Enter Login Username rohan.varghese 2. Save | H70: Logged in as HRMS admin amit (Amit Kumar Shaji, role HRMS / Administrator); on Core HR > Employee, New Employee form (/employee) open; username rohan.varghese already exists → Enter Login Username rohan.varghese → Save | I70: "Login Username 'rohan.varghese' already exists." nothing created | J70: Negative | K70: Major | L70: High | M70: Not Automated | O70: Not Executed | R70: /employee | T70: §10.2
A71: TC-CHR-070 | B71: Employee | C71: Duplicates | D71: Same person name allowed with different phone/e-mail | E71: Logged in as HRMS admin amit (Amit Kumar Shaji, role HRMS / Administrator); on Core HR > Employee, New Employee form (/employee) open; an employee named Rohan Varghese exists | G71: 1. Create another Rohan Varghese with unique phone, e-mail, username 2. Save | H71: Logged in as HRMS admin amit (Amit Kumar Shaji, role HRMS / Administrator); on Core HR > Employee, New Employee form (/employee) open; an employee named Rohan Varghese exists → Create another Rohan Varghese with unique phone, e-mail, username → Save | I71: Saved — names are not unique; employees are told apart by code/e-mail | J71: Positive | K71: Minor | L71: Low | M71: Not Automated | O71: Not Executed | R71: /employee
A72: TC-CHR-071 | B72: Employee | C72: Duplicates | D72: Duplicate check messages are field-specific | E72: Logged in as HRMS admin amit (Amit Kumar Shaji, role HRMS / Administrator); on Core HR > Employee, New Employee form (/employee) open | G72: 1. Enter a phone used by employee A and an e-mail used by employee B 2. Save | H72: Logged in as HRMS admin amit (Amit Kumar Shaji, role HRMS / Administrator); on Core HR > Employee, New Employee form (/employee) open → Enter a phone used by employee A and an e-mail used by employee B → Save | I72: Message identifies the clashing field(s); one clash is not masked by another | J72: Negative | K72: Minor | L72: Low | M72: Not Automated | O72: Not Executed | R72: /employee | T72: §10.3
A73: TC-CHR-072 | B73: Employee | C73: Login creation | D73: Login is created on save and shown once | E73: Logged in as HRMS admin amit (Amit Kumar Shaji, role HRMS / Administrator); on Core HR > Employee, New Employee form (/employee) open | F73: Username: rohan.varghese | G73: 1. Create a valid employee with Login Username set and Can Login ticked 2. Read the dialog | H73: Logged in as HRMS admin amit (Amit Kumar Shaji, role HRMS / Administrator); on Core HR > Employee, New Employee form (/employee) open → Create a valid employee with Login Username set and Can Login ticked → Read the dialog | I73: "Login created for <name>" dialog shows the Username and Password = the new employee code | J73: Positive | K73: Critical | L73: High | M73: Automated (Linear Run) | N73: Linear 001 Employee — createRunEmployee | O73: Passed (19 Oct 2026) | R73: /employee
A74: TC-CHR-073 | B74: Employee | C74: Login creation | D74: Employee can sign in with username + employee code | E74: An employee created with Can Login ticked | G74: 1. Log out 2. Sign in with company code pbhrms, the Login Username and the employee code as password | H74: An employee created with Can Login ticked → Log out → Sign in with company code pbhrms, the Login Username and the employee code as password | I74: Sign-in succeeds; employee lands on Home with self-service menus | J74: E2E | K74: Critical | L74: High | M74: Automated (Linear Run) | N74: Linear 056 Leave Approval — employeeAppliesManagerApproves (run employee signs in with code password) | O74: Passed (19 Oct 2026) | R74: /employee
A75: TC-CHR-074 | B75: Employee | C75: Login creation | D75: Blank Login Username defaults to the employee code | E75: Logged in as HRMS admin amit (Amit Kumar Shaji, role HRMS / Administrator); on Core HR > Employee, New Employee form (/employee) open | G75: 1. Fill mandatory fields 2. Leave Login Username empty 3. Save | H75: Logged in as HRMS admin amit (Amit Kumar Shaji, role HRMS / Administrator); on Core HR > Employee, New Employee form (/employee) open → Fill mandatory fields → Leave Login Username empty → Save | I75: Login created with username = employee code (dialog shows it) | J75: Positive | K75: Major | L75: Medium | M75: Not Automated | O75: Not Executed | R75: /employee | T75: FR-CH-006
A76: TC-CHR-075 | B76: Employee | C76: Login creation | D76: Can Login unticked creates no usable login | E76: Logged in as HRMS admin amit (Amit Kumar Shaji, role HRMS / Administrator); on Core HR > Employee, New Employee form (/employee) open | G76: 1. Fill mandatory fields 2. Untick Can Login 3. Save 4. Try signing in as that user | H76: Logged in as HRMS admin amit (Amit Kumar Shaji, role HRMS / Administrator); on Core HR > Employee, New Employee form (/employee) open → Fill mandatory fields → Untick Can Login → Save → Try signing in as that user | I76: No login dialog (or login disabled); sign-in is refused | J76: Negative | K76: Major | L76: High | M76: Not Automated | O76: Not Executed | R76: /employee
A77: TC-CHR-076 | B77: Employee | C77: Login creation | D77: Can Login is ticked by default | E77: Logged in as HRMS admin amit (Amit Kumar Shaji, role HRMS / Administrator); on Core HR > Employee, New Employee form (/employee) open | G77: 1. Choose Role Group and User Level 2. Observe Can Login | H77: Logged in as HRMS admin amit (Amit Kumar Shaji, role HRMS / Administrator); on Core HR > Employee, New Employee form (/employee) open → Choose Role Group and User Level → Observe Can Login | I77: Can Login checkbox is ticked by default | J77: UI | K77: Trivial | L77: Low | M77: Automated (Linear Run) | N77: Linear 001 Employee — createRunEmployee | O77: Passed (19 Oct 2026) | R77: /employee
A78: TC-CHR-077 | B78: Employee | C78: Login creation | D78: Role Group drives the employee's menus | E78: Employee created with Role Group Staff | G78: 1. Sign in as the employee 2. Inspect the sidebar | H78: Employee created with Role Group Staff → Sign in as the employee → Inspect the sidebar | I78: Only Staff-permitted menus (My Workspace etc.) are shown | J78: Integration | K78: Critical | L78: High | M78: Automated (Linear Run) | N78: Linear 056 Leave Approval — employeeAppliesManagerApproves (run employee signs in with code password) | O78: Passed (19 Oct 2026) | R78: /employee
A79: TC-CHR-078 | B79: Employee | C79: Login creation | D79: All Branches access checkbox | E79: Logged in as HRMS admin amit (Amit Kumar Shaji, role HRMS / Administrator); on Core HR > Employee, New Employee form (/employee) open | G79: 1. Tick All Branches 2. Save 3. Sign in as employee where branch pickers exist | H79: Logged in as HRMS admin amit (Amit Kumar Shaji, role HRMS / Administrator); on Core HR > Employee, New Employee form (/employee) open → Tick All Branches → Save → Sign in as employee where branch pickers exist | I79: Employee can see/select all branches where their role permits | J79: Positive | K79: Minor | L79: Low | M79: Automated (Linear Run) | N79: Linear 001 Employee — createRunEmployee | O79: Passed (19 Oct 2026) | R79: /employee
A80: TC-CHR-079 | B80: Employee | C80: Login creation | D80: Password is not displayed again after the dialog | E80: Logged in as HRMS admin amit (Amit Kumar Shaji, role HRMS / Administrator); employee created | G80: 1. Close the login dialog 2. Open the employee Edit form | H80: Logged in as HRMS admin amit (Amit Kumar Shaji, role HRMS / Administrator); employee created → Close the login dialog → Open the employee Edit form | I80: No password field or plain-text password is shown anywhere afterwards | J80: Security | K80: Major | L80: Medium | M80: Not Automated | O80: Not Executed | R80: /employee
A81: TC-CHR-080 | B81: Employee | C81: Login creation | D81: Login username with spaces/special characters | E81: Logged in as HRMS admin amit (Amit Kumar Shaji, role HRMS / Administrator); on Core HR > Employee, New Employee form (/employee) open | G81: 1. Enter Login Username "rohan v@#" 2. Save | H81: Logged in as HRMS admin amit (Amit Kumar Shaji, role HRMS / Administrator); on Core HR > Employee, New Employee form (/employee) open → Enter Login Username "rohan v@#" → Save | I81: Rejected with a format message, or sanitised consistently; no broken login | J81: Validation | K81: Minor | L81: Low | M81: Not Automated | O81: Not Executed | R81: /employee
A82: TC-CHR-081 | B82: Employee | C82: Reports To | D82: Reports To lists only higher-level users | E82: Logged in as HRMS admin amit (Amit Kumar Shaji, role HRMS / Administrator); on Core HR > Employee, New Employee form (/employee) open | G82: 1. Choose User Level Team Member 2. Open Reports To | H82: Logged in as HRMS admin amit (Amit Kumar Shaji, role HRMS / Administrator); on Core HR > Employee, New Employee form (/employee) open → Choose User Level Team Member → Open Reports To | I82: Options are people at a higher level (e.g. Amit Kumar Shaji); Team Members are not offered | J82: Positive | K82: Major | L82: Medium | M82: Automated (Linear Run) | N82: Linear 001 Employee — createRunEmployee | O82: Passed (19 Oct 2026) | R82: /employee | T82: FR-CH-010
A83: TC-CHR-082 | B83: Employee | C83: Reports To | D83: Top level (Administrator) does not require Reports To | E83: Logged in as HRMS admin amit (Amit Kumar Shaji, role HRMS / Administrator); on Core HR > Employee, New Employee form (/employee) open | G83: 1. Choose User Level Administrator 2. Fill other mandatory fields without Reports To 3. Save | H83: Logged in as HRMS admin amit (Amit Kumar Shaji, role HRMS / Administrator); on Core HR > Employee, New Employee form (/employee) open → Choose User Level Administrator → Fill other mandatory fields without Reports To → Save | I83: Saved — Reports To is not mandatory at the top level | J83: Positive | K83: Minor | L83: Low | M83: Not Automated | O83: Not Executed | R83: /employee | T83: FR-CH-010
A84: TC-CHR-083 | B84: Employee | C84: Reports To | D84: Changing User Level reloads Reports To | E84: Logged in as HRMS admin amit (Amit Kumar Shaji, role HRMS / Administrator); on Core HR > Employee, New Employee form (/employee) open | G84: 1. Pick User Level Team Member and a Reports To 2. Change User Level to Manager | H84: Logged in as HRMS admin amit (Amit Kumar Shaji, role HRMS / Administrator); on Core HR > Employee, New Employee form (/employee) open → Pick User Level Team Member and a Reports To → Change User Level to Manager | I84: Reports To list reloads for the new level; an invalid previous choice is cleared | J84: Negative | K84: Minor | L84: Low | M84: Not Automated | O84: Not Executed | R84: /employee
A85: TC-CHR-084 | B85: Employee | C85: Reports To | D85: Reporting manager appears in the employee's approvals chain | E85: Run employee reports to Amit; leave workflow uses Report Person | G85: 1. Employee applies for leave 2. Amit opens Leave Approval | H85: Run employee reports to Amit; leave workflow uses Report Person → Employee applies for leave → Amit opens Leave Approval | I85: The request is routed to Amit (the Reports To person) | J85: Integration | K85: Critical | L85: High | M85: Automated (Linear Run) | N85: Linear 056 Leave Approval — employeeAppliesManagerApproves | O85: Passed (19 Oct 2026) | R85: /employee
A86: TC-CHR-085 | B86: Employee Profile | C86: Profile view | D86: Profile opens with the read-only tab strip | E86: Logged in as HRMS admin amit (Amit Kumar Shaji, role HRMS / Administrator); run employee exists | G86: 1. Open the run employee from the list or Worker Directory | H86: Logged in as HRMS admin amit (Amit Kumar Shaji, role HRMS / Administrator); run employee exists → Open the run employee from the list or Worker Directory | I86: /employee-view/<guid> shows tabs Basic Details, Address, Bank Details, Documents, Emergency, History, Lifecycle, Probation, Salary History, Background Verification, Attendance History, Leave History; Edit button at top | J86: UI | K86: Major | L86: High | M86: Automated (Linear Run) | N86: Linear 002 Worker Directory — findRunEmployeeAndCompleteProfile | O86: Passed (19 Oct 2026) | R86: /employee-view/<guid>
A87: TC-CHR-086 | B87: Employee Profile | C87: Profile view | D87: Basic Details shows saved values | E87: Logged in as HRMS admin amit (Amit Kumar Shaji, role HRMS / Administrator); profile completed | G87: 1. Open the profile 2. Read the Basic Details panel | H87: Logged in as HRMS admin amit (Amit Kumar Shaji, role HRMS / Administrator); profile completed → Open the profile → Read the Basic Details panel | I87: Name, code, designation, branch, department, Blood Group and Nationality match what was saved | J87: Positive | K87: Critical | L87: High | M87: Automated (Linear Run) | N87: Linear 002 Worker Directory — findRunEmployeeAndCompleteProfile | O87: Passed (19 Oct 2026) | R87: /employee-view/<guid>
A88: TC-CHR-087 | B88: Employee Profile | C88: Profile view | D88: Profile is read-only | E88: Logged in as HRMS admin amit (Amit Kumar Shaji, role HRMS / Administrator) | G88: 1. Open each profile tab | H88: Logged in as HRMS admin amit (Amit Kumar Shaji, role HRMS / Administrator) → Open each profile tab | I88: No Add/Upload/Edit controls in any tab panel; only the top Edit button leads to the editor | J88: Positive | K88: Major | L88: Medium | M88: Not Automated | O88: Not Executed | R88: /employee-view/<guid> | S88: Verified 2026-09-12
A89: TC-CHR-088 | B89: Employee Profile | C89: Profile view | D89: Route uses GUID, not internal id | E89: Logged in as HRMS admin amit (Amit Kumar Shaji, role HRMS / Administrator) | G89: 1. Open a profile 2. Inspect the URL | H89: Logged in as HRMS admin amit (Amit Kumar Shaji, role HRMS / Administrator) → Open a profile → Inspect the URL | I89: URL is /employee-view/<36-char GUID>; no sequential numeric id exposed | J89: Security | K89: Major | L89: Medium | M89: Not Automated | O89: Not Executed | R89: /employee-view/<guid> | T89: FR-CH-027
A90: TC-CHR-089 | B90: Employee Profile | C90: Profile view | D90: Address tab shows present and permanent address | E90: Logged in as HRMS admin amit (Amit Kumar Shaji, role HRMS / Administrator); address saved | G90: 1. Open Address tab | H90: Logged in as HRMS admin amit (Amit Kumar Shaji, role HRMS / Administrator); address saved → Open Address tab | I90: Both addresses shown with country/state/city/pincode/lines | J90: Positive | K90: Minor | L90: Low | M90: Not Automated | O90: Not Executed | R90: /employee-view/<guid>
A91: TC-CHR-090 | B91: Employee Profile | C91: Profile view | D91: History / Lifecycle timeline shows changes newest first | E91: Logged in as HRMS admin amit (Amit Kumar Shaji, role HRMS / Administrator); department was changed via Edit | G91: 1. Open History and Lifecycle tabs | H91: Logged in as HRMS admin amit (Amit Kumar Shaji, role HRMS / Administrator); department was changed via Edit → Open History and Lifecycle tabs | I91: Events (Joined, Department Change, etc.) shown with date, old → new value, acting user; newest first; no add/edit/delete | J91: Positive | K91: Major | L91: Medium | M91: Not Automated | O91: Not Executed | R91: /employee-view/<guid> | T91: §4.8
A92: TC-CHR-091 | B92: Employee Profile | C92: Profile view | D92: Leave History reflects approved leave | E92: Run employee has an approved leave | G92: 1. Open Leave History tab | H92: Run employee has an approved leave → Open Leave History tab | I92: Approved leave appears with type, dates and status | J92: Integration | K92: Major | L92: Medium | M92: Not Automated | O92: Not Executed | R92: /employee-view/<guid>
A93: TC-CHR-092 | B93: Employee Profile | C93: Profile view | D93: Salary History is read-only projection | E93: Logged in as HRMS admin amit (Amit Kumar Shaji, role HRMS / Administrator); employee has a salary structure | G93: 1. Open Salary History tab | H93: Logged in as HRMS admin amit (Amit Kumar Shaji, role HRMS / Administrator); employee has a salary structure → Open Salary History tab | I93: Current structure and revisions listed read-only | J93: Integration | K93: Minor | L93: Low | M93: Not Automated | O93: Not Executed | R93: /employee-view/<guid> | S93: Payroll owned by teammates
A94: TC-CHR-093 | B94: Employee Profile | C94: Profile view | D94: Documents tab summarises ID proofs | E94: Employee has uploaded a document via ESS | G94: 1. Open Documents tab | H94: Employee has uploaded a document via ESS → Open Documents tab | I94: Document type, number (masked if applicable), expiry and verification state shown read-only | J94: Integration | K94: Minor | L94: Low | M94: Not Automated | O94: Not Executed | R94: /employee-view/<guid>
A95: TC-CHR-094 | B95: Employee Profile | C95: Profile view | D95: Edit button opens /employee/<guid> | E95: Logged in as HRMS admin amit (Amit Kumar Shaji, role HRMS / Administrator) | G95: 1. Click Edit on the profile | H95: Logged in as HRMS admin amit (Amit Kumar Shaji, role HRMS / Administrator) → Click Edit on the profile | I95: Edit form opens for the same GUID pre-filled | J95: Positive | K95: Critical | L95: High | M95: Automated (Linear Run) | N95: Linear 002 Worker Directory — findRunEmployeeAndCompleteProfile | O95: Passed (19 Oct 2026) | R95: /employee-view/<guid>
A96: TC-CHR-095 | B96: Employee Profile | C96: Profile view | D96: Invalid GUID shows not-found | E96: Logged in as HRMS admin amit (Amit Kumar Shaji, role HRMS / Administrator) | G96: 1. Open /employee-view/00000000-0000-0000-0000-000000000000 | H96: Logged in as HRMS admin amit (Amit Kumar Shaji, role HRMS / Administrator) → Open /employee-view/00000000-0000-0000-0000-000000000000 | I96: Friendly not found / empty message; no unhandled error | J96: Negative | K96: Minor | L96: Low | M96: Not Automated | O96: Not Executed | R96: /employee-view/<guid>
A97: TC-CHR-096 | B97: Employee Edit | C97: Edit profile | D97: Complete profile: department, blood group, nationality, honorific, address | E97: Logged in as HRMS admin amit (Amit Kumar Shaji, role HRMS / Administrator); run employee Edit form open (/employee/<guid>) | F97: Dept Testing; O+; India; 682016; 2nd Floor, QA Towers; MG Road | G97: 1. Set Department Testing 2. Set Honorific 3. Set Nationality India 4. Set Blood Group O+ 5. Fill Present Pincode and Address Line 1/2 6. Save 7. Open the profile | H97: Logged in as HRMS admin amit (Amit Kumar Shaji, role HRMS / Administrator); run employee Edit form open (/employee/<guid>) → Set Department Testing → Set Honorific → Set Nationality India → Set Blood Group O+ → Fill Present Pincode and Address Line 1/2 → Save → Open the profile | I97: Saved; profile Basic Details shows Blood Group O+ and Nationality India; Address shows the lines | J97: Positive | K97: Critical | L97: High | M97: Automated (Linear Run) | N97: Linear 002 Worker Directory — findRunEmployeeAndCompleteProfile | O97: Passed (19 Oct 2026) | R97: /employee/<guid>
A98: TC-CHR-097 | B98: Employee Edit | C98: Edit profile | D98: Edit form is pre-filled with saved values | E98: Logged in as HRMS admin amit (Amit Kumar Shaji, role HRMS / Administrator); run employee Edit form open (/employee/<guid>) | G98: 1. Open the Edit form | H98: Logged in as HRMS admin amit (Amit Kumar Shaji, role HRMS / Administrator); run employee Edit form open (/employee/<guid>) → Open the Edit form | I98: First name, code, phone, e-mail, designation, branch etc. are pre-filled | J98: Positive | K98: Critical | L98: High | M98: Automated (Linear Run) | N98: Linear 002 Worker Directory — findRunEmployeeAndCompleteProfile | O98: Passed (19 Oct 2026) | R98: /employee/<guid>
A99: TC-CHR-098 | B99: Employee Edit | C99: Edit profile | D99: Blood Group offers only valid values | E99: Logged in as HRMS admin amit (Amit Kumar Shaji, role HRMS / Administrator); run employee Edit form open (/employee/<guid>) | G99: 1. Open Blood Group | H99: Logged in as HRMS admin amit (Amit Kumar Shaji, role HRMS / Administrator); run employee Edit form open (/employee/<guid>) → Open Blood Group | I99: Options A+, A-, B+, B-, AB+, AB-, O+, O- | J99: UI | K99: Trivial | L99: Low | M99: Not Automated | O99: Not Executed | R99: /employee/<guid> | T99: §7.2
A100: TC-CHR-099 | B100: Employee Edit | C100: Edit profile | D100: Department list loads on the Edit form | E100: Logged in as HRMS admin amit (Amit Kumar Shaji, role HRMS / Administrator); run employee Edit form open (/employee/<guid>) | G100: 1. Open Department | H100: Logged in as HRMS admin amit (Amit Kumar Shaji, role HRMS / Administrator); run employee Edit form open (/employee/<guid>) → Open Department | I100: Departments of the tenant listed (DIGITAL MARKETING, Finance and Accounts, Human Resources, SEO, SOFTWARE DEVELOPMENT, Testing …) | J100: UI | K100: Minor | L100: Medium | M100: Automated (Linear Run) | N100: Linear 002 Worker Directory — findRunEmployeeAndCompleteProfile | O100: Passed (19 Oct 2026) | R100: /employee/<guid>
...

Sheet Recruitment
A1: Test ID | B1: Page / Sub-module | C1: Scenario | D1: Description | E1: Preconditions | F1: Test Data | G1: Test Steps | H1: Steps to Reproduce | I1: Expected Result | J1: Type | K1: Severity | L1: Priority | M1: Automation Status | N1: Automation Reference | O1: Execution Status | P1: Actual Result | Q1: Tested By / Date | R1: Route | S1: Remarks | T1: SRS Ref
A2: TC-REC-001 | B2: Job Requisitions | C2: Page load | D2: Job Requisitions page opens and renders correctly | E2: Logged in as HRMS admin (amit); Departments, Designations and Branches exist | G2: 1. Open Recruitment > Job Requisitions 2. Wait for the loading indicator to clear 3. Observe heading, toolbar and table | H2: Logged in as HRMS admin (amit); Departments, Designations and Branches exist → Open Recruitment > Job Requisitions → Wait for the loading indicator to clear → Observe heading, toolbar and table | I2: Page loads without login redirect, 404 or app error; heading shown; New Requisition button, "Search designation..." box, Requested By filter, page-size selector (10/25/50/100) and requisitions table with REQUESTED ON column render | J2: UI | K2: Major | L2: High | M2: Automated (Page Check) | N2: Linear 012 Job Requisitions — page check | O2: Passed (19 Oct 2026) | R2: /requisition-list
A3: TC-REC-002 | B3: Job Requisitions | C3: Page load | D3: Requisition list shows the expected columns | E3: Logged in as HRMS admin (amit); Departments, Designations and Branches exist | G3: 1. Open Job Requisitions 2. Inspect the table header 3. Compare the screen with the expected result | H3: Logged in as HRMS admin (amit); Departments, Designations and Branches exist → Open Job Requisitions → Inspect the table header → Compare the screen with the expected result | I3: Columns Sl.No, Designation, Department, Positions, Request Type, Status, Action (and REQUESTED ON) are displayed | J3: UI | K3: Trivial | L3: Low | M3: Not Automated | O3: Not Executed | R3: /requisition-list | T3: Tester Ed. S1
A4: TC-REC-003 | B4: Job Requisitions | C4: Create requisition | D4: Raise a requisition with all mandatory fields and submit it | E4: Logged in as HRMS admin (amit); Departments, Designations and Branches exist | F4: Department: SOFTWARE DEVELOPMENT; Designation: SOFTWARE TESTER; Branch: Main Branch; Positions: 1; Employee Type: Full Time Employee; Work Type: Office; Justification: "Additional Software Tester for Q4 delivery (Auto DD-Mon HH.MM.SS)" | G4: 1. Click New Requisition 2. Select Department, then Designation (cascade) 3. Select Branch, enter Positions, select Employee Type and Work Type 4. Enter Business Justification 5. Click Submit 6. If "Requisition Already Exists" appears, click "Yes, raise it anyway" | H4: Logged in as HRMS admin (amit); Departments, Designations and Branches exist → Click New Requisition → Select Department, then Designation (cascade) → Select Branch, enter Positions, select Employee Type and Work Type → Enter Business Justification → Click Submit → If "Requisition Already Exists" appears, click "Yes, raise it anyway" | I4: Form closes; requisition listed with status Submitted (or Approved when no workflow is configured); justification visible as tooltip on the row | J4: Positive | K4: Critical | L4: High | M4: Automated (Linear Run) | N4: Linear 012 Job Requisitions — raiseAndApproveRequisition | O4: Passed (19 Oct 2026) | R4: /requisition-list | T4: FR-REC-001..006
A5: TC-REC-004 | B5: Job Requisitions | C5: Create requisition | D5: Raise a requisition with all fields filled | E5: Logged in as HRMS admin (amit); Departments, Designations and Branches exist | F5: Salary 50000–80000; Expected Joining: today+30; Skills: Selenium, Playwright, API testing | G5: 1. Click New Requisition 2. Fill Department, Designation, Branch, Positions, Request Type = New Position, Employee Type, Work Type 3. Enter Salary Range From/To, Expected Joining Date (+30 days), Required Skills, Business Justification 4. Click Submit | H5: Logged in as HRMS admin (amit); Departments, Designations and Branches exist → Click New Requisition → Fill Department, Designation, Branch, Positions, Request Type = New Position, Employee Type, Work Type → Enter Salary Range From/To, Expected Joining Date (+30 days), Required Skills, Business Justification → Click Submit | I5: Requisition saved; all entered values shown in the row View popup exactly as entered | J5: Positive | K5: Major | L5: Medium | M5: Not Automated | O5: Not Executed | R5: /requisition-list | T5: FR-REC-003
A6: TC-REC-005 | B6: Job Requisitions | C6: Create requisition | D6: Save a requisition as Draft | E6: Logged in as HRMS admin (amit); Departments, Designations and Branches exist | G6: 1. Click New Requisition 2. Fill all mandatory fields 3. Click Save Draft | H6: Logged in as HRMS admin (amit); Departments, Designations and Branches exist → Click New Requisition → Fill all mandatory fields → Click Save Draft | I6: Message "Requisition saved as draft"; row listed with status Draft; Edit and Submit-for-approval icons available | J6: Positive | K6: Major | L6: Medium | M6: Not Automated | O6: Not Executed | R6: /requisition-list | T6: FR-REC-006
A7: TC-REC-006 | B7: Job Requisitions | C7: Create requisition | D7: Designation dropdown is disabled until a Department is chosen | E7: Logged in as HRMS admin (amit); Departments, Designations and Branches exist | G7: 1. Click New Requisition 2. Observe Designation before choosing a Department 3. Choose Department SOFTWARE DEVELOPMENT | H7: Logged in as HRMS admin (amit); Departments, Designations and Branches exist → Click New Requisition → Observe Designation before choosing a Department → Choose Department SOFTWARE DEVELOPMENT | I7: Designation is disabled showing "-- Choose --" until a Department is picked; then it lists only that department's designations | J7: UI | K7: Minor | L7: Medium | M7: Not Automated | O7: Not Executed | R7: /requisition-list
A8: TC-REC-007 | B8: Job Requisitions | C8: Create requisition | D8: Changing Department resets the selected Designation | E8: Logged in as HRMS admin (amit); Departments, Designations and Branches exist | G8: 1. Click New Requisition 2. Pick Department and Designation 3. Change Department to Human Resources | H8: Logged in as HRMS admin (amit); Departments, Designations and Branches exist → Click New Requisition → Pick Department and Designation → Change Department to Human Resources | I8: Designation is cleared and reloaded with the new department's designations; stale designation cannot be submitted | J8: Validation | K8: Minor | L8: Low | M8: Not Automated | O8: Not Executed | R8: /requisition-list
A9: TC-REC-008 | B9: Job Requisitions | C9: Create requisition | D9: Duplicate requisition for the same role asks for confirmation | E9: Logged in as HRMS admin (amit); Departments, Designations and Branches exist | G9: 1. Raise a requisition for SOFTWARE TESTER / SOFTWARE DEVELOPMENT / Main Branch 2. Raise another identical requisition 3. Click Submit | H9: Logged in as HRMS admin (amit); Departments, Designations and Branches exist → Raise a requisition for SOFTWARE TESTER / SOFTWARE DEVELOPMENT / Main Branch → Raise another identical requisition → Click Submit | I9: SweetAlert "Requisition Already Exists" appears offering "Yes, raise it anyway"; nothing is saved until confirmed | J9: Negative | K9: Major | L9: High | M9: Automated (Linear Run) | N9: Linear 012 Job Requisitions — raiseAndApproveRequisition | O9: Passed (19 Oct 2026) | R9: /requisition-list | S9: Proven app behaviour: duplicate role prompts "raise it anyway"
A10: TC-REC-009 | B10: Job Requisitions | C10: Create requisition | D10: Cancel the duplicate-requisition prompt | E10: Logged in as HRMS admin (amit); Departments, Designations and Branches exist | G10: 1. Open Recruitment > Job Requisitions 2. Trigger the "Requisition Already Exists" prompt 3. Click Cancel / No | H10: Logged in as HRMS admin (amit); Departments, Designations and Branches exist → Open Recruitment > Job Requisitions → Trigger the "Requisition Already Exists" prompt → Click Cancel / No | I10: Prompt closes; no second requisition is created; form stays open with entered values | J10: Negative | K10: Minor | L10: Medium | M10: Not Automated | O10: Not Executed | R10: /requisition-list
A11: TC-REC-010 | B11: Job Requisitions | C11: Create requisition | D11: Replacement request type requires Employee Being Replaced | E11: Logged in as HRMS admin (amit); Departments, Designations and Branches exist | G11: 1. Click New Requisition 2. Set Request Type = Replacement 3. Leave Employee Being Replaced empty 4. Fill other mandatory fields and Submit | H11: Logged in as HRMS admin (amit); Departments, Designations and Branches exist → Click New Requisition → Set Request Type = Replacement → Leave Employee Being Replaced empty → Fill other mandatory fields and Submit | I11: Employee Being Replaced field appears and is mandatory; submit blocked with a validation message | J11: Validation | K11: Minor | L11: Medium | M11: Not Automated | O11: Not Executed | R11: /requisition-list | T11: FR-REC-001
A12: TC-REC-011 | B12: Job Requisitions | C12: Mandatory field validation | D12: Submit requisition without Department | E12: Logged in as HRMS admin (amit); Departments, Designations and Branches exist | G12: 1. Click New Requisition 2. Fill every mandatory field except Department 3. Click Submit | H12: Logged in as HRMS admin (amit); Departments, Designations and Branches exist → Click New Requisition → Fill every mandatory field except Department → Click Submit | I12: Submit blocked; message "Please select a Department"; field highlighted; no record created | J12: Validation | K12: Major | L12: High | M12: Not Automated | O12: Not Executed | R12: /requisition-list | T12: Tester Ed. 8.1
A13: TC-REC-012 | B13: Job Requisitions | C13: Mandatory field validation | D13: Submit requisition without Designation | E13: Logged in as HRMS admin (amit); Departments, Designations and Branches exist | G13: 1. Click New Requisition 2. Fill every mandatory field except Designation 3. Click Submit | H13: Logged in as HRMS admin (amit); Departments, Designations and Branches exist → Click New Requisition → Fill every mandatory field except Designation → Click Submit | I13: Submit blocked; message "Please select a Designation"; field highlighted; no record created | J13: Validation | K13: Major | L13: High | M13: Not Automated | O13: Not Executed | R13: /requisition-list | T13: Tester Ed. 8.1
A14: TC-REC-013 | B14: Job Requisitions | C14: Mandatory field validation | D14: Submit requisition without Branch | E14: Logged in as HRMS admin (amit); Departments, Designations and Branches exist | G14: 1. Click New Requisition 2. Fill every mandatory field except Branch 3. Click Submit | H14: Logged in as HRMS admin (amit); Departments, Designations and Branches exist → Click New Requisition → Fill every mandatory field except Branch → Click Submit | I14: Submit blocked; message "Please select a Branch"; field highlighted; no record created | J14: Validation | K14: Major | L14: High | M14: Not Automated | O14: Not Executed | R14: /requisition-list | T14: Tester Ed. 8.1
A15: TC-REC-014 | B15: Job Requisitions | C15: Mandatory field validation | D15: Submit requisition without Employee Type | E15: Logged in as HRMS admin (amit); Departments, Designations and Branches exist | G15: 1. Click New Requisition 2. Fill every mandatory field except Employee Type 3. Click Submit | H15: Logged in as HRMS admin (amit); Departments, Designations and Branches exist → Click New Requisition → Fill every mandatory field except Employee Type → Click Submit | I15: Submit blocked; message "Please select an Employment Type"; field highlighted; no record created | J15: Validation | K15: Major | L15: High | M15: Not Automated | O15: Not Executed | R15: /requisition-list | T15: Tester Ed. 8.1
A16: TC-REC-015 | B16: Job Requisitions | C16: Mandatory field validation | D16: Submit requisition without Work Type | E16: Logged in as HRMS admin (amit); Departments, Designations and Branches exist | G16: 1. Click New Requisition 2. Fill every mandatory field except Work Type 3. Click Submit | H16: Logged in as HRMS admin (amit); Departments, Designations and Branches exist → Click New Requisition → Fill every mandatory field except Work Type → Click Submit | I16: Submit blocked; message "Please select a Work Type"; field highlighted; no record created | J16: Validation | K16: Major | L16: High | M16: Not Automated | O16: Not Executed | R16: /requisition-list | T16: Tester Ed. 8.1
A17: TC-REC-016 | B17: Job Requisitions | C17: Mandatory field validation | D17: Submit requisition with Positions blank | E17: Logged in as HRMS admin (amit); Departments, Designations and Branches exist | G17: 1. Click New Requisition 2. Fill all mandatory fields, clear Positions 3. Click Submit | H17: Logged in as HRMS admin (amit); Departments, Designations and Branches exist → Click New Requisition → Fill all mandatory fields, clear Positions → Click Submit | I17: Message "Positions is required."; not saved | J17: Validation | K17: Major | L17: High | M17: Not Automated | O17: Not Executed | R17: /requisition-list | T17: Tester Ed. 8.1
A18: TC-REC-017 | B18: Job Requisitions | C18: Mandatory field validation | D18: Submit an empty requisition form | E18: Logged in as HRMS admin (amit); Departments, Designations and Branches exist | G18: 1. Open Recruitment > Job Requisitions 2. Click New Requisition 3. Click Submit without entering anything | H18: Logged in as HRMS admin (amit); Departments, Designations and Branches exist → Open Recruitment > Job Requisitions → Click New Requisition → Click Submit without entering anything | I18: All mandatory fields (Department, Designation, Branch, Positions, Employee Type, Work Type) flagged; nothing saved | J18: Validation | K18: Minor | L18: Medium | M18: Not Automated | O18: Not Executed | R18: /requisition-list
A19: TC-REC-018 | B19: Job Requisitions | C19: Field limits | D19: Positions = 0 is rejected | E19: Logged in as HRMS admin (amit); Departments, Designations and Branches exist | F19: Positions: 0 | G19: 1. Open New Requisition 2. Enter Positions 0 with other mandatory fields 3. Submit | H19: Logged in as HRMS admin (amit); Departments, Designations and Branches exist → Open New Requisition → Enter Positions 0 with other mandatory fields → Submit | I19: Message "Positions must be at least 1." | J19: Boundary | K19: Major | L19: High | M19: Not Automated | O19: Not Executed | R19: /requisition-list | T19: FR-REC-002
A20: TC-REC-019 | B20: Job Requisitions | C20: Field limits | D20: Negative Positions is rejected | E20: Logged in as HRMS admin (amit); Departments, Designations and Branches exist | F20: Positions: -5 | G20: 1. Open New Requisition 2. Enter Positions -5 3. Submit | H20: Logged in as HRMS admin (amit); Departments, Designations and Branches exist → Open New Requisition → Enter Positions -5 → Submit | I20: Message "Positions cannot be negative. Enter a value between 1 and 9,999." | J20: Boundary | K20: Minor | L20: Medium | M20: Not Automated | O20: Not Executed | R20: /requisition-list
A21: TC-REC-020 | B21: Job Requisitions | C21: Field limits | D21: Positions = 10000 is rejected | E21: Logged in as HRMS admin (amit); Departments, Designations and Branches exist | F21: Positions: 10000 | G21: 1. Open New Requisition 2. Enter Positions 10000 3. Submit | H21: Logged in as HRMS admin (amit); Departments, Designations and Branches exist → Open New Requisition → Enter Positions 10000 → Submit | I21: Message "Positions cannot exceed 9,999." | J21: Boundary | K21: Minor | L21: Medium | M21: Not Automated | O21: Not Executed | R21: /requisition-list
A22: TC-REC-021 | B22: Job Requisitions | C22: Field limits | D22: Positions boundary values 1 and 9999 are accepted | E22: Logged in as HRMS admin (amit); Departments, Designations and Branches exist | F22: Positions: 1, 9999 | G22: 1. Raise a requisition with Positions 1 2. Raise another with Positions 9999 3. Compare the screen with the expected result | H22: Logged in as HRMS admin (amit); Departments, Designations and Branches exist → Raise a requisition with Positions 1 → Raise another with Positions 9999 → Compare the screen with the expected result | I22: Both requisitions save successfully | J22: Boundary | K22: Minor | L22: Medium | M22: Not Automated | O22: Not Executed | R22: /requisition-list
A23: TC-REC-022 | B23: Job Requisitions | C23: Field limits | D23: Decimal or text Positions is not accepted | E23: Logged in as HRMS admin (amit); Departments, Designations and Branches exist | F23: 1.5, abc | G23: 1. Open New Requisition 2. Type 1.5 then "abc" in Positions 3. Submit | H23: Logged in as HRMS admin (amit); Departments, Designations and Branches exist → Open New Requisition → Type 1.5 then "abc" in Positions → Submit | I23: Field accepts integers only; 1.5 rejected / letters cannot be typed | J23: Boundary | K23: Minor | L23: Low | M23: Not Automated | O23: Not Executed | R23: /requisition-list
A24: TC-REC-023 | B24: Job Requisitions | C24: Field limits | D24: Negative salary is rejected | E24: Logged in as HRMS admin (amit); Departments, Designations and Branches exist | F24: Salary From: -1 | G24: 1. Open New Requisition 2. Enter Salary Range From -1 3. Submit | H24: Logged in as HRMS admin (amit); Departments, Designations and Branches exist → Open New Requisition → Enter Salary Range From -1 → Submit | I24: Message "Salary cannot be negative" | J24: Validation | K24: Minor | L24: Medium | M24: Not Automated | O24: Not Executed | R24: /requisition-list
A25: TC-REC-024 | B25: Job Requisitions | C25: Field limits | D25: Salary Range To lower than From is rejected | E25: Logged in as HRMS admin (amit); Departments, Designations and Branches exist | F25: From 80000, To 50000 | G25: 1. Open New Requisition 2. Enter Salary From 80000 and To 50000 3. Submit | H25: Logged in as HRMS admin (amit); Departments, Designations and Branches exist → Open New Requisition → Enter Salary From 80000 and To 50000 → Submit | I25: Message "Salary Range To must be greater than or equal to From" | J25: Validation | K25: Minor | L25: Medium | M25: Not Automated | O25: Not Executed | R25: /requisition-list
A26: TC-REC-025 | B26: Job Requisitions | C26: Field limits | D26: Expected Joining Date in the past is rejected | E26: Logged in as HRMS admin (amit); Departments, Designations and Branches exist | F26: Expected Joining: today-1 | G26: 1. Open New Requisition 2. Set Expected Joining Date to yesterday 3. Submit | H26: Logged in as HRMS admin (amit); Departments, Designations and Branches exist → Open New Requisition → Set Expected Joining Date to yesterday → Submit | I26: Message "Expected Joining Date cannot be in the past" | J26: Validation | K26: Minor | L26: Medium | M26: Not Automated | O26: Not Executed | R26: /requisition-list
A27: TC-REC-026 | B27: Job Requisitions | C27: Field limits | D27: Business Justification accepts long text and special characters | E27: Logged in as HRMS admin (amit); Departments, Designations and Branches exist | F27: 1000-char text with <b>tags</b> & quotes | G27: 1. Open New Requisition 2. Enter 1000 characters incl. & < > " ' in Business Justification 3. Submit | H27: Logged in as HRMS admin (amit); Departments, Designations and Branches exist → Open New Requisition → Enter 1000 characters incl. & < > " ' in Business Justification → Submit | I27: Saved; text shown escaped (no HTML injection) in the tooltip/View | J27: Boundary | K27: Minor | L27: Low | M27: Not Automated | O27: Not Executed | R27: /requisition-list
A28: TC-REC-027 | B28: Job Requisitions | C28: Edit / view / delete | D28: Edit a Draft requisition | E28: Logged in as HRMS admin (amit); Departments, Designations and Branches exist | G28: 1. Click Edit on a Draft row 2. Change Positions from 1 to 2 3. Save | H28: Logged in as HRMS admin (amit); Departments, Designations and Branches exist → Click Edit on a Draft row → Change Positions from 1 to 2 → Save | I28: Changes saved; row shows Positions 2 | J28: Positive | K28: Major | L28: Medium | M28: Not Automated | O28: Not Executed | R28: /requisition-list
A29: TC-REC-028 | B29: Job Requisitions | C29: Edit / view / delete | D29: Submitted or Approved requisition cannot be edited | E29: Logged in as HRMS admin (amit); Departments, Designations and Branches exist | G29: 1. Open Recruitment > Job Requisitions 2. Locate a Submitted or Approved requisition 3. Try Edit | H29: Logged in as HRMS admin (amit); Departments, Designations and Branches exist → Open Recruitment > Job Requisitions → Locate a Submitted or Approved requisition → Try Edit | I29: Edit hidden/blocked; message "A submitted or approved requisition cannot be edited." | J29: Negative | K29: Major | L29: High | M29: Not Automated | O29: Not Executed | R29: /requisition-list | T29: Tester Ed. 8.1
A30: TC-REC-029 | B30: Job Requisitions | C30: Edit / view / delete | D30: View a requisition read-only | E30: Logged in as HRMS admin (amit); Departments, Designations and Branches exist | G30: 1. Open Recruitment > Job Requisitions 2. Click the View icon on any row 3. Compare the screen with the expected result | H30: Logged in as HRMS admin (amit); Departments, Designations and Branches exist → Open Recruitment > Job Requisitions → Click the View icon on any row → Compare the screen with the expected result | I30: Read-only popup shows all requisition fields; no editable inputs | J30: Positive | K30: Minor | L30: Low | M30: Not Automated | O30: Not Executed | R30: /requisition-list
A31: TC-REC-030 | B31: Job Requisitions | C31: Edit / view / delete | D31: Delete a Draft requisition with confirmation | E31: Logged in as HRMS admin (amit); Departments, Designations and Branches exist | G31: 1. Open Recruitment > Job Requisitions 2. Click Delete on a Draft row 3. Confirm "Delete this requisition?" | H31: Logged in as HRMS admin (amit); Departments, Designations and Branches exist → Open Recruitment > Job Requisitions → Click Delete on a Draft row → Confirm "Delete this requisition?" | I31: Row removed from the list; success message shown | J31: Positive | K31: Major | L31: Medium | M31: Not Automated | O31: Not Executed | R31: /requisition-list
A32: TC-REC-031 | B32: Job Requisitions | C32: Edit / view / delete | D32: Cancel requisition delete | E32: Logged in as HRMS admin (amit); Departments, Designations and Branches exist | G32: 1. Open Recruitment > Job Requisitions 2. Click Delete on a Draft row 3. Click Cancel in the confirmation | H32: Logged in as HRMS admin (amit); Departments, Designations and Branches exist → Open Recruitment > Job Requisitions → Click Delete on a Draft row → Click Cancel in the confirmation | I32: Dialog closes; requisition remains | J32: Negative | K32: Minor | L32: Low | M32: Not Automated | O32: Not Executed | R32: /requisition-list
A33: TC-REC-032 | B33: Job Requisitions | C33: Edit / view / delete | D33: Approval trail popup shows the approval history | E33: Logged in as HRMS admin (amit); Departments, Designations and Branches exist | G33: 1. Open Recruitment > Job Requisitions 2. Click the Approval trail icon on an Approved / Rejected row 3. Compare the screen with the expected result | H33: Logged in as HRMS admin (amit); Departments, Designations and Branches exist → Open Recruitment > Job Requisitions → Click the Approval trail icon on an Approved / Rejected row → Compare the screen with the expected result | I33: Trail lists each level, approver, decision, remarks and date; Rejected rows read "Rejection reason / approval trail" | J33: Positive | K33: Major | L33: Medium | M33: Not Automated | O33: Not Executed | R33: /requisition-list | T33: FR-REC-010
A34: TC-REC-033 | B34: Job Requisitions | C34: Approval workflow | D34: Approved requisition shows Approved and auto-creates a job opening | E34: Logged in as HRMS admin (amit); Departments, Designations and Branches exist | G34: 1. Raise a requisition 2. Approve it in My Approvals (Confirm Approval) 3. Return to Job Requisitions 4. Open Job Board | H34: Logged in as HRMS admin (amit); Departments, Designations and Branches exist → Raise a requisition → Approve it in My Approvals (Confirm Approval) → Return to Job Requisitions → Open Job Board | I34: Requisition status Approved (with Job Code once the opening exists); a new opening for the designation is created on Job Board | J34: Integration | K34: Critical | L34: High | M34: Automated (Linear Run) | N34: Linear 012 Job Requisitions — raiseAndApproveRequisition | O34: Passed (19 Oct 2026) | R34: /requisition-list | T34: FR-REC-012
A35: TC-REC-034 | B35: Job Requisitions | C35: Approval workflow | D35: Re-submitting an unchanged rejected requisition is blocked | E35: Logged in as HRMS admin (amit); Departments, Designations and Branches exist | G35: 1. Have a requisition rejected in My Approvals 2. Re-submit it without changes 3. Compare the screen with the expected result | H35: Logged in as HRMS admin (amit); Departments, Designations and Branches exist → Have a requisition rejected in My Approvals → Re-submit it without changes → Compare the screen with the expected result | I35: Message "This requisition was rejected. Please update it based on the rejection reason before submitting it again." | J35: Negative | K35: Major | L35: High | M35: Not Automated | O35: Not Executed | R35: /requisition-list | T35: BR-REQ-05
A36: TC-REC-035 | B36: Job Requisitions | C36: Approval workflow | D36: Rejected requisition re-submits after an edit | E36: Logged in as HRMS admin (amit); Departments, Designations and Branches exist | G36: 1. Edit the rejected requisition (Positions 2→3) 2. Save 3. Submit for approval | H36: Logged in as HRMS admin (amit); Departments, Designations and Branches exist → Edit the rejected requisition (Positions 2→3) → Save → Submit for approval | I36: Accepted; status Submitted again; appears in approver queue | J36: Positive | K36: Major | L36: Medium | M36: Not Automated | O36: Not Executed | R36: /requisition-list
A37: TC-REC-036 | B37: Job Requisitions | C37: Approval workflow | D37: Submit for approval only on Draft/Rejected/Returned rows | E37: Logged in as HRMS admin (amit); Departments, Designations and Branches exist | G37: 1. Open Recruitment > Job Requisitions 2. Inspect the Action icons on Draft, Submitted and Approved rows 3. Compare the screen with the expected result | H37: Logged in as HRMS admin (amit); Departments, Designations and Branches exist → Open Recruitment > Job Requisitions → Inspect the Action icons on Draft, Submitted and Approved rows → Compare the screen with the expected result | I37: Submit-for-approval icon shown only on Draft / Rejected / Returned rows | J37: UI | K37: Trivial | L37: Low | M37: Not Automated | O37: Not Executed | R37: /requisition-list
A38: TC-REC-037 | B38: Job Requisitions | C38: List operations | D38: Search requisitions by designation | E38: Logged in as HRMS admin (amit); Departments, Designations and Branches exist | G38: 1. Open Recruitment > Job Requisitions 2. Type "SOFTWARE TESTER" in "Search designation..." 3. Compare the screen with the expected result | H38: Logged in as HRMS admin (amit); Departments, Designations and Branches exist → Open Recruitment > Job Requisitions → Type "SOFTWARE TESTER" in "Search designation..." → Compare the screen with the expected result | I38: Only matching requisitions are listed | J38: Positive | K38: Major | L38: Medium | M38: Not Automated | O38: Not Executed | R38: /requisition-list
A39: TC-REC-038 | B39: Job Requisitions | C39: List operations | D39: Search with no match shows empty state | E39: Logged in as HRMS admin (amit); Departments, Designations and Branches exist | G39: 1. Open Recruitment > Job Requisitions 2. Search "zzzz-no-such-role" 3. Compare the screen with the expected result | H39: Logged in as HRMS admin (amit); Departments, Designations and Branches exist → Open Recruitment > Job Requisitions → Search "zzzz-no-such-role" → Compare the screen with the expected result | I39: Table shows a "no records" empty state; no error | J39: Negative | K39: Minor | L39: Low | M39: Not Automated | O39: Not Executed | R39: /requisition-list
A40: TC-REC-039 | B40: Job Requisitions | C40: List operations | D40: Filter by Requested By | E40: Logged in as HRMS admin (amit); Departments, Designations and Branches exist | G40: 1. Open Recruitment > Job Requisitions 2. Type "Amit" in the Requested By filter 3. Compare the screen with the expected result | H40: Logged in as HRMS admin (amit); Departments, Designations and Branches exist → Open Recruitment > Job Requisitions → Type "Amit" in the Requested By filter → Compare the screen with the expected result | I40: Only requisitions raised by Amit are listed | J40: Positive | K40: Minor | L40: Low | M40: Not Automated | O40: Not Executed | R40: /requisition-list
A41: TC-REC-040 | B41: Job Requisitions | C41: List operations | D41: Filter by Department / Branch / Work Type / Status and Clear All | E41: Logged in as HRMS admin (amit); Departments, Designations and Branches exist | G41: 1. Open filters 2. Pick Department, Branch, Work Type, Status = Approved 3. Apply Filters 4. Clear All | H41: Logged in as HRMS admin (amit); Departments, Designations and Branches exist → Open filters → Pick Department, Branch, Work Type, Status = Approved → Apply Filters → Clear All | I41: List narrows to matches; Clear All restores the full list | J41: Positive | K41: Major | L41: Medium | M41: Not Automated | O41: Not Executed | R41: /requisition-list | T41: Tester Ed. S1
A42: TC-REC-041 | B42: Job Requisitions | C42: List operations | D42: Sort by REQUESTED ON | E42: Logged in as HRMS admin (amit); Departments, Designations and Branches exist | G42: 1. Open Recruitment > Job Requisitions 2. Click REQUESTED ON header twice 3. Compare the screen with the expected result | H42: Logged in as HRMS admin (amit); Departments, Designations and Branches exist → Open Recruitment > Job Requisitions → Click REQUESTED ON header twice → Compare the screen with the expected result | I42: Rows sort ascending then descending by request date | J42: UI | K42: Trivial | L42: Low | M42: Not Automated | O42: Not Executed | R42: /requisition-list
A43: TC-REC-042 | B43: Job Requisitions | C43: List operations | D43: Change page size and paginate | E43: Logged in as HRMS admin (amit); Departments, Designations and Branches exist | G43: 1. Open Recruitment > Job Requisitions 2. Set page size 25, then 100 3. Use the pager | H43: Logged in as HRMS admin (amit); Departments, Designations and Branches exist → Open Recruitment > Job Requisitions → Set page size 25, then 100 → Use the pager | I43: Row count follows the page size; pager navigates correctly | J43: UI | K43: Trivial | L43: Low | M43: Not Automated | O43: Not Executed | R43: /requisition-list
A44: TC-REC-043 | B44: Job Requisitions | C44: Permissions | D44: Staff user cannot access Job Requisitions | E44: A test-created Staff employee with login exists | G44: 1. Log in as a Staff employee (test-created, password = employee code) 2. Look for Recruitment > Job Requisitions 3. Open /requisition-list directly | H44: A test-created Staff employee with login exists → Log in as a Staff employee (test-created, password = employee code) → Look for Recruitment > Job Requisitions → Open /requisition-list directly | I44: Menu item hidden; direct URL refused / access denied | J44: Permission | K44: Major | L44: High | M44: Not Automated | O44: Not Executed | R44: /requisition-list | T44: Tester Ed. 9.2
A45: TC-REC-044 | B45: Job Requisitions | C45: Permissions | D45: Logged-out user is redirected to login | E45: Not logged in | G45: 1. Log out 2. Open https://hrms-test.progbiz.in/requisition-list 3. Compare the screen with the expected result | H45: Not logged in → Log out → Open https://hrms-test.progbiz.in/requisition-list → Compare the screen with the expected result | I45: Redirected to the login page; no data shown | J45: Security | K45: Critical | L45: High | M45: Not Automated | O45: Not Executed | R45: /requisition-list
A46: TC-REC-045 | B46: Job Requisitions | C46: Permissions | D46: Read-only role sees no New Requisition / Edit / Delete | E46: Read-only recruitment role user exists | G46: 1. Log in as a user with JobRequisition Has Access only 2. Open Job Requisitions 3. Compare the screen with the expected result | H46: Read-only recruitment role user exists → Log in as a user with JobRequisition Has Access only → Open Job Requisitions → Compare the screen with the expected result | I46: List visible; New Requisition button and Edit/Delete icons absent | J46: Permission | K46: Major | L46: Medium | M46: Not Automated | O46: Not Executed | R46: /requisition-list | T46: P-01
A47: TC-REC-046 | B47: Job Board | C47: Page load | D47: Job Board page opens and renders correctly | E47: Logged in as HRMS admin (amit); designation SOFTWARE TESTER exists | G47: 1. Open Recruitment > Job Board 2. Wait for loading to clear 3. Compare the screen with the expected result | H47: Logged in as HRMS admin (amit); designation SOFTWARE TESTER exists → Open Recruitment > Job Board → Wait for loading to clear → Compare the screen with the expected result | I47: Page loads; Job Openings / Candidates / Talent Pools tab strip, Add Job Opening, Refresh, Open public career page and Copy Indeed XML feed icons, table with JOB CODE, JOB OPENING, CREATED ON, Candidates, Hiring Lead, Status, Action | J47: UI | K47: Major | L47: High | M47: Automated (Page Check) | N47: Linear 013 Job Board — page check | O47: Passed (19 Oct 2026) | R47: /vacancy-list
A48: TC-REC-047 | B48: Job Board | C48: Page load | D48: Tab strip navigates between Job Openings, Candidates and Talent Pools | E48: Logged in as HRMS admin (amit); designation SOFTWARE TESTER exists | G48: 1. On Job Board click Candidates 2. Click Talent Pools 3. Click Job Openings | H48: Logged in as HRMS admin (amit); designation SOFTWARE TESTER exists → On Job Board click Candidates → Click Talent Pools → Click Job Openings | I48: Each tab navigates (/recruitment-candidates, /talent-pool, /vacancy-list); the current tab is highlighted and inert | J48: UI | K48: Minor | L48: Medium | M48: Not Automated | O48: Not Executed | R48: /vacancy-list | T48: Tester Ed. T1
A49: TC-REC-048 | B49: Job Board | C49: Create job opening | D49: Create a job opening with all mandatory fields | E49: Logged in as HRMS admin (amit); designation SOFTWARE TESTER exists | F49: SOFTWARE TESTER; FullTime; SOFTWARE DEVELOPMENT; Open; Office; Main Branch; Vacancies 1 | G49: 1. Click Add Job Opening 2. Select Designation, Employment Type, Department, Status = Open, Work Type, Branch 3. Enter Number of Vacancies 4. Click Save | H49: Logged in as HRMS admin (amit); designation SOFTWARE TESTER exists → Click Add Job Opening → Select Designation, Employment Type, Department, Status = Open, Work Type, Branch → Enter Number of Vacancies → Click Save | I49: Success message; opening listed with a new JOBnnnn code, status Open, not yet published | J49: Positive | K49: Critical | L49: High | M49: Automated (Linear Run) | N49: Linear 013 Job Board — openingAndCandidate | O49: Passed (19 Oct 2026) | R49: /vacancy-list
A50: TC-REC-049 | B50: Job Board | C50: Create job opening | D50: Create a job opening with all fields incl. salary range and Vacancy Type | E50: Logged in as HRMS admin (amit); designation SOFTWARE TESTER exists | G50: 1. Click Add Job Opening 2. Fill all mandatory fields 3. Enter Salary Range From 300000 / To 600000, Vacancy Type = New Position 4. Save 5. Open the row View popup | H50: Logged in as HRMS admin (amit); designation SOFTWARE TESTER exists → Click Add Job Opening → Fill all mandatory fields → Enter Salary Range From 300000 / To 600000, Vacancy Type = New Position → Save → Open the row View popup | I50: Saved; detail popup shows Salary Range, Opening Type, Department, Branch, Work Type, Employment Type as entered | J50: Positive | K50: Major | L50: Medium | M50: Not Automated | O50: Not Executed | R50: /vacancy-list
A51: TC-REC-050 | B51: Job Board | C51: Create job opening | D51: Create a job opening as Draft | E51: Logged in as HRMS admin (amit); designation SOFTWARE TESTER exists | G51: 1. Click Add Job Opening 2. Fill mandatory fields with Status = Draft 3. Save | H51: Logged in as HRMS admin (amit); designation SOFTWARE TESTER exists → Click Add Job Opening → Fill mandatory fields with Status = Draft → Save | I51: Opening saved as Draft; row menu does NOT offer Publish (must be moved to Open first) | J51: Positive | K51: Major | L51: Medium | M51: Not Automated | O51: Not Executed | R51: /vacancy-list | S51: Intended behaviour per SRS N-02 | T51: N-02
A52: TC-REC-051 | B52: Job Board | C52: Create job opening | D52: Save job opening without Designation | E52: Logged in as HRMS admin (amit); designation SOFTWARE TESTER exists | G52: 1. Click Add Job Opening 2. Fill all mandatory fields except Designation 3. Click Save | H52: Logged in as HRMS admin (amit); designation SOFTWARE TESTER exists → Click Add Job Opening → Fill all mandatory fields except Designation → Click Save | I52: Save blocked; Designation flagged as required; no opening created | J52: Validation | K52: Major | L52: High | M52: Not Automated | O52: Not Executed | R52: /vacancy-list
A53: TC-REC-052 | B53: Job Board | C53: Create job opening | D53: Save job opening without Employment Type | E53: Logged in as HRMS admin (amit); designation SOFTWARE TESTER exists | G53: 1. Click Add Job Opening 2. Fill all mandatory fields except Employment Type 3. Click Save | H53: Logged in as HRMS admin (amit); designation SOFTWARE TESTER exists → Click Add Job Opening → Fill all mandatory fields except Employment Type → Click Save | I53: Save blocked; Employment Type flagged as required; no opening created | J53: Validation | K53: Minor | L53: Medium | M53: Not Automated | O53: Not Executed | R53: /vacancy-list
A54: TC-REC-053 | B54: Job Board | C54: Create job opening | D54: Save job opening without Department | E54: Logged in as HRMS admin (amit); designation SOFTWARE TESTER exists | G54: 1. Click Add Job Opening 2. Fill all mandatory fields except Department 3. Click Save | H54: Logged in as HRMS admin (amit); designation SOFTWARE TESTER exists → Click Add Job Opening → Fill all mandatory fields except Department → Click Save | I54: Save blocked; Department flagged as required; no opening created | J54: Validation | K54: Minor | L54: Medium | M54: Not Automated | O54: Not Executed | R54: /vacancy-list
A55: TC-REC-054 | B55: Job Board | C55: Create job opening | D55: Save job opening without Status | E55: Logged in as HRMS admin (amit); designation SOFTWARE TESTER exists | G55: 1. Click Add Job Opening 2. Fill all mandatory fields except Status 3. Click Save | H55: Logged in as HRMS admin (amit); designation SOFTWARE TESTER exists → Click Add Job Opening → Fill all mandatory fields except Status → Click Save | I55: Save blocked; Status flagged as required; no opening created | J55: Validation | K55: Minor | L55: Medium | M55: Not Automated | O55: Not Executed | R55: /vacancy-list
A56: TC-REC-055 | B56: Job Board | C56: Create job opening | D56: Save job opening without Work Type | E56: Logged in as HRMS admin (amit); designation SOFTWARE TESTER exists | G56: 1. Click Add Job Opening 2. Fill all mandatory fields except Work Type 3. Click Save | H56: Logged in as HRMS admin (amit); designation SOFTWARE TESTER exists → Click Add Job Opening → Fill all mandatory fields except Work Type → Click Save | I56: Save blocked; Work Type flagged as required; no opening created | J56: Validation | K56: Minor | L56: Medium | M56: Not Automated | O56: Not Executed | R56: /vacancy-list
A57: TC-REC-056 | B57: Job Board | C57: Create job opening | D57: Save job opening without Branch | E57: Logged in as HRMS admin (amit); designation SOFTWARE TESTER exists | G57: 1. Click Add Job Opening 2. Fill all mandatory fields except Branch 3. Click Save | H57: Logged in as HRMS admin (amit); designation SOFTWARE TESTER exists → Click Add Job Opening → Fill all mandatory fields except Branch → Click Save | I57: Save blocked; Branch flagged as required; no opening created | J57: Validation | K57: Minor | L57: Medium | M57: Not Automated | O57: Not Executed | R57: /vacancy-list
A58: TC-REC-057 | B58: Job Board | C58: Create job opening | D58: Save job opening without Number of Vacancies | E58: Logged in as HRMS admin (amit); designation SOFTWARE TESTER exists | G58: 1. Click Add Job Opening 2. Fill all mandatory fields except Number of Vacancies 3. Click Save | H58: Logged in as HRMS admin (amit); designation SOFTWARE TESTER exists → Click Add Job Opening → Fill all mandatory fields except Number of Vacancies → Click Save | I58: Save blocked; Number of Vacancies flagged as required; no opening created | J58: Validation | K58: Minor | L58: Medium | M58: Not Automated | O58: Not Executed | R58: /vacancy-list
A59: TC-REC-058 | B59: Job Board | C59: Create job opening | D59: Number of Vacancies 0 or negative is rejected | E59: Logged in as HRMS admin (amit); designation SOFTWARE TESTER exists | F59: 0, -1 | G59: 1. Click Add Job Opening 2. Enter Vacancies 0, then -1 3. Save | H59: Logged in as HRMS admin (amit); designation SOFTWARE TESTER exists → Click Add Job Opening → Enter Vacancies 0, then -1 → Save | I59: Validation message; not saved | J59: Boundary | K59: Minor | L59: Medium | M59: Not Automated | O59: Not Executed | R59: /vacancy-list
A60: TC-REC-059 | B60: Job Board | C60: Create job opening | D60: Salary Range To lower than From is rejected on an opening | E60: Logged in as HRMS admin (amit); designation SOFTWARE TESTER exists | G60: 1. Add Job Opening 2. Salary From 600000, To 300000 3. Save | H60: Logged in as HRMS admin (amit); designation SOFTWARE TESTER exists → Add Job Opening → Salary From 600000, To 300000 → Save | I60: Validation "Salary Range To must be greater than or equal to From"; not saved | J60: Validation | K60: Minor | L60: Medium | M60: Not Automated | O60: Not Executed | R60: /vacancy-list | T60: FR-REC-017
A61: TC-REC-060 | B61: Job Board | C61: Create job opening | D61: Negative salary on an opening is rejected | E61: Logged in as HRMS admin (amit); designation SOFTWARE TESTER exists | G61: 1. Add Job Opening 2. Salary From -100 3. Save | H61: Logged in as HRMS admin (amit); designation SOFTWARE TESTER exists → Add Job Opening → Salary From -100 → Save | I61: Validation error; not saved | J61: Validation | K61: Minor | L61: Low | M61: Not Automated | O61: Not Executed | R61: /vacancy-list
A62: TC-REC-061 | B62: Job Board | C62: Create job opening | D62: Job Code is unique and sequential | E62: Logged in as HRMS admin (amit); designation SOFTWARE TESTER exists | G62: 1. Create two openings one after another 2. Compare their JOB codes 3. Compare the screen with the expected result | H62: Logged in as HRMS admin (amit); designation SOFTWARE TESTER exists → Create two openings one after another → Compare their JOB codes → Compare the screen with the expected result | I62: Each opening gets a distinct JOBnnnn code, the second higher than the first | J62: Positive | K62: Minor | L62: Low | M62: Not Automated | O62: Not Executed | R62: /vacancy-list | T62: SRS 10.3
A63: TC-REC-062 | B63: Job Board | C63: Edit / view | D63: View opening detail popup | E63: Logged in as HRMS admin (amit); designation SOFTWARE TESTER exists | G63: 1. Open Recruitment > Job Board 2. Click the View icon on an opening 3. Compare the screen with the expected result | H63: Logged in as HRMS admin (amit); designation SOFTWARE TESTER exists → Open Recruitment > Job Board → Click the View icon on an opening → Compare the screen with the expected result | I63: Popup shows Department, Branch, Work Type, Employment Type, Salary Range, Created/Published/Closed On, Applications, Hiring Team, application-form settings; buttons View N application(s), Edit, Close | J63: Positive | K63: Major | L63: Medium | M63: Not Automated | O63: Not Executed | R63: /vacancy-list
A64: TC-REC-063 | B64: Job Board | C64: Edit / view | D64: Edit an opening (Draft to Open) | E64: Logged in as HRMS admin (amit); designation SOFTWARE TESTER exists | G64: 1. Open a Draft opening 2. Edit 3. Change Status to Open 4. Save | H64: Logged in as HRMS admin (amit); designation SOFTWARE TESTER exists → Open a Draft opening → Edit → Change Status to Open → Save | I64: Status Open; Publish now available in the row menu | J64: Positive | K64: Major | L64: Medium | M64: Not Automated | O64: Not Executed | R64: /vacancy-list
A65: TC-REC-064 | B65: Job Board | C65: Edit / view | D65: "View N application(s)" opens the applications for the opening | E65: Logged in as HRMS admin (amit); designation SOFTWARE TESTER exists | G65: 1. Open Recruitment > Job Board 2. Open the detail popup of an opening with applicants 3. Click View N application(s) | H65: Logged in as HRMS admin (amit); designation SOFTWARE TESTER exists → Open Recruitment > Job Board → Open the detail popup of an opening with applicants → Click View N application(s) | I65: Job Applications for that opening are shown | J65: Integration | K65: Minor | L65: Low | M65: Not Automated | O65: Not Executed | R65: /vacancy-list
A66: TC-REC-065 | B66: Job Board | C66: Publish lifecycle | D66: Publish an Open opening | E66: Logged in as HRMS admin (amit); designation SOFTWARE TESTER exists | G66: 1. Open the row menu (⋮) of an Open opening 2. Click Publish 3. Confirm "Publish this opening for applications?" | H66: Logged in as HRMS admin (amit); designation SOFTWARE TESTER exists → Open the row menu (⋮) of an Open opening → Click Publish → Confirm "Publish this opening for applications?" | I66: Message "Opening published"; status/badge shows Published; opening appears on the public career page | J66: Positive | K66: Critical | L66: High | M66: Automated (Linear Run) | N66: Linear 013 Job Board — openingAndCandidate | O66: Passed (19 Oct 2026) | R66: /vacancy-list | T66: FR-REC-017
A67: TC-REC-066 | B67: Job Board | C67: Publish lifecycle | D67: Close a published opening | E67: Logged in as HRMS admin (amit); designation SOFTWARE TESTER exists | G67: 1. Open Recruitment > Job Board 2. Row menu > Close 3. Confirm the "Close this opening?…" dialog | H67: Logged in as HRMS admin (amit); designation SOFTWARE TESTER exists → Open Recruitment > Job Board → Row menu > Close → Confirm the "Close this opening?…" dialog | I67: Message "Opening closed"; opening removed from the career page; its public link stops accepting applications | J67: Positive | K67: Critical | L67: High | M67: Not Automated | O67: Not Executed | R67: /vacancy-list | T67: Tester Ed. S2
A68: TC-REC-067 | B68: Job Board | C68: Publish lifecycle | D68: Reopen a closed opening | E68: Logged in as HRMS admin (amit); designation SOFTWARE TESTER exists | G68: 1. Open Recruitment > Job Board 2. Row menu > Reopen on a closed opening 3. Confirm | H68: Logged in as HRMS admin (amit); designation SOFTWARE TESTER exists → Open Recruitment > Job Board → Row menu > Reopen on a closed opening → Confirm | I68: Message "Opening reopened"; opening published back to the careers page | J68: Positive | K68: Major | L68: Medium | M68: Not Automated | O68: Not Executed | R68: /vacancy-list
A69: TC-REC-068 | B69: Job Board | C69: Publish lifecycle | D69: Archive an opening | E69: Logged in as HRMS admin (amit); designation SOFTWARE TESTER exists | G69: 1. Open Recruitment > Job Board 2. Row menu > Archive 3. Confirm "Archive this opening?" | H69: Logged in as HRMS admin (amit); designation SOFTWARE TESTER exists → Open Recruitment > Job Board → Row menu > Archive → Confirm "Archive this opening?" | I69: Message "Opening archived"; opening hidden from the default status filter | J69: Positive | K69: Minor | L69: Low | M69: Not Automated | O69: Not Executed | R69: /vacancy-list
A70: TC-REC-069 | B70: Job Board | C70: Publish lifecycle | D70: Cancel the Publish confirmation | E70: Logged in as HRMS admin (amit); designation SOFTWARE TESTER exists | G70: 1. Open Recruitment > Job Board 2. Row menu > Publish 3. Click Cancel | H70: Logged in as HRMS admin (amit); designation SOFTWARE TESTER exists → Open Recruitment > Job Board → Row menu > Publish → Click Cancel | I70: Opening stays unpublished | J70: Negative | K70: Minor | L70: Low | M70: Not Automated | O70: Not Executed | R70: /vacancy-list
A71: TC-REC-070 | B71: Job Board | C71: Publish lifecycle | D71: Delete an opening with confirmation | E71: Logged in as HRMS admin (amit); designation SOFTWARE TESTER exists | G71: 1. Open Recruitment > Job Board 2. Row menu > Delete on an opening with no applications 3. Confirm | H71: Logged in as HRMS admin (amit); designation SOFTWARE TESTER exists → Open Recruitment > Job Board → Row menu > Delete on an opening with no applications → Confirm | I71: Opening removed from the list | J71: Positive | K71: Minor | L71: Low | M71: Not Automated | O71: Not Executed | R71: /vacancy-list
A72: TC-REC-071 | B72: Job Board | C72: Public links | D72: Open public career page from the Job Board | E72: Logged in as HRMS admin (amit); designation SOFTWARE TESTER exists | G72: 1. Open Recruitment > Job Board 2. Click the "Open public career page" icon 3. Compare the screen with the expected result | H72: Logged in as HRMS admin (amit); designation SOFTWARE TESTER exists → Open Recruitment > Job Board → Click the "Open public career page" icon → Compare the screen with the expected result | I72: A new tab opens /careers/<tenant-guid> showing "Join Our Team" and published openings | J72: Integration | K72: Critical | L72: High | M72: Automated (Linear Run) | N72: Linear 014 Job Applications — candidateSelfApplies | O72: Passed (19 Oct 2026) | R72: /vacancy-list
A73: TC-REC-072 | B73: Job Board | C73: Public links | D73: Copy public job link of a published opening | E73: Logged in as HRMS admin (amit); designation SOFTWARE TESTER exists | G73: 1. Open Recruitment > Job Board 2. Row menu > Copy public job link on a published opening 3. Paste the link in a private window | H73: Logged in as HRMS admin (amit); designation SOFTWARE TESTER exists → Open Recruitment > Job Board → Row menu > Copy public job link on a published opening → Paste the link in a private window | I73: Link copied (confirmation toast); it opens the Apply Now form for that opening without login | J73: Positive | K73: Major | L73: Medium | M73: Not Automated | O73: Not Executed | R73: /vacancy-list
A74: TC-REC-073 | B74: Job Board | C74: Public links | D74: Copy Indeed XML feed URL | E74: Logged in as HRMS admin (amit); designation SOFTWARE TESTER exists | G74: 1. Open Recruitment > Job Board 2. Click "Copy Indeed XML feed URL" 3. Open the copied URL | H74: Logged in as HRMS admin (amit); designation SOFTWARE TESTER exists → Open Recruitment > Job Board → Click "Copy Indeed XML feed URL" → Open the copied URL | I74: URL copied; it returns XML listing published openings | J74: Positive | K74: Minor | L74: Low | M74: Not Automated | O74: Not Executed | R74: /vacancy-list | T74: FR-REC-018
